Workbook

Sheet Summary
B2: Registered Pesticides Database — Bangladesh (up to 81st PTAC Meeting)
B4: Total Registered Products | D4: Crop-Pest Recommendations | G4: Unique Common Names | I4: Registration Holders
B5: 5452 | D5: 7250 | G5: 441 | I5: 879
B7: Products by Category
B8: Category | C8: Common Names | D8: Registered Products | E8: Recommendations
B9: Miticide | C9: 8 | D9: =COUNTA(Miticide!E5:E209) -> 205 | E9: =SUM(Miticide!L5:L209) -> 314
B10: Fungicide | C10: 103 | D10: =COUNTA(Fungicide!E5:E1056) -> 1052 | E10: =SUM(Fungicide!L5:L1056) -> 1543
B11: Insecticide | C11: 160 | D11: =COUNTA(Insecticide!E5:E2504) -> 2500 | E11: =SUM(Insecticide!L5:L2504) -> 3589
B12: Herbicide | C12: 68 | D12: =COUNTA(Herbicide!E5:E896) -> 892 | E12: =SUM(Herbicide!L5:L896) -> 984
B13: Store Grain Insecticide | C13: 3 | D13: =COUNTA('Store Grain Insecticide'!E5:E92) -> 88 | E13: =SUM('Store Grain Insecticide'!L5:L92) -> 91
B14: Rodenticide | C14: 2 | D14: =COUNTA(Rodenticide!E5:E19) -> 15 | E14: =SUM(Rodenticide!L5:L19) -> 15
B15: Bio Pesticide | C15: 20 | D15: =COUNTA('Bio Pesticide'!E5:E39) -> 35 | E15: =SUM('Bio Pesticide'!L5:L39) -> 42
B16: Public Health | C16: 77 | D16: =COUNTA('Public Health'!E5:E669) -> 665 | E16: =SUM('Public Health'!K5:K669) -> 672
B17: Total | C17: =SUM(C9:C16) -> 441 | D17: =SUM(D9:D16) -> 5452 | E17: =SUM(E9:E16) -> 7250
D18: =D17-D16 -> 4787
B20: Top 10 Registration Holders
B21: Companies/agencies with the most registered products
B22: # | C22: Name | D22: Products
B23: 1 | C23: ACI Formulations Limited | D23: 115
B24: 2 | C24: Haychem (Bangladesh) Limited | D24: 101
B25: 3 | C25: Sun Seed Pesticides | D25: 76
B26: 4 | C26: Intefa | D26: 62
B27: 5 | C27: Mimpex Agrochemicals Limited | D27: 61
B28: 6 | C28: Auto Crop Care Limited | D28: 59
B29: 7 | C29: McDonald Bangladesh (Pvt) Limited | D29: 58
B30: 8 | C30: Mamun Agro Products Ltd. | D30: 58
B31: 9 | C31: Valent Tech Limited | D31: 56
B32: 10 | C32: Bangladesh Agricultural Industries | D32: 53
B34: Top 10 Recommended Crops
B35: Crops with the most registered products (agricultural categories)
B36: # | C36: Name | D36: Products
B37: 1 | C37: Rice | D37: 1659
B38: 2 | C38: Tea | D38: 1598
B39: 3 | C39: Potato | D39: 473
B40: 4 | C40: Jute | D40: 420
B41: 5 | C41: Mango | D41: 391
B42: 6 | C42: Brinjal | D42: 281
B43: 7 | C43: Cotton | D43: 226
B44: 8 | C44: Tomato | D44: 204
B45: 9 | C45: Bean | D45: 153
B46: 10 | C46: Sugarcane | D46: 148
B48: Top 10 Target Pests
B49: Pests/weeds with the most registered products (all categories)
B50: # | C50: Name | D50: Products
B51: 1 | C51: BPH | D51: 820
B52: 2 | C52: Aphid | D52: 459
B53: 3 | C53: Mosquito | D53: 405
B54: 4 | C54: Helopeltis | D54: 310
B55: 5 | C55: Powdery mildew | D55: 289
B56: 6 | C56: Late blight | D56: 267
B57: 7 | C57: Hopper | D57: 247
B58: 8 | C58: Termite | D58: 240
B59: 9 | C59: Anthracnose | D59: 154
B60: 10 | C60: Hairy caterpillar | D60: 152
B62: Registration Number Types
B63: Prefix | C63: Meaning | D63: Products
B64: AP | C64: Agricultural Pesticide registration | D64: 4752
B65: AP (Bio) | C65: Agricultural Bio-Pesticide registration | D65: 35
B66: PHP | C66: Public Health Pesticide registration | D66: 664
B67: Missing | C67: No registration number printed in source | D67: 1
B69: Note: a few source registration numbers contain typographical variants (e.g. "AP--3368", "A-3375", "AP- 612"); they are counted under AP. See the README sheet for the full list.

Sheet README
B2: README — Registered Pesticides Database of Bangladesh
B4: About This Database
B5: Database | C5: Registered Pesticides of Bangladesh — approved up to the 81st Pesticide Technical Advisory Committee (PTAC) Meeting
B6: Issuing authority | C6: Department of Agricultural Extension (DAE), Ministry of Agriculture, Government of the People's Republic of Bangladesh
B7: Source page | C7: https://dae.gov.bd/pages/files/6922da2a933eb65569e02d1e (page title: "নিবন্ধিত বালাইনাশক" — Registered Pesticides, last updated 4 February 2024)
B8: Source document | C8: https://objectstorage.ap-dcc-gazipur-1.oraclecloud15.com/n/axvjbnqprylg/b/V2Ministry/o/office-dae/2024/12/7ad5aab9257b4eafbf8e15157f9bef18.pdf
B9: Extraction date | C9: 2026-09-15
B10: Scope | C10: 5,452 registered products (brands) across 8 categories, covering 7,247+ crop-pest recommendations, 441 unique common names (active ingredients/groups) and 879 registration holders
B12: Sheet Guide
B13: Summary | C13: Overview: totals by category, top registration holders, top crops and pests, registration number types, and a category chart
B14: Miticide / Fungicide / Insecticide / Herbicide / Store Grain Insecticide / Rodenticide / Bio Pesticide | C14: Agricultural pesticide categories — one row per registered product (brand)
B15: Public Health | C15: Household/public-health pesticide products (mosquito coils, aerosols, repellents, baits) — one row per registered product; no "Crops" column
B16: Review | C16: Self-check sheet: live formulas cross-check record counts against the source extraction; all rows should show PASS
B18: Column Definitions
B19: SL No (Common Name) | C19: Serial number of the common-name group within its category, as printed in the source list
B20: Common Name | C20: Chemical common name / active-ingredient group. In the source, this cell is merged across all products of the group, so it is repeated on every product row of that group here
B21: SL No (Products) | C21: Serial number of the product (brand) within its common-name group
B22: Brand Name | C22: Trade name of the registered product, including its formulation (e.g. "Taba 25WDG")
B23: Registration No | C23: Registration number printed in the source: AP-#### (agricultural), AP (Bio)-## (bio-pesticide), PHP-### (public health)
B24: Registration Holder | C24: Company or agency holding the registration
B25: Recommended Crops | C25: Crops for which the product is recommended (agricultural sheets only); multiple values are comma-separated
B26: Recommended Pests | C26: Target pests, diseases or weeds; multiple values are comma-separated
B27: Dosage Rate | C27: Distinct dosage rates, semicolon-separated (dosages may repeat across recommendations; see next column for the pairing)
B28: Recommendations (Crop | Pest | Dosage) | C28: One line per recommendation as printed in the source; a "-" marks a field left blank in the source
B29: No. of Recommendations | C29: Number of crop-pest(-dosage) lines printed for this product in the source
B31: How the Data Was Reconstructed
B32: Method | C32: The 189-page source PDF was parsed table-by-table with cell-level extraction (pdfplumber). Where the source table used merged cells, values were reconstructed as follows.
B33: Merged common names | C33: The common name (and its serial) is printed only on the first row of each group in the source; it was forward-filled to all products of the same group
B34: Merged recommendations | C34: When a recommendation line repeated the crop or pest of the line above (vertically merged cells), the missing field was inherited from the previous line; when the dosage cell was merged, the previous dosage applies
B35: Multi-line cells | C35: Where one cell contained several lines (e.g. two dosage lines), they were zipped into separate recommendations when the line counts aligned
B36: One row per product | C36: Each output row is one registered product (brand). All of its crop-pest-dosage lines are kept in the "Recommendations" column and summarised in the Crops / Pests / Dosage columns
B38: Data Quality Notes (source quirks, kept as printed)
B39: Typo registrations | C39: A few registration numbers contain source typos and are kept verbatim: "AP5615" (Nurzeb 80WP), "A-3375" (Abin 85WP), "AP--3368" (Umate 40EC), "AP--2277" (AP-Tap 57%), "AAP-4833" (Mita 33EC), "AP- 612" (Nuben 72WP), "PHP508" (Hit Super Mosquito Coil)
B40: Missing registrations | C40: One product (Golder Aerosol, S N Trade International, Public Health) has no registration number printed in the source
B41: Duplicate registrations | C41: 14 registration numbers are each assigned to two different products in the source (e.g. AP-3612 for both Gonder 50WP and Rosa 72SL); both rows are kept
B42: Missing pests | C42: AP-4472 (Marlo 2.5EC), AP-847 (Silah 500EC) and PHP-419 (Mosfly Cik Aerosol) have a blank pest and/or dosage cell in the source
B43: Serial gap | C43: The Store Grain Insecticide category jumps from serial 1 to 3 (no common name number 2 is printed in the source)
B44: Combined rows | C44: A handful of source rows squeeze two products into one line (e.g. "AP-2391 AP-2393 — Mascothrin 10EC / Korothrin 10EC"); these are kept as a single row with " / "-joined values where the source gives no way to split them
B45: Language | C45: All product data is printed in English in the source; the source page itself is in Bangla
B47: Provenance & Reuse
B48: Copyright | C48: Data © Department of Agricultural Extension (DAE), Ministry of Agriculture, Bangladesh. This workbook is a faithful extraction of the published list
B49: Verification | C49: Record counts were verified against registration-number tokens in the raw PDF text (5,452 = 5,452) and per-category serial continuity; see the Review sheet for live checks

Sheet Miticide
B2: Registered Miticides in Bangladesh — up to 81st PTAC Meeting
B4: SL No (Common Name) | C4: Common Name | D4: SL No (Products) | E4: Brand Name | F4: Registration No | G4: Registration Holder | H4: Recommended Crops | I4: Recommended Pests | J4: Dosage Rate | K4: Recommendations (Crop | Pest | Dosage) | L4: No. of Recommendations | M4: MoA Code
B5: 1 | C5: Ethion | D5: 1 | E5: Pithion 46.5EC | F5: AP-5242 | G5: Padma Oil Company Ltd. | H5: Chilli | I5: Mites | J5: 2 ml/L of water | K5: Chilli | Mites | 2 ml/L of water | L5: 1 | M5: IRAC 1B
B6: 2 | C6: Ethion (5%) + Thiamethoxam (20%) | D6: 1 | E6: Taba 25WDG | F6: AP-4578 | G6: Alif Agro | H6: Chilli, Rice | I6: Thrips, Aphid, BPH | J6: 100 g/ha; 0.2 g/L of water | K6: Chilli | Thrips | 100 g/ha Chilli | Aphid | 0.2 g/L of water Rice | BPH | 100 g/ha | L6: 3 | M6: IRAC 1B
B7: 3 | C7: Fenpropathrin | D7: 1 | E7: Danitol 10EC | F7: AP-291 | G7: Shetu Corporation Limited | H7: Brinjal, Tea | I7: Red spider mite | J7: 1 ml/L of water; 1.00 L/ha | K7: Brinjal | Red spider mite | 1 ml/L of water Tea | Red spider mite | 1.00 L/ha | L7: 2 | M7: IRAC 3A
B8: 3 | C8: Fenpropathrin | D8: 2 | E8: Ritol 10EC | F8: AP-3509 | G8: Rajib Agro Chemicals Ltd. | H8: Tea | I8: Red spider mite | J8: 1.00 L/ha | K8: Tea | Red spider mite | 1.00 L/ha | L8: 1 | M8: IRAC 3A
B9: 3 | C9: Fenpropathrin | D9: 3 | E9: Dumet 10EC | F9: AP-4577 | G9: Mimpex Agrochemicals Limited | H9: Tea | I9: Red mite | J9: 1.00 L/ha | K9: Tea | Red mite | 1.00 L/ha | L9: 1 | M9: IRAC 3A
B10: 3 | C10: Fenpropathrin | D10: 4 | E10: Fenpro 10EC | F10: AP-4922 | G10: Oroni International Limited | H10: Tea | I10: Red spider mite | J10: 1.00 L/ha | K10: Tea | Red spider mite | 1.00 L/ha | L10: 1 | M10: IRAC 3A
B11: 3 | C11: Fenpropathrin | D11: 5 | E11: Samitol 10EC | F11: AP-5303 | G11: SAM Agro Chemical | H11: Chilli | I11: Aphid | J11: 2 ml/L of water | K11: Chilli | Aphid | 2 ml/L of water | L11: 1 | M11: IRAC 3A
B12: 3 | C12: Fenpropathrin | D12: 6 | E12: Unifen 20EC | F12: AP-5304 | G12: Unifarma Bangladesh Industries | H12: Tea | I12: Red Spider Mite | J12: 500 ml/ha | K12: Tea | Red Spider Mite | 500 ml/ha | L12: 1 | M12: IRAC 3A
B13: 3 | C13: Fenpropathrin | D13: 7 | E13: Fenpen 10EC | F13: AP-5305 | G13: S I Agro International | H13: Tea | I13: Red Spider Mite | J13: 1.00 L/ha | K13: Tea | Red Spider Mite | 1.00 L/ha | L13: 1 | M13: IRAC 3A
B14: 3 | C14: Fenpropathrin | D14: 8 | E14: Denethrin 10EC | F14: AP-5681 | G14: Bongshe Moharaj & Agro Technology | H14: Tea | I14: Red spider mite | J14: 1.00 L/ha | K14: Tea | Red spider mite | 1.00 L/ha | L14: 1 | M14: IRAC 3A
B15: 4 | C15: Fenpropathrin (3%) + Fenvalerate (7%) | D15: 1 | E15: Sniper 10SC | F15: AP-4565 | G15: Eminence Chemical Industries Ltd | H15: Tea | I15: Helopeltis | J15: 200 ml/ha | K15: Tea | Helopeltis | 200 ml/ha | L15: 1 | M15: IRAC 3A
B16: 5 | C16: Pyriproxyfen (5%) + Fenpropathrin (15%) | D16: 1 | E16: Sweetprid 20EC | F16: AP-4923 | G16: Sweet Agrovet Limited | H16: Brinjal | I16: Aphid | J16: 1 ml/L of water | K16: Brinjal | Aphid | 1 ml/L of water | L16: 1
B17: 5 | C17: Pyriproxyfen (5%) + Fenpropathrin (15%) | D17: 2 | E17: Nepathrin Plus 20EC | F17: AP-5306 | G17: Need Agro Industries | H17: Tea, Mango | I17: Red Spider Mite, Hopper | J17: 500 ml/ha; 1 ml/L of water | K17: Tea | Red Spider Mite | 500 ml/ha Mango | Hopper | 1 ml/L of water | L17: 2
B18: 5 | C18: Pyriproxyfen (5%) + Fenpropathrin (15%) | D18: 3 | E18: Super Win 20EC | F18: AP-5307 | G18: Win Agro Limited | H18: Tea | I18: Red Spider Mite | J18: 500 ml/ha | K18: Tea | Red Spider Mite | 500 ml/ha | L18: 1
B19: 5 | C19: Pyriproxyfen (5%) + Fenpropathrin (15%) | D19: 4 | E19: Jamir 20EC | F19: AP-5524 | G19: Intefa | H19: Jute | I19: Hairy Caterpillar | J19: 550 ml/ha | K19: Jute | Hairy Caterpillar | 550 ml/ha | L19: 1
B20: 5 | C20: Pyriproxyfen (5%) + Fenpropathrin (15%) | D20: 5 | E20: Plabon 20EC | F20: AP-5525 | G20: General Agro Chemicals Ltd. | H20: Brinjal | I20: Red Spider Mite | J20: 0.5 ml/L of water | K20: Brinjal | Red Spider Mite | 0.5 ml/L of water | L20: 1
B21: 5 | C21: Pyriproxyfen (5%) + Fenpropathrin (15%) | D21: 6 | E21: Fair-Hit 20EC | F21: AP-5779 | G21: Fair Agrochemicals Services Ltd. | H21: Mango, Tea | I21: Hopper, Helopeltis | J21: 1 ml/L of water; 500 ml/ha | K21: Mango | Hopper | 1 ml/L of water Tea | Helopeltis | 500 ml/ha | L21: 2
B22: 5 | C22: Pyriproxyfen (5%) + Fenpropathrin (15%) | D22: 7 | E22: Khallash 20EC | F22: AP-5780 | G22: Babylon Agriscience Ltd. | H22: Cotton | I22: Ball worm | J22: 200 ml/ha | K22: Cotton | Ball worm | 200 ml/ha | L22: 1
B23: 5 | C23: Pyriproxyfen (5%) + Fenpropathrin (15%) | D23: 8 | E23: ZicZole 20SC | F23: AP-6003 | G23: Gurpukur Corporation | H23: Jute | I23: Hairy Caterpillar | J23: 500 ml/ha | K23: Jute | Hairy Caterpillar | 500 ml/ha | L23: 1
B24: 5 | C24: Pyriproxyfen (5%) + Fenpropathrin (15%) | D24: 9 | E24: Serf Super 20EC | F24: AP-6004 | G24: Serf Agro Industroes | H24: Mango | I24: Hopper | J24: 1 ml/L of water | K24: Mango | Hopper | 1 ml/L of water | L24: 1
B25: 5 | C25: Pyriproxyfen (5%) + Fenpropathrin (15%) | D25: 10 | E25: Daoya 20EC | F25: AP-6005 | G25: Express Agro Care Ltd. | H25: Jute | I25: Hairy Caterpillar | J25: 650 ml/ha | K25: Jute | Hairy Caterpillar | 650 ml/ha | L25: 1
B26: 5 | C26: Pyriproxyfen (5%) + Fenpropathrin (15%) | D26: 11 | E26: Daze 20EC | F26: AP-6006 | G26: Roof Crop Care Ltd. | H26: Jute, Mango | I26: Hairy Caterpillar, Hopper | J26: 500 ml/ha; 1 ml/L of water | K26: Jute | Hairy Caterpillar | 500 ml/ha Mango | Hopper | 1 ml/L of water | L26: 2
B27: 5 | C27: Pyriproxyfen (5%) + Fenpropathrin (15%) | D27: 12 | E27: Rongon 20EC | F27: AP-6007 | G27: Valent Tech Limited | H27: Potato | I27: Cutworm | J27: 3 ml/L of water | K27: Potato | Cutworm | 3 ml/L of water | L27: 1
... B31: 5 | C31: Pyriproxyfen (5%) + Fenpropathrin (15%) | D31: 16 | E31: Ricofen Plus 20EC | F31: AP-6011 | G31: Rico Agrovet | H31: Tea | I31: Red spider mite | J31: 500 ml/ha | K31: Tea | Red spider mite | 500 ml/ha | L31: 1
B32: 6 | C32: Hexythiazox | D32: 1 | E32: Mite Scavenger 10EC | F32: AP-3898 | G32: Eminence Chemical Industries Ltd | H32: Tea | I32: Red spider mite | J32: 500 ml/ha | K32: Tea | Red spider mite | 500 ml/ha | L32: 1 | M32: IRAC 10A
B33: 6 | C33: Hexythiazox | D33: 2 | E33: Hexythiao 5.45EC | F33: AP-4076 | G33: Hossain Enterprise C C Ltd | H33: Tea, Brinjal | I33: Red spider mite, Mite | J33: 1.0 L/ha; 1 ml/L of water | K33: Tea | Red spider mite | 1.0 L/ha Brinjal | Mite | 1 ml/L of water | L33: 2 | M33: IRAC 10A
B34: 6 | C34: Hexythiazox | D34: 3 | E34: Larsimite 10EC | F34: AP-4576 | G34: Larsen Chemical Industries (Pvt) Ltd. | H34: Tea, Jute | I34: Red spider mite, Yellow mite | J34: 500 ml/ha | K34: Tea | Red spider mite | 500 ml/ha Jute | Yellow mite | 500 ml/ha | L34: 2 | M34: IRAC 10A
B35: 6 | C35: Hexythiazox | D35: 4 | E35: Demiter 10EC | F35: AP-4925 | G35: Win Agro Limited | H35: Tea, Rice | I35: Red spider mite, BPH | J35: 500 ml/ha; 1.0 L/ha | K35: Tea | Red spider mite | 500 ml/ha Rice | BPH | 1.0 L/ha | L35: 2 | M35: IRAC 10A
B36: 6 | C36: Hexythiazox | D36: 5 | E36: Nezox 10EC | F36: AP-4926 | G36: Need Agro Industries | H36: Tea, Rice | I36: Red spider mite, BPH | J36: 500 ml/ha; 1.0 L/ha | K36: Tea | Red spider mite | 500 ml/ha Rice | BPH | 1.0 L/ha | L36: 2 | M36: IRAC 10A
B37: 6 | C37: Hexythiazox | D37: 6 | E37: Mileage 10EC | F37: AP-5309 | G37: ACI Formulations Limited | H37: Tea, Chilli | I37: Red Spider Mite, Thrips | J37: 500 ml/ha; 1 ml/L of water | K37: Tea | Red Spider Mite | 500 ml/ha Chilli | Thrips | 1 ml/L of water | L37: 2 | M37: IRAC 10A
B38: 6 | C38: Hexythiazox | D38: 7 | E38: Aimzox 10EC | F38: AP-5311 | G38: Agricultural Input Marketing | H38: Tea, Jute | I38: Red spider mite, Yellow Mite | J38: 500 ml/ha; 800 ml/ha | K38: Tea | Red spider mite | 500 ml/ha Jute | Yellow Mite | 800 ml/ha | L38: 2 | M38: IRAC 10A
B39: 6 | C39: Hexythiazox | D39: 8 | E39: Sunex 10EC | F39: AP-5529 | G39: Sun Seed Pesticides | H39: Tea | I39: Red Spider Mite | J39: 500 ml/ha | K39: Tea | Red Spider Mite | 500 ml/ha | L39: 1 | M39: IRAC 10A
B40: 6 | C40: Hexythiazox | D40: 9 | E40: Spidex 10EC | F40: AP-5717 | G40: Hossain Enterprise C C Ltd | H40: Tea | I40: Red Spider Mite | J40: 500 ml/ha | K40: Tea | Red Spider Mite | 500 ml/ha | L40: 1 | M40: IRAC 10A
B41: 7 | C41: Propargite | D41: 1 | E41: Omite 57EC | F41: AP-184 | G41: Shetu Corporation Limited | H41: Tea, Brinjal | I41: Red spider mites, Red mite | J41: 1.0 L/ha | K41: Tea | Red spider mites | 1.0 L/ha Brinjal | Red mite | 1.0 L/ha | L41: 2 | M41: IRAC 12C
B42: 7 | C42: Propargite | D42: 2 | E42: Sumite 57EC | F42: AP-360 | G42: McDonald Bangladesh (Pvt) Limited | H42: Tea | I42: Red mites | J42: 1.0 L/ha | K42: Tea | Red mites | 1.0 L/ha | L42: 1 | M42: IRAC 12C
B43: 7 | C43: Propargite | D43: 3 | E43: Emimite 57EC | F43: AP-1159 | G43: Eminence Chemical Industries Ltd | H43: Tea | I43: Red spider mites | J43: 1.0 L/ha | K43: Tea | Red spider mites | 1.0 L/ha | L43: 1 | M43: IRAC 12C
... B47: 7 | C47: Propargite | D47: 7 | E47: Oromite 57EC | F47: AP-5351 | G47: Oroni International Limited | H47: Tea, Brinjal | I47: Red spider mites, Red mite | J47: 1.0 L/ha; 2 ml/L of water | K47: Tea | Red spider mites | 1.0 L/ha Brinjal | Red mite | 2 ml/L of water | L47: 2 | M47: IRAC 12C
B48: 8 | C48: Sulphur | D48: 1 | E48: Limi Sulphur 80WP | F48: AP-292 | G48: The Limit Agroproducts Limited | H48: Jute, Tea | I48: Yellow mites, Red mites | J48: 1.68 kg/ha; 2.20 kg/ha | K48: Jute | Yellow mites | 1.68 kg/ha Tea | Red mites | 2.20 kg/ha | L48: 2
B49: 8 | C49: Sulphur | D49: 2 | E49: Cosavet DF | F49: AP-397 | G49: Alpha Agro Limited | H49: Jute, Tea, Cucurbit | I49: Yellow mites, Red mites, Powdery mildew | J49: 880 g/ha; 2.20 kg/ha; 2 g/L of water | K49: Jute | Yellow mites | 880 g/ha Tea | Red mites | 2.20 kg/ha Cucurbit | Powdery mildew | 2 g/L of water | L49: 3
B50: 8 | C50: Sulphur | D50: 3 | E50: Sulphur 80WP | F50: AP-392 | G50: Gourab Industries Limited | H50: Jute, Tea, Cucurbit | I50: Yellow mites, Mites, Powdery mildew | J50: 0.12% a.i./ha; 2.20 kg/ha; 1.25 g/L of water | K50: Jute | Yellow mites | 0.12% a.i./ha Tea | Mites | 2.20 kg/ha Cucurbit | Powdery mildew | 1.25 g/L of water | L50: 3
B51: 8 | C51: Sulphur | D51: 4 | E51: Sulfolac 80WG | F51: AP-413 | G51: SAM Agro Chemical | H51: Jute, Cucurbit, Tea, Rice | I51: Yellow Mites, Powdery mildew, Red mites, Leaf scald | J51: 2.20 kg/ha; 1.25 g/L of water | K51: Jute | Yellow Mites | 2.20 kg/ha Cucurbit | Powdery mildew | 1.25 g/L of water Tea | Red mites | 2.20 kg/ha Rice | Leaf scald | 2.20 kg/ha | L51: 4
B52: 8 | C52: Sulphur | D52: 5 | E52: Filvit 80WG | F52: AP-480 | G52: Agritech | H52: Tea | I52: Red mites | J52: 2.20 kg/ha | K52: Tea | Red mites | 2.20 kg/ha | L52: 1
B53: 8 | C53: Sulphur | D53: 6 | E53: Haysulf DF 80% | F53: AP-481 | G53: Haychem (Bangladesh) Limited | H53: Tea, Cucurbit, Jute, Coriander | I53: Red mites, Powdery mildew, Yellow mites | J53: 2.20 kg/ha; 2 g/L of water; 0.12 a.i/ha | K53: Tea | Red mites | 2.20 kg/ha Cucurbit | Powdery mildew | 2 g/L of water Jute | Yellow mites | 0.12 a.i/ha Coriander | Powdery mildew | 2 g/L of water | L53: 4
B54: 8 | C54: Sulphur | D54: 7 | E54: Phytovit 80DF | F54: AP-510 | G54: East West Chemicals Ltd. | H54: Cucurbit, Jute | I54: Powdery mildew, Yellow mites | J54: 2 g/Lof water; 1.75 kg/ha | K54: Cucurbit | Powdery mildew | 2 g/Lof water Jute | Yellow mites | 1.75 kg/ha | L54: 2
B55: 8 | C55: Sulphur | D55: 8 | E55: Vitasul 80WP | F55: AP-513 | G55: Padma Agro Sprayers Co. | H55: Cucurbits | I55: Powdery mildew | J55: 2 g/L of water | K55: Cucurbits | Powdery mildew | 2 g/L of water | L55: 1
B56: 8 | C56: Sulphur | D56: 9 | E56: Prosulf 80%DF | F56: AP-529 | G56: Haychem (Bangladesh) Limited | H56: Tea, Jute, Cucurbit | I56: Red mites, Yellow mites, Powdery mildew | J56: 2.25 kg/ha; 1.75 kg/ha; 2 g/L of water | K56: Tea | Red mites | 2.25 kg/ha Jute | Yellow mites | 1.75 kg/ha Cucurbit | Powdery mildew | 2 g/L of water | L56: 3
B57: 8 | C57: Sulphur | D57: 10 | E57: Kumulus DF | F57: AP-548 | G57: BASF Bangladesh Limited | H57: Tea, Bottle gourd, Potato, Cucumber,Teasle gourd, Bitter gourd, Bean,, Cabbage, Cauliflower, Snake gourd, Ridge, gourd, Watermelon, Rice | I57: Red spider mites & other mites, Powdery mildew, Leaf scald | J57: 2.20 kg/ha; 2.00 kg/ha; 2.50 kg/ha | K57: Tea | Red spider mites & other mites | 2.20 kg/ha Bottle gourd, Potato | Powdery mildew | 2.00 kg/ha Cucumber,Teasle gourd | Powdery mildew | 2.00 kg/ha Bitter gourd, Bean, | Powdery mildew | 2.00 kg/ha Cabbage, Cauliflower | Powdery mildew | 2.00 kg/ha Snake gourd, Ridge | Powdery mildew | 2.00 kg/ha gourd, Watermelon | Powdery mildew | 2.00 kg/ha Rice | Leaf scald | 2.50 kg/ha | L57: 8
B58: 8 | C58: Sulphur | D58: 11 | E58: Thiovit 80WG | F58: AP-552 | G58: Syngenta Bangladesh Limited | H58: Jute, Bottle gourd, Sweet, gourd, Cucurbit, Bitter gourd, Citrus,, Teasel gourd, Ribbed, gourd, Watermelon, Tomato, Tea, Sugarcane, Rice | I58: Yellow & Red mites, Powdery mildew, Wilt, Mites, Leaf scald | J58: 3.30 kg/ha; 2.25 kg/ha; 2.50 kg/ha | K58: Jute | Yellow & Red mites | 3.30 kg/ha Bottle gourd, Sweet | Powdery mildew | 2.25 kg/ha gourd, Cucurbit | Powdery mildew | 2.25 kg/ha Bitter gourd, Citrus, | Powdery mildew | 2.25 kg/ha Teasel gourd, Ribbed | Powdery mildew | 2.25 kg/ha gourd, Watermelon | Powdery mildew | 2.25 kg/ha Tomato | Wilt | 2.25 kg/ha Tea | Mites | 2.25 kg/ha Sugarcane | Powdery mildew | 3.30 kg/ha Rice | Leaf scald | 2.50 kg/ha | L58: 10
B59: 8 | C59: Sulphur | D59: 12 | E59: Corovit 80WG | F59: AP-562 | G59: Corbel International Limited | H59: Tea | I59: Red mites | J59: 2.25 kg/ha | K59: Tea | Red mites | 2.25 kg/ha | L59: 1
... B209: 8 | C209: Sulphur | D209: 162 | E209: LCI Super 80WDG | F209: AP-4187 | G209: Larsen Chemical Industries (Pvt) Ltd. | H209: Tea | I209: Red Spider mite | J209: 2.25 kg/ha | K209: Tea | Red Spider mite | 2.25 kg/ha | L209: 1
B210: Total (visible rows) | E210: =SUBTOTAL(103,E5:E209) -> 205 | L210: =SUBTOTAL(109,L5:L209) -> 314
B212: Source: Department of Agricultural Extension (DAE), Bangladesh — List of Registered Pesticides approved up to the 81st Pesticide Technical Advisory Committee (PTAC) Meeting. Extracted 2026-09-15 from https://dae.gov.bd/pages/files/6922da2a933eb65569e02d1e

Sheet Fungicide
B2: Registered Fungicides in Bangladesh — up to 81st PTAC Meeting
B4: SL No (Common Name) | C4: Common Name | D4: SL No (Products) | E4: Brand Name | F4: Registration No | G4: Registration Holder | H4: Recommended Crops | I4: Recommended Pests | J4: Dosage Rate | K4: Recommendations (Crop | Pest | Dosage) | L4: No. of Recommendations | M4: MoA Code
B5: 1 | C5: Azoxystrobin | D5: 1 | E5: Sitro 25 SC | F5: AP-3153 | G5: S I Agro International | H5: Tea | I5: Die back, Block rot | J5: 500 mlha | K5: Tea | Die back, Block rot | 500 mlha | L5: 1 | M5: FRAC 11
B6: 1 | C6: Azoxystrobin | D6: 2 | E6: Forbin 50WDG | F6: AP-3560 | G6: Sun Seed Pesticides | H6: Cucumber | I6: Powdery mildew | J6: 0.5 ml/L of water | K6: Cucumber | Powdery mildew | 0.5 ml/L of water | L6: 1 | M6: FRAC 11
B7: 1 | C7: Azoxystrobin | D7: 3 | E7: Forstrobin 25SC | F7: AP-4275 | G7: Forward International (BD) Ltd. | H7: Cucumber | I7: Powdery mildew | J7: 1 ml/L of water | K7: Cucumber | Powdery mildew | 1 ml/L of water | L7: 1 | M7: FRAC 11
B8: 1 | C8: Azoxystrobin | D8: 4 | E8: Affix 25SC | F8: AP-4691 | G8: RiceCo International Bangladesh Ltd | H8: Tea | I8: Die back | J8: 750 mlha | K8: Tea | Die back | 750 mlha | L8: 1 | M8: FRAC 11
B9: 1 | C9: Azoxystrobin | D9: 5 | E9: Azox 50WP | F9: AP-5054 | G9: McDonald Bangladesh (Pvt) Ltd. | H9: Sweet gourd | I9: Powdery mildew | J9: 0.5 g/L of water | K9: Sweet gourd | Powdery mildew | 0.5 g/L of water | L9: 1 | M9: FRAC 11
B10: 1 | C10: Azoxystrobin | D10: 6 | E10: Azomax 25SC | F10: AP-5360 | G10: Zaker Croplife Bangladesh | H10: Cucumbits, Cucumber, Tea | I10: Powdery mildew, Downy mildew, Black rot | J10: 1 ml/L of water; 500 mlha | K10: Cucumbits | Powdery mildew | 1 ml/L of water Cucumber | Downy mildew | 1 ml/L of water Tea | Black rot | 500 mlha | L10: 3 | M10: FRAC 11
B11: 2 | C11: Azoxystrobin (20% ) + Cyproconazole (8%) | D11: 1 | E11: Karishma 28SC | F11: AP-2431 | G11: Eon Agro Industries Limited | H11: Mango | I11: Anthracnose | J11: 1.2 L/ha | K11: Mango | Anthracnose | 1.2 L/ha | L11: 1 | M11: FRAC 11
B12: 2 | C12: Azoxystrobin (20% ) + Cyproconazole (8%) | D12: 2 | E12: Tared 280SC | F12: AP-3613 | G12: Intefa | H12: Potato | I12: Late blight | J12: 0.5 ml/L of water | K12: Potato | Late blight | 0.5 ml/L of water | L12: 1 | M12: FRAC 11
B13: 2 | C13: Azoxystrobin (20% ) + Cyproconazole (8%) | D13: 3 | E13: Dover 28SC | F13: AP-4245 | G13: Agritech | H13: Mango, Chilli | I13: Anthracnose | J13: 1 ml/L of water | K13: Mango | Anthracnose | 1 ml/L of water Chilli | Anthracnose | 1 ml/L of water | L13: 2 | M13: FRAC 11
B14: 2 | C14: Azoxystrobin (20% ) + Cyproconazole (8%) | D14: 4 | E14: Cauger 28SC | F14: AP-4692 | G14: RiceCo International Bangladesh Ltd | H14: Tea | I14: Die back | J14: 750 ml.ha | K14: Tea | Die back | 750 ml.ha | L14: 1 | M14: FRAC 11
B15: 2 | C15: Azoxystrobin (20% ) + Cyproconazole (8%) | D15: 5 | E15: Kasmira 28SC | F15: AP-4693 | G15: Mary Gold Agro Science | H15: Sweet gourd | I15: Powdery mildew | J15: 1 ml/L of water | K15: Sweet gourd | Powdery mildew | 1 ml/L of water | L15: 1 | M15: FRAC 11
B16: 2 | C16: Azoxystrobin (20% ) + Cyproconazole (8%) | D16: 6 | E16: Jinazole 28SC | F16: AP-4695 | G16: Alpha Agro Limited | H16: Sweet gourd, Wheat | I16: Powdery mildew, Leaf blight | J16: 1 ml/L of water | K16: Sweet gourd | Powdery mildew | 1 ml/L of water Wheat | Leaf blight | 1 ml/L of water | L16: 2 | M16: FRAC 11
... B91: 8 | C91: Boscalid (50%) | D91: 1 | E91: Sunca 50SC | F91: AP-5808 | G91: McDonald Bangladesh (Pvt) Limited | H91: Cucumber | I91: Powdery mildew | J91: 1 ml/L of water | K91: Cucumber | Powdery mildew | 1 ml/L of water | L91: 1 | M91: FRAC 7
B92: 9 | C92: Bismerthiazole | D92: 1 | E92: Bactrol 20WP | F92: AP-2567 | G92: Surovi Agro Industries Limited | H92: Potato | I92: Late blight | J92: 2 g/L of water | K92: Potato | Late blight | 2 g/L of water | L92: 1
B93: 9 | C93: Bismerthiazole | D93: 2 | E93: Bactroban 20WP | F93: AP-4218 | G93: Haychem (Bangladesh) Limited | H93: Tea, Potato, Rice, Tomato | I93: Red rust, Die back, Block rot, Wilt, Blast, Bacterial blight | J93: 2.00 kg/ha; 1.00 kg/h; 450 gg/ha; 2 g/L of water | K93: Tea | Red rust, Die back, Block rot | 2.00 kg/ha Potato | Wilt | 1.00 kg/h Rice | Blast, Bacterial blight | 450 gg/ha Tomato | Wilt | 2 g/L of water | L93: 4
B94: 9 | C94: Bismerthiazole | D94: 3 | E94: Radi 20WP | F94: AP-5012 | G94: Intefa | H94: Tomato | I94: Wilt | J94: 2 g/L of water | K94: Tomato | Wilt | 2 g/L of water | L94: 1
B95: 9 | C95: Bismerthiazole | D95: 4 | E95: Bismazol 20WP | F95: AP-5630 | G95: Square Pharmaceuticals Limited | H95: Tomato | I95: Wilt | J95: 2 g/L of water | K95: Tomato | Wilt | 2 g/L of water | L95: 1
B96: 10 | C96: Bismerthiazol (20%) + Kasungamycin (1.5%) | D96: 1 | E96: Sunoscar 21.5WP | F96: AP-5051 | G96: McDonald Bangladesh (Pvt) Limited | H96: Tea, Tomato | I96: Die Back, Wilt | J96: 1.5 Kg/ha; 2 g/L of water | K96: Tea | Die Back | 1.5 Kg/ha Tomato | Wilt | 2 g/L of water | L96: 2 | M96: FRAC 24
B97: 10 | C97: Bismerthiazol (20%) + Kasungamycin (1.5%) | D97: 2 | E97: Kimia 21.5WP | F97: AP-5375 | G97: Mimpex Agrochemicals Limited | H97: Tomato | I97: Wilt | J97: 2 g/L of water | K97: Tomato | Wilt | 2 g/L of water | L97: 1 | M97: FRAC 24
B98: 11 | C98: Carbendazim | D98: 1 | E98: Knowin 50WP | F98: AP-241 | G98: McDonald Bangladesh (Pvt) Limited | H98: Rice, Guava, Tea, Banana, Sugarcane, Mango | I98: Sheath blight, Anthracnose, Red rust, Black rot, Die back & Gall Ma, Sigatoka, Pine apple, Wilt & red rot | J98: 1.00 kg/ha; 2 g/L of water; 750 gm/ha; 1 ml/L of water | K98: Rice | Sheath blight | 1.00 kg/ha Guava | Anthracnose | 2 g/L of water Tea | Red rust, Black rot, Die back & Gall Ma | 750 gm/ha Banana | Sigatoka | 2 g/L of water Sugarcane | Pine apple, Wilt & red rot | 1 ml/L of water Mango | Anthracnose | 1 ml/L of water | L98: 6 | M98: FRAC 1
B99: 11 | C99: Carbendazim | D99: 2 | E99: Shincar 50WP | F99: AP-355 | G99: United Phosphorus (Bangladesh) Ltd. | H99: Tobacco | I99: Frog eye & Leaf spot | J99: 2 g/L of water | K99: Tobacco | Frog eye & Leaf spot | 2 g/L of water | L99: 1 | M99: FRAC 1
B100: 11 | C100: Carbendazim | D100: 3 | E100: Aimcozim 50WP | F100: AP-375 | G100: ACI Formulations Limited | H100: Rice, Tea, Sugarcane, Tomato | I100: Sheath blight, Red rust, Sett rot, Pineapple, Red rot & Wilt, Seedling rot | J100: 500 gm/ha; 750 gm/ha; 2 g/L of water | K100: Rice | Sheath blight | 500 gm/ha Tea | Red rust | 750 gm/ha Sugarcane | Sett rot, Pineapple | 500 gm/ha Sugarcane | Red rot & Wilt | 500 gm/ha Tomato | Seedling rot | 2 g/L of water | L100: 5 | M100: FRAC 1
B101: 11 | C101: Carbendazim | D101: 4 | E101: Agben 50%F | F101: AP-439 | G101: Genetica Industries Ltd. | H101: Sugarcane, Rice | I101: Sett treatment, Sheath blight | J101: 1 g/L of water; 1.00 kg/ha | K101: Sugarcane | Sett treatment | 1 g/L of water Rice | Sheath blight | 1.00 kg/ha | L101: 2 | M101: FRAC 1
B102: 11 | C102: Carbendazim | D102: 5 | E102: Forastin 50WP | F102: AP-511 | G102: Shetu Pesticides Limited | H102: Rice, Sugarcane | I102: Sheath blight, Sett rot | J102: 1.00 kg/ha; 1 g/L of water | K102: Rice | Sheath blight | 1.00 kg/ha Sugarcane | Sett rot | 1 g/L of water | L102: 2 | M102: FRAC 1
B103: 11 | C103: Carbendazim | D103: 6 | E103: Genuine 50WP | F103: AP-531 | G103: SAM Agro Chemical | H103: Sugarcane, Tomato, Rice, Garden pea, Mango, Chili | I103: Sett rot disease, Wilt, Sheath blight, Powdery mildew, Hopper, Anthracnose | J103: 1 g/L of water; 2 g/L of water; 1.00 kg/ha | K103: Sugarcane | Sett rot disease | 1 g/L of water Tomato | Wilt | 2 g/L of water Rice | Sheath blight | 1.00 kg/ha Garden pea | Powdery mildew | 2 g/L of water Mango | Hopper | 1 g/L of water Chili | Anthracnose | 2 g/L of water | L103: 6 | M103: FRAC 1
B104: 11 | C104: Carbendazim | D104: 7 | E104: Cindazim 50WP | F104: AP-627 | G104: Shetu Corporation Limited | H104: Tomato, Rice, Sugarcane | I104: Wilt, Sheath blight, Sett rot, Pineapple Red rot, Wilt | J104: 2 g/L of water; 1.00 kg/ha; 500 gm/ha | K104: Tomato | Wilt | 2 g/L of water Rice | Sheath blight | 1.00 kg/ha Sugarcane | Sett rot, Pineapple Red rot, Wilt | 500 gm/ha | L104: 3 | M104: FRAC 1
B105: 11 | C105: Carbendazim | D105: 8 | E105: Nayan 50WP | F105: AP-720 | G105: Anika Enterprise | H105: Tomato, Cabbage, Cauli, Sugarcane, Banana | I105: Seedling rot, Sett rot, Sigatoka | J105: 1 g/kg seed; 1 g/L of water | K105: Tomato, Cabbage, Cauli | Seedling rot | 1 g/kg seed Sugarcane | Sett rot | 1 g/L of water Banana | Sigatoka | 1 g/L of water | L105: 3 | M105: FRAC 1
B106: 11 | C106: Carbendazim | D106: 9 | E106: Zimper 50 WP | F106: AP-725 | G106: Prime Agro Limited | H106: Banana, Tomato | I106: Sigatoka, Wilt | J106: 2 g/L of water | K106: Banana | Sigatoka | 2 g/L of water Tomato | Wilt | 2 g/L of water | L106: 2 | M106: FRAC 1
B107: 11 | C107: Carbendazim | D107: 10 | E107: Evazim 50WP | F107: AP-729 | G107: E H & Agrovet Limited | H107: Rice, Sugarcane | I107: Sheath blight, Sett rot | J107: 1.00 kg/ha; 1 g/L of water | K107: Rice | Sheath blight | 1.00 kg/ha Sugarcane | Sett rot | 1 g/L of water | L107: 2 | M107: FRAC 1
... B244: 12 | C244: Carbendazim ( 32.5%) + Hexaconazole (2.5%) | D244: 2 | E244: Offense 35SC | F244: AP-4278 | G244: Popular Agro Industries | H244: Mango | I244: Anthracnose | J244: 0.5 ml/L of water | K244: Mango | Anthracnose | 0.5 ml/L of water | L244: 1 | M244: FRAC 1
C245: 40% + 5% | D245: 3 | E245: Dhan Shiri 45SC | F245: AP-5034 | G245: Sea Trade Fertilizer Limited | H245: Tea | I245: Dieback | J245: 750 ml/ha | K245: Tea | Dieback | 750 ml/ha | L245: 1
B246: 13 | C246: Carbendazin ( 20%) + Thiram (40%) | D246: 1 | E246: Topath 60WP | F246: AP-4720 | G246: Symbiosis Technology | H246: Tea | I246: Red Rust, Die Back, Block Rot | J246: 1.00 kg/ha | K246: Tea | Red Rust, Die Back, Block Rot | 1.00 kg/ha | L246: 1 | M246: FRAC 1
B247: 14 | C247: Carbendazim (25%) + Thiram (25%) Imidacloprid (25%) | D247: 1 | E247: Atavo 75WDG | F247: AP-4721 | G247: Annodatta Limited | H247: Tomato, Rice | I247: Wilt, Bakanae | J247: 8 g/kg Seed; 8 g/Kg Seed | K247: Tomato | Wilt | 8 g/kg Seed Rice | Bakanae | 8 g/Kg Seed | L247: 2 | M247: FRAC 1
B248: 14 | C248: Carbendazim (25%) + Thiram (25%) Imidacloprid (25%) | D248: 2 | E248: Nazda 75WDG | F248: AP-4722 | G248: Sasco International | H248: Tomato | I248: Wilt | J248: 8 g/kg Seed | K248: Tomato | Wilt | 8 g/kg Seed | L248: 1 | M248: FRAC 1
B249: 14 | C249: Carbendazim (25%) + Thiram (25%) Imidacloprid (25%) | D249: 3 | E249: Topzim Super 75WDG | F249: AP-4723 | G249: Tasin Agro Care | H249: Tomato, Rice | I249: Wilt, Bakanae | J249: 8 g/kg Seed; 8g/Kg Seed | K249: Tomato | Wilt | 8 g/kg Seed Rice | Bakanae | 8g/Kg Seed | L249: 2 | M249: FRAC 1
B250: 14 | C250: Carbendazim (25%) + Thiram (25%) Imidacloprid (25%) | D250: 4 | E250: Ama Plus 75WG | F250: AP-5036 | G250: Amana Agro Science | H250: Tea | I250: Dieback | J250: 500 gm/ha | K250: Tea | Dieback | 500 gm/ha | L250: 1 | M250: FRAC 1
B251: 14 | C251: Carbendazim (25%) + Thiram (25%) Imidacloprid (25%) | D251: 5 | E251: Naz Gold 75WDG | F251: AP-5037 | G251: Mondol Traders | H251: Bean | I251: Aphid | J251: 0. 2 gm/L of water | K251: Bean | Aphid | 0. 2 gm/L of water | L251: 1 | M251: FRAC 1
B252: 15 | C252: Carbendazim (10%) + Imidacloprid (10) + Metalaxyl (10%) | D252: 1 | E252: Fasal Special 30WP | F252: AP-5011 | G252: Fasal Agro Industries Ltd. | H252: Tea, Sweet gourd | I252: Helopeltis, Die back, Black rot, Powdery mildew | J252: 1.0 Kg/ha; 750 gm/ha; 250 gm/ha | K252: Tea | Helopeltis | 1.0 Kg/ha Tea | Die back, Black rot | 750 gm/ha Sweet gourd | Die back, Black rot | 750 gm/ha Sweet gourd | Powdery mildew | 250 gm/ha | L252: 4 | M252: FRAC 1
B253: 15 | C253: Carbendazim (10%) + Imidacloprid (10) + Metalaxyl (10%) | D253: 2 | E253: Regiment 30WP | F253: AP-5578 | G253: ACI Agrolink Limited | H253: Rice | I253: Hispa | J253: 500 gm/ha | K253: Rice | Hispa | 500 gm/ha | L253: 1 | M253: FRAC 1
B254: 16 | C254: Imidacloprid (20) + Metalaxyl M (20%) + Tebuconazole (2%) | D254: 1 | E254: Multiguard 42WS | F254: AP-5579 | G254: Global Agrovet Limited | H254: Bean | I254: Aphid | J254: 1.25 Kg/ha | K254: Bean | Aphid | 1.25 Kg/ha | L254: 1 | M254: IRAC 4A
B255: 17 | C255: Tebuconazole (12.50%) Cyproconazole (40.00%) Azoxystrobin (11.00%) | D255: 1 | E255: Troy 63.5SC | F255: AP-5806 | G255: Babylon Agriscience Ltd. | H255: Sweet gourd | I255: Powdery mildew | J255: 1 ml/L of water | K255: Sweet gourd | Powdery mildew | 1 ml/L of water | L255: 1 | M255: FRAC 3
B256: 18 | C256: Carbendazim ( 25%) Flusilazole (12.5%) | D256: 1 | E256: Lustre 37.5SC | F256: AP-4596 | G256: Dhanuka Agri Solutions Pvt. Ltd. | H256: Tea | I256: Die back | J256: 750 ml/ha | K256: Tea | Die back | 750 ml/ha | L256: 1 | M256: FRAC 1
B257: 18 | C257: Carbendazim ( 25%) Flusilazole (12.5%) | D257: 2 | E257: Pacer 37.5SC | F257: AP-3141 | G257: Eon Agro Industries Limited | H257: Wheat | I257: Leaf blight | J257: 600 ml/ha | K257: Wheat | Leaf blight | 600 ml/ha | L257: 1 | M257: FRAC 1
... B269: 21 | C269: Carbendazim (17.5%) Iprodione (35%) | D269: 8 | E269: Kardion 52.5WP | F269: AP-5017 | G269: NCL | H269: Tea | I269: Die back | J269: 750 gm/ha | K269: Tea | Die back | 750 gm/ha | L269: 1 | M269: FRAC 1
C270: Carbendazim (25%) Iprodione (25%) | D270: 9 | E270: Orazim Plus 50WP | F270: AP-4591 | G270: Green Bangla Agrovet Ltd. | H270: Tea | I270: Die back | J270: 1.00 kg/ha | K270: Tea | Die back | 1.00 kg/ha | L270: 1 | M270: FRAC 1
C271: Carbendazim (25%) Iprodione (25%) | D271: 10 | E271: Hyprozim 50WP | F271: AP-4592 | G271: Haychem (Bangladesh) Limited | H271: Tea, Rice | I271: Die back, Sheath blight | J271: 1.00 kg/ha; 500 gm/ha | K271: Tea | Die back | 1.00 kg/ha Rice | Sheath blight | 500 gm/ha | L271: 2 | M271: FRAC 1
C272: Carbendazim (25%) Iprodione (25%) | D272: 11 | E272: Rodazima 50WP | F272: AP-4595 | G272: Mahir Agro Care | H272: Mango | I272: Anthracnose | J272: 2 g/L of water | K272: Mango | Anthracnose | 2 g/L of water | L272: 1 | M272: FRAC 1
C273: Carbendazim (25%) Iprodione (25%) | D273: 12 | E273: Moscozim 50WP | F273: AP-5015 | G273: Mosco Marketing Company | H273: Tea | I273: Die back | J273: 750 gm/ha | K273: Tea | Die back | 750 gm/ha | L273: 1 | M273: FRAC 1
B274: 22 | C274: Chlorothalonil | D274: 1 | E274: Daconil 500EC | F274: AP-2114 | G274: Haychem (Bangladesh) Limited | H274: Potato, Tomato | I274: Late Blight, Early blight | J274: 750 ml/ha; 2 g/L of water | K274: Potato | Late Blight | 750 ml/ha Tomato | Early blight | 2 g/L of water | L274: 2 | M274: FRAC M5
B275: 22 | C275: Chlorothalonil | D275: 2 | E275: Satez 50SC | F275: AP-4719 | G275: Sonali Agro Crop care | H275: Potato | I275: Late blight | J275: 2 g/L of water | K275: Potato | Late blight | 2 g/L of water | L275: 1 | M275: FRAC M5
B276: 22 | C276: Chlorothalonil | D276: 3 | E276: M-Thal 72SC | F276: AP-5372 | G276: Mamun Agro Products Ltd. | H276: Tea | I276: Red Rust | J276: 1.50 L/ha | K276: Tea | Red Rust | 1.50 L/ha | L276: 1 | M276: FRAC M5
B277: 23 | C277: Chlorothalonil (30%) + Cymoxanil (6%) | D277: 1 | E277: Bounty 36WP | F277: AP-3925 | G277: Shetu Pesticides Limited | H277: Tomato | I277: Early blight | J277: 2 g/L of water | K277: Tomato | Early blight | 2 g/L of water | L277: 1 | M277: FRAC M5
B278: 23 | C278: Chlorothalonil (30%) + Cymoxanil (6%) | D278: 2 | E278: Selfi 36WP | F278: AP-4629 | G278: Mimpex Agrochemicals Limited | H278: Tea, Potato | I278: Red rust, Late blight | J278: 1.00 kg/ha; 2 g/L of water | K278: Tea | Red rust | 1.00 kg/ha Potato | Late blight | 2 g/L of water | L278: 2 | M278: FRAC M5
B279: 23 | C279: Chlorothalonil (30%) + Cymoxanil (6%) | D279: 3 | E279: Coral 36WP | F279: AP-4630 | G279: East West Chemicals Ltd. | H279: Tea | I279: Red rust | J279: 3.00 kg/ha | K279: Tea | Red rust | 3.00 kg/ha | L279: 1 | M279: FRAC M5
B280: 23 | C280: Chlorothalonil (30%) + Cymoxanil (6%) | D280: 4 | E280: Samidew 36WP | F280: AP-5384 | G280: SAM Agro Chemical | H280: Potato | I280: Late blight | J280: 2 g/L of water | K280: Potato | Late blight | 2 g/L of water | L280: 1 | M280: FRAC M5
B281: 24 | C281: Copper hydroxide 77%) | D281: 1 | E281: Champion 77WP | F281: AP-354 | G281: Petrochem (Bangladesh) Limited | H281: Potato & Tomato, Mango, Chili, Citrus, Banana, Ground nut, Tea | I281: Late blight, Anthracnose, Scab, Leaf spot, Tikka rust, Red rust disease | J281: 2 g/L of water; 2.24 kg/ha | K281: Potato & Tomato | Late blight | 2 g/L of water Mango, Chili | Anthracnose | 2 g/L of water Citrus | Scab | 2 g/L of water Banana | Leaf spot | 2 g/L of water Ground nut | Tikka rust | 2 g/L of water Tea | Red rust disease | 2.24 kg/ha | L281: 6 | M281: FRAC M1
B282: 24 | C282: Copper hydroxide 77%) | D282: 2 | E282: Dolphin 77WP | F282: AP-716 | G282: MAP Agro Industries Limited | H282: Banana | I282: Sigatoka | J282: 6.50 g/L of water | K282: Banana | Sigatoka | 6.50 g/L of water | L282: 1 | M282: FRAC M1
B283: 24 | C283: Copper hydroxide 77%) | D283: 3 | E283: Hidrocob 77WP | F283: AP-792 | G283: Mimpex Agrochemicals Limited | H283: Potato | I283: Late blight | J283: 3.50 g/Lof water | K283: Potato | Late blight | 3.50 g/Lof water | L283: 1 | M283: FRAC M1
B284: 24 | C284: Copper hydroxide 77%) | D284: 4 | E284: Parasol 77WP | F284: AP-1360 | G284: Eminence Chemical Industries Ltd | H284: Potato, Chili | I284: Late blight, Anthracnose | J284: 2 g/L of water | K284: Potato | Late blight | 2 g/L of water Chili | Anthracnose | 2 g/L of water | L284: 2 | M284: FRAC M1
B285: 24 | C285: Copper hydroxide 77%) | D285: 5 | E285: Superex 77WP | F285: AP-1861 | G285: Rajib Agro Chemicals Ltd. | H285: Tea | I285: Die back,Black rot, Red rust | J285: 750 gm/ha | K285: Tea | Die back,Black rot, Red rust | 750 gm/ha | L285: 1 | M285: FRAC M1
... B373: 32 | C373: Pyraclostrobin (25%) | D373: 1 | E373: Forblast 250SC | F373: AP-4626 | G373: Forward International (BD). Ltd. | H373: Tea | I373: Red rust | J373: 750 ml/ha; 1.0 L/ha | K373: Tea | Red rust | 750 ml/ha - | - | 1.0 L/ha | L373: 2 | M373: FRAC 11
C374: Pyraclostrobin (10%) | D374: 1 | E374: Seltima 10 CS | F374: AP-5112 | G374: BASF Bangladesh Limited | H374: Rice | I374: Sheath blight, Blast | J374: 1.0 L/ha | K374: Rice | Sheath blight | - Rice | Blast | 1.0 L/ha | L374: 2 | M374: FRAC 11
B375: 33 | C375: Pyraclostrobin (6.7%) + Dimethomorph (12%) | D375: 1 | E375: Headline Team | F375: AP-4188 | G375: BASF Bangladesh Limited | H375: Potato | I375: Late blight | J375: 2.5 g/L of water | K375: Potato | Late blight | 2.5 g/L of water | L375: 1 | M375: FRAC 11
B376: 34 | C376: Pyraclostrobin (13%) + Tricyclazole (25%) | D376: 1 | E376: Noblast 38SC | F376: AP-5797 | G376: Eminence Chemical Industries Ltd. | H376: Tea | I376: Red rust | J376: 750 ml/ha | K376: Tea | Red rust | 750 ml/ha | L376: 1 | M376: FRAC 11
B377: 35 | C377: Ametoctradin (30%) + Dimethomorph (22.5%) | D377: 1 | E377: Zampro DM | F377: AP-4189 | G377: BASF Bangladesh Limited | H377: Potato | I377: Late blight | J377: 1.6 ml/L of water | K377: Potato | Late blight | 1.6 ml/L of water | L377: 1 | M377: FRAC 40
B378: 36 | C378: Diniconazole | D378: 1 | E378: Merabou 12.5WP | F378: AP-984 | G378: MAP Agro Industries Limited | H378: Ground nut | I378: Tikka | J378: 2 g/L of water | K378: Ground nut | Tikka | 2 g/L of water | L378: 1 | M378: FRAC 3
B379: 37 | C379: Edifenphos | D379: 1 | E379: Edifen 50EC | F379: AP-268 | G379: Shetu Pesticides Limited | H379: Rice | I379: Blast, Blister blight & Brown blight | J379: 850 ml/ha | K379: Rice | Blast, Blister blight & Brown blight | 850 ml/ha | L379: 1 | M379: FRAC 6
B380: 38 | C380: Epoxiconazole | D380: 1 | E380: Opal 7.5EC | F380: AP-2314 | G380: BASF Bangladesh Limited | H380: Rice, Cucurbit, Banana | I380: Sheath blight, Powder mildew, Sigatoka | J380: 1.25 L/ha; 2.5 ml/L of water; 2 ml/L of water | K380: Rice | Sheath blight | 1.25 L/ha Cucurbit | Powder mildew | 2.5 ml/L of water Banana | Sigatoka | 2 ml/L of water | L380: 3 | M380: FRAC 3
B381: 39 | C381: Epoxiconazol (12.5%) Carbendazim (12.5%) | D381: 1 | E381: Rista 25SC | F381: AP-3226 | G381: Eon Agro Industries Limited | H381: Cucumber | I381: Powder mildew | J381: 800 ml/ha | K381: Cucumber | Powder mildew | 800 ml/ha | L381: 1 | M381: FRAC 3
B382: 40 | C382: Hexaconazole | D382: 1 | E382: Contaf 5EC | F382: AP-460 | G382: Auto Crop Care Limited | H382: Rice, Banana, Cucurbits, Tea, Mango, Ground nut, Bettle Vine | I382: Sheath blight, Sigatoka, Powdery mildew, Red rust disease, Powdery mildew and Anthracnose, Tikka disease, Leaf rot, Vine rot & blight | J382: 500 ml/ha; 1 ml/L of water; 750 ml/ha; 2 ml/L of water | K382: Rice | Sheath blight | 500 ml/ha Banana | Sigatoka | 1 ml/L of water Cucurbits | Powdery mildew | 1 ml/L of water Tea | Red rust disease | 750 ml/ha Mango | Powdery mildew and Anthracnose | 2 ml/L of water Ground nut | Tikka disease | 1 ml/L of water Bettle Vine | Leaf rot, Vine rot & blight | 1 ml/L of water | L382: 7 | M382: FRAC 3
B383: 40 | C383: Hexaconazole | D383: 2 | E383: Hayconazol 5EC | F383: AP-713 | G383: Haychem (Bangladesh) Limited | H383: Banana, Cucurbit, Rice, Mango | I383: Sigatoka, Powdery mildew, Sheath blight/Blast, Anthracnose | J383: 1 ml/L of water; 500 ml/ha | K383: Banana | Sigatoka | 1 ml/L of water Cucurbit | Powdery mildew | 1 ml/L of water Rice | Sheath blight/Blast | 500 ml/ha Mango | Anthracnose | 1 ml/L of water | L383: 4 | M383: FRAC 3
B384: 40 | C384: Hexaconazole | D384: 3 | E384: Force 5EC | F384: AP-717 | G384: The Limit Agroproducts Limited | H384: Banana, Tea, Rice | I384: Sigatoka, Red rust, Sheath blight | J384: 1 ml/L of water; 750 ml/ha; 500 ml/ha | K384: Banana | Sigatoka | 1 ml/L of water Tea | Red rust | 750 ml/ha Rice | Sheath blight | 500 ml/ha | L384: 3 | M384: FRAC 3
B385: 40 | C385: Hexaconazole | D385: 4 | E385: Control 5EC | F385: AP-782 | G385: SARK Bangladesh | H385: Cucurbit, Banana, Rice | I385: Powdery mildew, Sigatoka, Sheath blight | J385: 1 ml/L of water; 0.5 ml/L of water; 500 ml/ha | K385: Cucurbit | Powdery mildew | 1 ml/L of water Banana | Sigatoka | 0.5 ml/L of water Rice | Sheath blight | 500 ml/ha | L385: 3 | M385: FRAC 3
B386: 40 | C386: Hexaconazole | D386: 5 | E386: Paragon 5EC | F386: AP-858 | G386: Agro Continent Bangladesh | H386: Banana, Tea | I386: Sigatoka, Die back,Black rot, Red rust | J386: 500 ml/ha; 750 ml/ha | K386: Banana | Sigatoka | 500 ml/ha Tea | Die back,Black rot, Red rust | 750 ml/ha | L386: 2 | M386: FRAC 3
... B525: 47 | C525: Iprodione (17.5%) + Carbendazim (8.5%) | D525: 1 | E525: Iprozim 26WP | F525: AP-1355 | G525: Oroni International Limited | H525: Mustard, Onion, Potato, Sugarcane | I525: Alternaria bright, Purple blotch, Late blight, Sett rot | J525: 1 g/L of water; 2 g/L of water | K525: Mustard | Alternaria bright | 1 g/L of water Onion | Purple blotch | 2 g/L of water Potato | Late blight | 2 g/L of water Sugarcane | Sett rot | 2 g/L of water | L525: 4 | M525: FRAC 2
C526: Iprodione (25%) + Carbendazim (25%) | D526: 2 | E526: Dizim Plus 50WP | F526: AP-3930 | G526: Digital Crop Solution | H526: Mango, Onion | I526: Anthracnose, Purpule blotch | J526: 2 g/L of water | K526: Mango | Anthracnose | 2 g/L of water Onion | Purpule blotch | 2 g/L of water | L526: 2 | M526: FRAC 2
B527: 48 | C527: Iprodione (12.5%) + Mancozeb (37.5%) | D527: 1 | E527: Relief 50WP | F527: AP-3934 | G527: East West Chemicals Ltd. | H527: Tea | I527: Red rust, Die back, Black rot | J527: 2.00 kg/ha | K527: Tea | Red rust, Die back, Black rot | 2.00 kg/ha | L527: 1 | M527: FRAC 2
B528: 49 | C528: Isoprothiolane | D528: 1 | E528: Nac-Pro 40EC | F528: AP-5626 | G528: National AgriCare Import & Export Ltd | H528: Rice | I528: Sheath blight | J528: 750 ml/ha | K528: Rice | Sheath blight | 750 ml/ha | L528: 1 | M528: FRAC 6
B529: 50 | C529: Kasugamycin | D529: 1 | E529: Kasumin 2% Liquid | F529: AP-1357 | G529: Shetu Corporation Limited | H529: Chili, Wheat, Mango | I529: Anthracnose, Leaf rust | J529: 0.5 ml/L of water | K529: Chili | Anthracnose | 0.5 ml/L of water Wheat | Leaf rust | 0.5 ml/L of water Mango | Anthracnose | 0.5 ml/L of water | L529: 3 | M529: FRAC 24
B530: 50 | C530: Kasugamycin | D530: 2 | E530: Kaiser 6WP | F530: AP-4730 | G530: Nokon Limited | H530: Tomato | I530: Wilt | J530: 2 g/L of water | K530: Tomato | Wilt | 2 g/L of water | L530: 1 | M530: FRAC 24
B531: 51 | C531: Kasugamycin (4%) + Carbendazim (50%) | D531: 1 | E531: Sunpuma 54WP | F531: AP-5039 | G531: McDonald Bangladesh (Pvt) Limited | H531: Sweer gourd | I531: Powdery mildew | J531: 1.5 g/L of water | K531: Sweer gourd | Powdery mildew | 1.5 g/L of water | L531: 1 | M531: FRAC 24
B532: 51 | C532: Kasugamycin (4%) + Carbendazim (50%) | D532: 2 | E532: Nacsumin 54WP | F532: AP-5396 | G532: National AgriCare Import & Export Ltd | H532: Chili | I532: Anthracnose | J532: 1 g/L of water | K532: Chili | Anthracnose | 1 g/L of water | L532: 1 | M532: FRAC 24
B533: 51 | C533: Kasugamycin (4%) + Carbendazim (50%) | D533: 3 | E533: Kasucar 54WP | F533: AP-5397 | G533: SAM Agro Chemical | H533: Tomato | I533: Wilt | J533: 1.5 g/L of water | K533: Tomato | Wilt | 1.5 g/L of water | L533: 1 | M533: FRAC 24
B534: 52 | C534: Mancozeb | D534: 1 | E534: Nemispore 80WP | F534: AP-166 | G534: ACI Formulations Limited | H534: Potato | I534: Late & Early blight | J534: 2.50 kg/ha | K534: Potato | Late & Early blight | 2.50 kg/ha | L534: 1 | M534: FRAC M3
B535: 52 | C535: Mancozeb | D535: 2 | E535: Pencozeb 80WP | F535: AP-242 | G535: Shetu Pesticides Limited | H535: Potato, Ground nut, Tomato, Mango | I535: Late blight, Tikka rust, Early blight, Anthracnose | J535: 2.24 kg/ha; 2 g/L of water | K535: Potato | Late blight | 2.24 kg/ha Ground nut | Tikka rust | 2 g/L of water Tomato | Early blight | 2 g/L of water Mango | Anthracnose | 2 g/L of water | L535: 4 | M535: FRAC M3
B536: 52 | C536: Mancozeb | D536: 3 | E536: Indofil M 45 | F536: AP-272 | G536: Auto Crop Care Limited | H536: Potato, Onion, Mango | I536: Late blight, Purple blotch, Powdery mildew and Anthracnose | J536: 2 g/L of water | K536: Potato | Late blight | 2 g/L of water Onion | Purple blotch | 2 g/L of water Mango | Powdery mildew and Anthracnose | 2 g/L of water | L536: 3 | M536: FRAC M3
B537: 52 | C537: Mancozeb | D537: 4 | E537: Edcozeb 80WP | F537: AP-273 | G537: Sea Trade Fertilizer Limited | H537: Potato, Tomato, Mango | I537: Late blight, Early blight, Anthracnose | J537: 2 g/L of water | K537: Potato | Late blight | 2 g/L of water Tomato | Early blight | 2 g/L of water Mango | Anthracnose | 2 g/L of water | L537: 3 | M537: FRAC M3
B538: 52 | C538: Mancozeb | D538: 5 | E538: Suncozeb 80WP | F538: AP-352 | G538: Shetu Corporation Limited | H538: Potato, Tomato | I538: Late blight | J538: 2 g/L of water | K538: Potato | Late blight | 2 g/L of water Tomato | Late blight | 2 g/L of water | L538: 2 | M538: FRAC M3
... B587: 52 | C587: Mancozeb | D587: 54 | E587: Sinozeb 80WP | F587: AP-1903 | G587: Surovi Agro Industries Limited | H587: Tomato, Potato | I587: Early blight, Late blight | J587: 2 g/L of water | K587: Tomato | Early blight | 2 g/L of water Potato | Late blight | 2 g/L of water | L587: 2 | M587: FRAC M3
B588: 52 | C588: Mancozeb | D588: 55 | E588: Sukria 80WP | F588: AP-1920 | G588: Fasal Agro Industries Ltd. Potato | I588: Late blight | J588: 2 g/L of water | K588: - | Late blight | 2 g/L of water | L588: 1 | M588: FRAC M3
B589: 52 | C589: Mancozeb | D589: 56 57 | E589: Magnate 80WP | F589: AP-1922 | G589: Rahman Pesticide & Chemicals Co. | H589: Potato | I589: Late blight | J589: 2 g/L of water | K589: Potato | Late blight | 2 g/L of water | L589: 1 | M589: FRAC M3
B590: 52 | C590: Mancozeb | E590: Sinewzeb 80WP | F590: AP-1923 | G590: Super Agro Services Co. Ltd. | H590: Potato | I590: Late blight | J590: 2 g/L of water | K590: Potato | Late blight | 2 g/L of water | L590: 1 | M590: FRAC M3
B591: 52 | C591: Mancozeb | D591: 58 59 | E591: Smartzeb 80WP | F591: AP-1925 | G591: Smart Agrovet | H591: Potato | I591: Late blight | J591: 2 g/L of water | K591: Potato | Late blight | 2 g/L of water | L591: 1 | M591: FRAC M3
B592: 52 | C592: Mancozeb | E592: Naczeb 80WP | F592: AP-1928 | G592: National AgriCare Import & Export Ltd | H592: Potato | I592: Late blight | J592: 2 g/L of water | K592: Potato | Late blight | 2 g/L of water | L592: 1 | M592: FRAC M3
B593: 52 | C593: Mancozeb | D593: 60 | E593: Jazz 80WP | F593: AP-2001 | G593: Syngenta Bangladesh Limited | H593: Tomato, Potato, Mango | I593: Late &Early blight, Late blight, Anthracnose | J593: 2 g/L of water | K593: Tomato | Late &Early blight | 2 g/L of water Potato | Late blight | 2 g/L of water Mango | Anthracnose | 2 g/L of water | L593: 3 | M593: FRAC M3
B594: 52 | C594: Mancozeb | D594: 61 | E594: Rekazeb 80WP | F594: AP-2140 | G594: T H Pesticides | H594: Tea, Potato | I594: Die back, Black rot, Late blight | J594: 2.00 kg/ha; 1.5 g/L of water | K594: Tea | Die back, Black rot | 2.00 kg/ha Potato | Late blight | 1.5 g/L of water | L594: 2 | M594: FRAC M3
B595: 52 | C595: Mancozeb | D595: 62 | E595: Encozeb 80WP | F595: AP-2142 | G595: Chemist Crop Care Ltd. | H595: Onion, Tomato | I595: Purple Bloch, Late &Early blight | J595: 2 g/L of water | K595: Onion | Purple Bloch | 2 g/L of water Tomato | Late &Early blight | 2 g/L of water | L595: 2 | M595: FRAC M3
B596: 52 | C596: Mancozeb | D596: 63 | E596: Cleanzeb 80WP | F596: AP-2143 | G596: Clean Agro | H596: Tomato | I596: Late & Early blight | J596: 2 g/L of water | K596: Tomato | Late & Early blight | 2 g/L of water | L596: 1 | M596: FRAC M3
...

Sheet Insecticide
B2: Registered Insecticides in Bangladesh — up to 81st PTAC Meeting
B4: SL No (Common Name) | C4: Common Name | D4: SL No (Products) | E4: Brand Name | F4: Registration No | G4: Registration Holder | H4: Recommended Crops | I4: Recommended Pests | J4: Dosage Rate | K4: Recommendations (Crop | Pest | Dosage) | L4: No. of Recommendations | M4: MoA Code
B5: 1 | C5: Abamectin | D5: 1 | E5: Vertimec 1.8EC | F5: AP-890 | G5: Syngenta Bangladesh Limited | H5: Tea, Brinjal, Jujube, Litchi | I5: Red spider mite, Mite | J5: 1.25 L/ha; 1.20 L/ha; 1.25 ml/L of water | K5: Tea | Red spider mite | 1.25 L/ha Brinjal | Red spider mite | 1.20 L/ha Jujube, Litchi | Mite | 1.25 ml/L of water | L5: 3 | M5: IRAC 6
B6: 1 | C6: Abamectin | D6: 2 | E6: Abom 1.8EC | F6: AP-891 | G6: McDonald Crop Care Ltd. | H6: Tea, Rice, Brinjal | I6: Red spider mite, BPH | J6: 500 ml/ha; 1.2 ml/L of water | K6: Tea | Red spider mite | 500 ml/ha Rice | BPH | 500 ml/ha Brinjal | Red spider mite | 1.2 ml/L of water | L6: 3 | M6: IRAC 6
B7: 1 | C7: Abamectin | D7: 3 | E7: Abatin 1.8EC | F7: AP-1017 | G7: National AgriCare Import & Export Ltd | H7: Cotton | I7: Bollworm (Spotted & American) | J7: 1250-1500 ml/ha | K7: Cotton | Bollworm (Spotted & American) | 1250-1500 ml/ha | L7: 1 | M7: IRAC 6
B8: 1 | C8: Abamectin | D8: 4 | E8: Sunmectin 1.8EC | F8: AP-1034 | G8: Auto Crop Care Limited | H8: Tea, Cotton, Rice, Brinjal | I8: Red spider mite, Helopeltis (Mosquito bug), Bollworm, Aphid, Jassid, BPH, Red spider mites | J8: 1.25 L/ha; 1.20 L/ha; 1.50 L/ha; 1.0 L/ha; 1.20 ml/L of water | K8: Tea | Red spider mite | 1.25 L/ha Tea | Helopeltis (Mosquito bug) | 1.20 L/ha Cotton | Bollworm, Aphid, Jassid | 1.50 L/ha Rice | BPH | 1.0 L/ha Brinjal | Red spider mites | 1.20 ml/L of water | L8: 5 | M8: IRAC 6
B9: 1 | C9: Abamectin | D9: 5 | E9: Kraft 1.8EC | F9: AP-1141 | G9: Oroni International Limited | H9: Brinjal | I9: Red spider mite | J9: 1.20 ml/L of water | K9: Brinjal | Red spider mite | 1.20 ml/L of water | L9: 1 | M9: IRAC 6
B10: 1 | C10: Abamectin | D10: 6 | E10: Toptin 1.8EC | F10: AP-1153 | G10: East West Chemicals Ltd. | H10: Rice | I10: BPH & Hispa | J10: 1.0 L/ha | K10: Rice | BPH & Hispa | 1.0 L/ha | L10: 1 | M10: IRAC 6
B11: 1 | C11: Abamectin | D11: 7 | E11: Licar 1.8EC | F11: AP-1206 | G11: Corbel International Limited | H11: Rice | I11: BPH & Hispa | J11: 1.0 L/ha | K11: Rice | BPH & Hispa | 1.0 L/ha | L11: 1 | M11: IRAC 6
B12: 1 | C12: Abamectin | D12: 8 | E12: Ambush 1.8EC | F12: AP-1241 | G12: Haychem (Bangladesh) Limited | H12: Tea, Rice, Brinjal | I12: Red spider mite, BPH | J12: 1.25 L/ha; 1.0 L/ha; 1.20 ml/L of water | K12: Tea | Red spider mite | 1.25 L/ha Rice | BPH | 1.0 L/ha Brinjal | Red spider mite | 1.20 ml/L of water | L12: 3 | M12: IRAC 6
B13: 1 | C13: Abamectin | D13: 9 | E13: Lakad 1.8EC | F13: AP-1282 | G13: Intefa | H13: Tea, Brinjal | I13: Red spider mite | J13: 1.25 L/ha; 1.20 ml/Lof water | K13: Tea | Red spider mite | 1.25 L/ha Brinjal | Red spider mite | 1.20 ml/Lof water | L13: 2 | M13: IRAC 6
B14: 1 | C14: Abamectin | D14: 10 | E14: Acamite 1.8EC | F14: AP-1286 | G14: ACI Formulations Limited | H14: Tea, Rice | I14: Red spider mite, BPH | J14: 1.25 L/ha; 1.00 L/ha | K14: Tea | Red spider mite | 1.25 L/ha Rice | BPH | 1.00 L/ha | L14: 2 | M14: IRAC 6
B15: 1 | C15: Abamectin | D15: 11 | E15: Alba 1.8EC | F15: AP-1467 | G15: SAMP Limited | H15: Rice | I15: BPH, Hispa | J15: 1.00 L/ha | K15: Rice | BPH, Hispa | 1.00 L/ha | L15: 1 | M15: IRAC 6
B16: 1 | C16: Abamectin | D16: 12 | E16: Iprotin 1.8EC | F16: AP-1509 | G16: Surovi Agro Industries Limited | H16: Tea | I16: Red spider mite | J16: 500 ml/ha | K16: Tea | Red spider mite | 500 ml/ha | L16: 1 | M16: IRAC 6
... B135: 2 | C135: Abamectin (1%) + acetamiprid (3%) | D135: 10 | E135: Forway 4EC | F135: AP-4918 | G135: Forward International (BD) Ltd. | H135: Rice | I135: BPH | J135: 1.0 L/ha | K135: Rice | BPH | 1.0 L/ha | L135: 1 | M135: IRAC 6
C136: (1.80%) + (15.00%) | D136: 11 | E136: Keratin 4EC | F136: AP-4919 | G136: Nafis Crop Care | H136: Rice | I136: BPH | J136: 1.0 L/ha | K136: Rice | BPH | 1.0 L/ha | L136: 1
C137: (1.80%) + (15.00%) | D137: 12 | E137: Sunabaprid 4EC | F137: AP-5230 | G137: McDonald Bangladesh (Pvt) Limited | H137: Tea, Brinjal | I137: Red spider mite | J137: 500 ml/ha; 1 ml/L of water | K137: Tea | Red spider mite | 500 ml/ha Brinjal | Red spider mite | 1 ml/L of water | L137: 2
C138: (1.80%) + (15.00%) | D138: 13 | E138: Descopritin 4EC | F138: AP-5562 | G138: Desh Agro Services Company Ltd. | H138: Rice | I138: BPH | J138: 1.0 L/ha | K138: Rice | BPH | 1.0 L/ha | L138: 1
C139: (1.80%) + (15.00%) | D139: 14 | E139: Abaprid 4EC | F139: AP-5563 | G139: Nature & Care Agro Products Ltd. | H139: Rice | I139: BPH | J139: 1.0 L/ha | K139: Rice | BPH | 1.0 L/ha | L139: 1
C140: (1.80%) + (15.00%) | D140: 15 | E140: Impede Plus 16.80EC | F140: AP-5565 | G140: Fasal Agro Industries Ltd | H140: Tea | I140: Red spider mite | J140: 250 ml/ | K140: Tea | Red spider mite | 250 ml/ | L140: 1
C141: (1.80%) + (15.00%) | D141: 16 | E141: Carbotin 4EC | F141: AP-5715 | G141: ICI Agri Care | H141: Brinjal | I141: Aphid | J141: 0.3 ml/L of water | K141: Brinjal | Aphid | 0.3 ml/L of water | L141: 1
C142: (1.80%) + (15.00%) | D142: 17 | E142: Faand 4EC | F142: AP-5901 | G142: Farmtech Bangladesh | H142: Rice | I142: BPH | J142: 1.0 L/ha | K142: Rice | BPH | 1.0 L/ha | L142: 1
B143: 3 | C143: Abamectin (1%) + Beta Cypermethrin (2%) | D143: 1 | E143: Emithrin Plus 3WDG | F143: AP-2066 | G143: Eminence Chemical Industries Ltd | H143: Tea | I143: Helopeltis | J143: 1 g/Lof water | K143: Tea | Helopeltis | 1 g/Lof water | L143: 1 | M143: IRAC 6
B144: 3 | C144: Abamectin (1%) + Beta Cypermethrin (2%) | D144: 2 | E144: Abaryl 3WDG | F144: AP-3507 | G144: Rahman Pesticide & Chemicals Co. | H144: Cotton | I144: Aphid, Jassid, Bollworm | J144: 100 gm/ha | K144: Cotton | Aphid, Jassid, Bollworm | 100 gm/ha | L144: 1 | M144: IRAC 6
B145: 3 | C145: Abamectin (1%) + Beta Cypermethrin (2%) | D145: 3 | E145: Aabata 3WDG | F145: AP-3508 | G145: Sweet Agrovet Limited | H145: Cotton | I145: Aphid, Jassid, Bollworm | J145: 100 gm/ha | K145: Cotton | Aphid, Jassid, Bollworm | 100 gm/ha | L145: 1 | M145: IRAC 6
B146: 3 | C146: Abamectin (1%) + Beta Cypermethrin (2%) | D146: 4 | E146: Betathrin 3WDG | F146: AP-3878 | G146: FIK Agro Products | H146: Country Bean | I146: Aphid | J146: 1 g/Lof water | K146: Country Bean | Aphid | 1 g/Lof water | L146: 1 | M146: IRAC 6
B147: 3 | C147: Abamectin (1%) + Beta Cypermethrin (2%) | D147: 5 | E147: Fasthrin 3WDG | F147: AP-3879 | G147: Fasal Agro Industries Ltd | H147: Tea | I147: Aphid | J147: 500 gm/ha | K147: Tea | Aphid | 500 gm/ha | L147: 1 | M147: IRAC 6
B148: 3 | C148: Abamectin (1%) + Beta Cypermethrin (2%) | D148: 6 | E148: Vico Plus 3WDG | F148: AP-3881 | G148: Nahar Agro International | H148: Country Bean, Tea | I148: Aphid, Red spider mite | J148: 0.5 gl/L of water; 1.25 Kg/ha | K148: Country Bean | Aphid | 0.5 gl/L of water Tea | Red spider mite | 1.25 Kg/ha | L148: 2 | M148: IRAC 6
B149: 3 | C149: Abamectin (1%) + Beta Cypermethrin (2%) | D149: 7 | E149: Goldimithrin Plus 3WDG | F149: AP-3882 | G149: Golden Agro Chemicals Limited | H149: Country Bean | I149: Aphid | J149: 1 g/Lof water | K149: Country Bean | Aphid | 1 g/Lof water | L149: 1 | M149: IRAC 6
B150: 3 | C150: Abamectin (1%) + Beta Cypermethrin (2%) | D150: 8 | E150: Pathrin 3WDG | F150: AP-3883 | G150: Marshal Agrovet Chemical Industries Ltd. | H150: Country Bean | I150: Aphid | J150: 1 g/Lof water | K150: Country Bean | Aphid | 1 g/Lof water | L150: 1 | M150: IRAC 6
B151: 3 | C151: Abamectin (1%) + Beta Cypermethrin (2%) | D151: 9 | E151: Ayesha 3WGD | F151: AP-4013 | G151: Genetica Industries Ltd. | H151: Tea | I151: Helopeltis | J151: 1.25 Kg/ha | K151: Tea | Helopeltis | 1.25 Kg/ha | L151: 1 | M151: IRAC 6
B152: 3 | C152: Abamectin (1%) + Beta Cypermethrin (2%) | D152: 10 | E152: Betatin 3WDG | F152: AP-4014 | G152: Aranya Crop Care Limited | H152: Tea, Potato | I152: Helopeltis, Aphid | J152: 1.25 Kg/ha; 0.5 gl/L of water | K152: Tea | Helopeltis | 1.25 Kg/ha Potato | Aphid | 0.5 gl/L of water | L152: 2 | M152: IRAC 6
B153: 3 | C153: Abamectin (1%) + Beta Cypermethrin (2%) | D153: 11 | E153: Adam Plus 3WDG | F153: AP-4015 | G153: Krishi Crop Care Limited | H153: Tea | I153: Helopeltis | J153: 1.25 Kg/ha | K153: Tea | Helopeltis | 1.25 Kg/ha | L153: 1 | M153: IRAC 6
B154: 3 | C154: Abamectin (1%) + Beta Cypermethrin (2%) | D154: 12 | E154: Achamka 3WDG | F154: AP-4016 | G154: Gurpukur Corporation | H154: Tea, Brinjal | I154: Aphid | J154: 500 gm/ha; 0.5 gl/L of water | K154: Tea | Aphid | 500 gm/ha Brinjal | Aphid | 0.5 gl/L of water | L154: 2 | M154: IRAC 6
... B171: 3 | C171: Abamectin (1%) + Beta Cypermethrin (2%) | D171: 29 | E171: Magot 3WDG | F171: AP-4533 | G171: Mosco Marketing Company | H171: Tea | I171: Aphid | J171: 500 gm/ha | K171: Tea | Aphid | 500 gm/ha | L171: 1 | M171: IRAC 6
C172: (0.6% + 1.55%) | D172: 30 | E172: Tufan 3WDG | F172: AP-4534 | G172: SARK Bangladesh | H172: Tea, Bean | I172: Helopeltis, Aphid | J172: 1.25 Kg/ha; 1 g/Lof water | K172: Tea | Helopeltis | 1.25 Kg/ha Bean | Aphid | 1 g/Lof water | L172: 2
C173: (0.6% + 1.55%) | D173: 31 | E173: Dimithrin Plus 3WDG | F173: AP-4535 | G173: D M Crop Care Limited | H173: Tea, Mango | I173: Helopeltis, Hopper | J173: 1.25 Kg/ha; 1 g/Lof water | K173: Tea | Helopeltis | 1.25 Kg/ha Mango | Hopper | 1 g/Lof water | L173: 2
C174: (0.6% + 1.55%) | D174: 32 | E174: M-Thrin Plus 3WDG | F174: AP-4536 | G174: Mamun Agro Products Ltd. | H174: Tea | I174: Aphid | J174: 500 gm/ha | K174: Tea | Aphid | 500 gm/ha | L174: 1
C175: (0.6% + 1.55%) | D175: 33 | E175: SB Marvel 3WDG | F175: AP-4930 | G175: SB Crop Care Industries Ltd. | H175: Bean | I175: Aphid | J175: 1 g/Lof water | K175: Bean | Aphid | 1 g/Lof water | L175: 1
C176: (0.6% + 1.55%) | D176: 34 | E176: Operation 3WDG | F176: AP-4931 | G176: Jass Agro Limited | H176: Tea | I176: Red spider mite | J176: 500 gm/ha | K176: Tea | Red spider mite | 500 gm/ha | L176: 1
C177: (0.6% + 1.55%) | D177: 35 | E177: Acamite Plus 3WDG | F177: AP-4933 | G177: ACI Formulations Limited | H177: Tea | I177: Helopeltis | J177: 1.25 Kg/ha | K177: Tea | Helopeltis | 1.25 Kg/ha | L177: 1
C178: (0.6% + 1.55%) | D178: 36 | E178: Ricothrin 3WG | F178: AP-4934 | G178: Rico Agrovet | H178: Tea | I178: Aphid | J178: 500 gm/ha | K178: Tea | Aphid | 500 gm/ha | L178: 1
C179: (0.6% + 1.55%) | D179: 37 | E179: Binta 2EC | F179: AP-4935 | G179: McDonald Bangladesh (Pvt) Limited | H179: Tea | I179: Red spider mite | J179: 500 ml/ha | K179: Tea | Red spider mite | 500 ml/ha | L179: 1
C180: (0.6% + 1.55%) | D180: 38 | E180: Lupin Plus 3WDG | F180: AP-5231 | G180: Valent Tech Limited | H180: Tea | I180: Aphid | J180: 500 gm/ha | K180: Tea | Aphid | 500 gm/ha | L180: 1
C181: (0.6% + 1.55%) | D181: 39 | E181: Cyba Plus 3WDG | F181: AP-5232 | G181: Krishok Bondhu Agro Ltd. | H181: Jute | I181: Hairy Caterpillar | J181: 250 gm/ha | K181: Jute | Hairy Caterpillar | 250 gm/ha | L181: 1
C182: (0.6% + 1.55%) | D182: 40 | E182: Force Cyper 4.5EC | F182: AP-5233 | G182: Forward International (BD) Ltd. | H182: Cotton | I182: Aphid, Jassid, Bollworm | J182: 500 ml/ha | K182: Cotton | Aphid, Jassid, Bollworm | 500 ml/ha | L182: 1
C183: (0.6% + 1.55%) | D183: 41 | E183: Naturethrin 3WDG | F183: AP-5234 | G183: Nature Care Manufacturing Industries Ltd. | H183: Tea | I183: Aphid | J183: 250 gm/ha | K183: Tea | Aphid | 250 gm/ha | L183: 1
... C194: (0.6% + 1.55%) | D194: 52 | E194: Abacyper 3WDG | F194: AP-5907 | G194: Take Care | H194: Tea | I194: Mosquito bug | J194: 1.25 Kg/ha | K194: Tea | Mosquito bug | 1.25 Kg/ha | L194: 1
B195: 4 | C195: Abamectin (2%) + Matrine (1%) | D195: 1 | E195: Nitex 3WG | F195: AP-2612 | G195: Mimpex Agrochemicals Limited | H195: Cotton | I195: Aphid, Bollworm | J195: 600 ml/ha | K195: Cotton | Aphid, Bollworm | 600 ml/ha | L195: 1 | M195: IRAC 6
B196: 5 | C196: Abamectin (0.3%) + Propargite (39.7%) | D196: 1 | E196: Zeromite 40EC | F196: AP-3457 | G196: Eon Agro Industries Limited | H196: Tea | I196: Red spider mite | J196: 1.0 L/ha | K196: Tea | Red spider mite | 1.0 L/ha | L196: 1 | M196: IRAC 6
B197: 5 | C197: Abamectin (0.3%) + Propargite (39.7%) | D197: 2 | E197: Abazite 40EC | F197: AP-3894 | G197: SARK Bangladesh | H197: Rice | I197: BPH | J197: 1.0 L/ha | K197: Rice | BPH | 1.0 L/ha | L197: 1 | M197: IRAC 6
B198: 5 | C198: Abamectin (0.3%) + Propargite (39.7%) | D198: 3 | E198: Hana 40EC | F198: AP-4921 | G198: Genetica Industries Ltd. | H198: Tea, Rice | I198: Red spider mite, BPH | J198: 1.0 L/ha | K198: Tea | Red spider mite | 1.0 L/ha Rice | BPH | 1.0 L/ha | L198: 2 | M198: IRAC 6
B199: 5 | C199: Abamectin (0.3%) + Propargite (39.7%) | D199: 4 | E199: Yeorkarr 25EC | F199: AP-6033 | G199: Basic Agrovet | H199: Jute | I199: Yellow mite | J199: 280 ml/ha | K199: Jute | Yellow mite | 280 ml/ha | L199: 1 | M199: IRAC 6
B200: 6 | C200: Abamectin (2%) + Imidacloprid (36%) (1% + 9%) (5% + 50%) | D200: 1 | E200: Lahib 38WDG | F200: AP-3845 | G200: Intefa | H200: Rice, Country Bean, Tea | I200: BPH, Aphid, Helopeltis | J200: 75 gm/ha; 0.1 g/L of water; 100 gm/ha | K200: Rice | BPH | 75 gm/ha Country Bean | Aphid | 0.1 g/L of water Tea | Helopeltis | 100 gm/ha | L200: 3 | M200: IRAC 6
B201: 6 | C201: Abamectin (2%) + Imidacloprid (36%) (1% + 9%) (5% + 50%) | D201: 2 | E201: Abagin 10EC | F201: AP-4571 | G201: Getco Agri Technologies Ltd. | H201: Tea, Cotton | I201: Red spider mite, Aphid | J201: 500 ml/ha | K201: Tea | Red spider mite | 500 ml/ha Cotton | Aphid | 500 ml/ha | L201: 2 | M201: IRAC 6
B202: 6 | C202: Abamectin (2%) + Imidacloprid (36%) (1% + 9%) (5% + 50%) | D202: 3 | E202: Abshara 38WDG | F202: AP-4572 | G202: Alif Agro | H202: Chilli | I202: Aphid & Jassid | J202: 50 gm/ha | K202: Chilli | Aphid & Jassid | 50 gm/ha | L202: 1 | M202: IRAC 6
B203: 6 | C203: Abamectin (2%) + Imidacloprid (36%) (1% + 9%) (5% + 50%) | D203: 4 | E203: Flare 38WDG | F203: AP-5589 | G203: Roof Crop Care Ltd. | H203: Jute, Rice | I203: Yellow Mite, BPH | J203: 350 gm/ha; 75 gm/ha | K203: Jute | Yellow Mite | 350 gm/ha Rice | BPH | 75 gm/ha | L203: 2 | M203: IRAC 6
B204: 6 | C204: Abamectin (2%) + Imidacloprid (36%) (1% + 9%) (5% + 50%) | D204: 5 | E204: Abamid 38WDG | F204: AP-5684 | G204: McDonald Bangladesh (Pvt) Limited | H204: Tea, Rice, Brinjal | I204: Aphid, BPH, Red Spider Mite | J204: 250 gm/ha; 125 gm/ha; 0.5 g/L of water | K204: Tea | Aphid | 250 gm/ha Rice | BPH | 125 gm/ha Brinjal | Red Spider Mite | 0.5 g/L of water | L204: 3 | M204: IRAC 6
B205: 6 | C205: Abamectin (2%) + Imidacloprid (36%) (1% + 9%) (5% + 50%) | D205: 6 | E205: Aba Imi Baba 55WDG | F205: AP-5685 | G205: SARK Bangladesh | H205: Bean, Rice | I205: Aphid, BPH | J205: 1 g/10 L of water; 75 gm/ha | K205: Bean | Aphid | 1 g/10 L of water Rice | BPH | 75 gm/ha | L205: 2 | M205: IRAC 6
B206: 6 | C206: Abamectin (2%) + Imidacloprid (36%) (1% + 9%) (5% + 50%) | D206: 7 | E206: Bandit 32.5SC | F206: AP-5900 | G206: Khan Agricultural Products Ltd. | H206: Brinjal | I206: Red mite | J206: 0.5 ml/L of water | K206: Brinjal | Red mite | 0.5 ml/L of water | L206: 1 | M206: IRAC 6
... B291: 24 | C291: Bifenthrin (11.25%) Zeta Cypermethrin (1.75%) | D291: 1 | E291: Sunbizt 15EC | F291: AP-6047 | G291: Ostrich Agro Chemicals Ltd. | H291: Mango | I291: Hopper | J291: 1 ml/L of water | K291: Mango | Hopper | 1 ml/L of water | L291: 1 | M291: IRAC 3A
B292: 25 | C292: Lufenuron (30%) + Bifenthrin (2.5%) | D292: 1 | E292: Sunorien 32.5EC | F292: AP-5543 | G292: Sun Seed Pesticides | H292: Jute | I292: Hairy Caterpillar | J292: 400 ml/ha | K292: Jute | Hairy Caterpillar | 400 ml/ha | L292: 1
B293: 26 | C293: Abamectin (1%) + Hexythiazox (2) | D293: 1 | E293: Akash 3ME | F293: AP-5249 | G293: Global Agrovet Limited | H293: Tea | I293: Red Spider Mite | J293: 500 L/ha | K293: Tea | Red Spider Mite | 500 L/ha | L293: 1 | M293: IRAC 6
B294: 27 | C294: Buprofezin | D294: 1 | E294: Sunprozin 40SC | F294: AP-1321 | G294: Oroni International Limited | H294: Bean | I294: Aphid | J294: 0.5 ml/Lof water | K294: Bean | Aphid | 0.5 ml/Lof water | L294: 1 | M294: IRAC 16
B295: 27 | C295: Buprofezin | D295: 2 | E295: Sunfezin 40WP | F295: AP-2311 | G295: Raven Agro Chemicals Limited | H295: Cotton | I295: Aphid, Jassid | J295: 120 gm/ha | K295: Cotton | Aphid, Jassid | 120 gm/ha | L295: 1 | M295: IRAC 16
B296: 27 | C296: Buprofezin | D296: 3 | E296: Award 40SC | F296: AP-2760 | G296: Square Pharmaceuticals Limited | H296: Rice | I296: BPH | J296: 250 ml/ha | K296: Rice | BPH | 250 ml/ha | L296: 1 | M296: IRAC 16
B297: 27 | C297: Buprofezin | D297: 4 | E297: Chentor 40SC | F297: AP-3422 | G297: Maitri Agro Industries | H297: Tea | I297: Helopeltis | J297: 1.00 L/ha | K297: Tea | Helopeltis | 1.00 L/ha | L297: 1 | M297: IRAC 16
B298: 27 | C298: Buprofezin | D298: 5 | E298: Tacoma 40SC | F298: AP-3790 | G298: Auto Crop Care Limited | H298: Tea, Rice | I298: Aphid, BPH | J298: 400 ml/ha; 250 ml/ha | K298: Tea | Aphid | 400 ml/ha Rice | BPH | 250 ml/ha | L298: 2 | M298: IRAC 16
B299: 27 | C299: Buprofezin | D299: 6 | E299: Essence Hot 40SC | F299: AP-5004 | G299: Clean Agro | H299: Bean | I299: Aphid | J299: 0.5 ml/L of water | K299: Bean | Aphid | 0.5 ml/L of water | L299: 1 | M299: IRAC 16
B300: 27 | C300: Buprofezin | D300: 7 | E300: Bolo 25SC | F300: AP-5985 | G300: RiceCo International Bangladesh Ltd. | H300: Rice | I300: BPH | J300: 500 ml/ha | K300: Rice | BPH | 500 ml/ha | L300: 1 | M300: IRAC 16
B301: 28 | C301: Buprofezin (40%) + Emamectin Benzoate (10%) | D301: 1 | E301: Memozin 50WP | F301: AP-5003 | G301: Sun Seed Pesticides | H301: Rice | I301: Yellow Stemborer | J301: 150 gm/ha | K301: Rice | Yellow Stemborer | 150 gm/ha | L301: 1 | M301: IRAC 16
B302: 29 | C302: Isoprocarb (20%) + Buprofezin (5%) | D302: 1 | E302: Lamah 25WP | F302: AP-4091 | G302: Intefa | H302: Rice, Jute | I302: BPH, Yellow Stemborer | J302: 0.5 kg/ha; 500 gm/ha | K302: Rice | BPH | 0.5 kg/ha Jute | Yellow Stemborer | 500 gm/ha | L302: 2 | M302: IRAC 1A
B303: 30 | C303: Buprofezin (40%) + Pymetrozine (20%) | D303: 1 | E303: Torry 60WDG | F303: AP-6043 | G303: R S Square Corporation | H303: Rice | I303: BPH | K303: Rice | BPH | - | L303: 1 | M303: IRAC 16
B304: 31 | C304: Isoprocarb (22%) Thiamethaxam (3%) | D304: 1 | E304: Genecarb 25WP | F304: AP-6018 | G304: General Agro Chemicals Ltd | H304: Rice | I304: BPH | J304: 0.60 kg/ha | K304: Rice | BPH | 0.60 kg/ha | L304: 1 | M304: IRAC 1A
B305: 32 | C305: Cadusafos | D305: 1 | E305: Rugby 10G | F305: AP-484 | G305: Shetu Pesticides Limited | H305: Tobacco, Sugarcane, Tea | I305: Nematodes, Termites, White grubs, Root Stock Borer, Nematode | J305: 15.00 kg/ha; 20.00 kg/ha; 150 g/m3 soil | K305: Tobacco | Nematodes | 15.00 kg/ha Sugarcane | Termites | 20.00 kg/ha Sugarcane | White grubs | 15.00 kg/ha Sugarcane | Root Stock Borer | 20.00 kg/ha Tea | Nematode | 150 g/m3 soil | L305: 5 | M305: IRAC 1B
B306: 32 | C306: Cadusafos | D306: 2 | E306: Apache 5G | F306: AP-4537 | G306: Auto Crop Care Limited | H306: Tea | I306: Nematode | J306: 300 g/m3 soil | K306: Tea | Nematode | 300 g/m3 soil | L306: 1 | M306: IRAC 1B
B307: 33 | C307: Carbaryl | D307: 1 | E307: Sevin 85SP | F307: AP-338 | G307: Bayer CropScience Limited | H307: Rice, Jute, Vegetables, Mango | I307: Leaf roller, Case worm, GLH, Thrips, Hispa & Rice bug, Caterpillar, Ear cutting caterpillar, Hairy caterpillar, weevil, Semilooper, Leaf eating caterpillar, Hoppers | J307: 1.70 kg/ha; 1 g/L of water | K307: Rice | Leaf roller, Case worm, GLH, Thrips, Hispa & Rice bug, Caterpillar, Ear cutting caterpillar | 1.70 kg/ha Jute | Hairy caterpillar, weevil, Semilooper | 1.70 kg/ha Vegetables | Leaf eating caterpillar | 1.70 kg/ha Mango | Hoppers | 1 g/L of water | L307: 4 | M307: IRAC 1A
B308: 33 | C308: Carbaryl | D308: 2 | E308: Vitabryl 85WP | F308: AP-401 | G308: McDonald Bangladesh (Pvt) Limited | H308: Jute, Rice, Mango | I308: Hairy caterpillar, BPH, Hopper | J308: 0.25% a.i./ha; 1.50 kg/ha; 1 g/L of water | K308: Jute | Hairy caterpillar | 0.25% a.i./ha Rice | BPH | 1.50 kg/ha Mango | Hopper | 1 g/L of water | L308: 3 | M308: IRAC 1A
B309: 33 | C309: Carbaryl | D309: 3 | E309: Kalvin 85WP | F309: AP-1232 | G309: Aungkur Traders | H309: Tea, Rice, Jute | I309: Helopeltis, BPH, Hairy caterpillar | J309: 1.00 kg/ha; 1.70 kg/ha; 1.50 kg/ha | K309: Tea | Helopeltis | 1.00 kg/ha Rice | BPH | 1.70 kg/ha Jute | Hairy caterpillar | 1.50 kg/ha | L309: 3 | M309: IRAC 1A
B310: 33 | C310: Carbaryl | D310: 4 | E310: Ravin 85WP | F310: AP-1496 | G310: Sea Trade Fertilizer Limited | H310: Jute, Rice | I310: Hairy caterpillar, BPH | J310: 500 gm/ha; 1.50 gm/ha | K310: Jute | Hairy caterpillar | 500 gm/ha Rice | BPH | 1.50 gm/ha | L310: 2 | M310: IRAC 1A
B311: 33 | C311: Carbaryl | D311: 5 | E311: Coral 85WP | F311: AP-1710 | G311: Agro Continent Bangladesh | H311: Rice | I311: BPH | J311: 1.50 kg/ha | K311: Rice | BPH | 1.50 kg/ha | L311: 1 | M311: IRAC 1A
B312: 33 | C312: Carbaryl | D312: 6 | E312: Pilot 85WP | F312: AP-1720 | G312: Anika Enterprises | H312: Rice, Tea | I312: BPH, Helopeltis, Hairy caterpillar | J312: 1.50 kg/ha; 1.00 kg/ha; 1.70 kg/ha | K312: Rice | BPH | 1.50 kg/ha Tea | Helopeltis | 1.00 kg/ha Tea | Hairy caterpillar | 1.70 kg/ha | L312: 3 | M312: IRAC 1A
B313: 33 | C313: Carbaryl | D313: 7 | E313: Ryl 85WP | F313: AP-2084 | G313: Agro Arena Associates Ltd. | H313: Jute, Tea | I313: Helopeltis | J313: 1.00 kg/ha | K313: Jute | - | - Tea | Helopeltis | 1.00 kg/ha | L313: 2 | M313: IRAC 1A
B314: 33 | C314: Carbaryl | D314: 8 | E314: Reflex 85WP | F314: AP-2203 | G314: Bangladesh Agricultural Industries | H314: Rice | I314: BPH | J314: 1.50 kg/ha | K314: Rice | BPH | 1.50 kg/ha | L314: 1 | M314: IRAC 1A
B315: 33 | C315: Carbaryl | D315: 9 | E315: Jupiter 85WP | F315: AP-2204 | G315: Amco Agricultural Industries | H315: Rice | I315: BPH | J315: 1.50 kg/ha | K315: Rice | BPH | 1.50 kg/ha | L315: 1 | M315: IRAC 1A
... B677: 43 | C677: Acetamiprid (20%) + Imidacloprid (50%) | D677: 1 | E677: Ricomid Plus 70WDG | F677: AP-5243 | G677: Rico Agrovet | H677: Tea, Rice | I677: Aphid, BPH | J677: 500 gm/ha; 25.70 gm/ha | K677: Tea | Aphid | 500 gm/ha Rice | BPH | 25.70 gm/ha | L677: 2 | M677: IRAC 4A
C678: (60% + 10%) | D678: 2 | E678: Nilama 70WDG | F678: AP-5244 | G678: Padma Agro Sprayers Co. | H678: Cotton, Jute | I678: Aphid, Jassids, Hairy Caterpillar, Aphid, Jassid | J678: 125 gm/ha; 100 gm/ha | K678: Cotton | Aphid, Jassids | 125 gm/ha Jute | Hairy Caterpillar | 100 gm/ha Cotton | Aphid, Jassid | 125 gm/ha | L678: 3
C679: (60% + 10%) | D679: 3 | E679: Fame 70WDG | F679: AP-5245 | G679: Haychem (Bangladesh) Limited | H679: Jute, Rice | I679: Hairy Caterpillar, BPH | J679: 100 gm/ha; 50 gm/ha | K679: Jute | Hairy Caterpillar | 100 gm/ha Rice | BPH | 50 gm/ha | L679: 2
B680: 44 | C680: Cartap (47.5%) + Fipronil (2.5%) | D680: 1 | E680: Suntap Plus 50WP | F680: AP-4499 | G680: McDonald Bangladesh (Pvt) Limited | H680: Rice | I680: YSB | J680: 0.75 gm/ha | K680: Rice | YSB | 0.75 gm/ha | L680: 1 | M680: IRAC 14
B681: 45 | C681: Chlorfenapyr | D681: 1 | E681: Intrepid 10SC | F681: AP-2700 | G681: BASF Bangladesh Limited | H681: Brinjal, Chilli, Tea | I681: Red mite, Thirps, Red Spider Mite and Thips | J681: 1 g/L of water; 1.00 L/ha | K681: Brinjal | Red mite | 1 g/L of water Chilli | Thirps | 1 g/L of water Tea | Red Spider Mite and Thips | 1.00 L/ha | L681: 3 | M681: IRAC 13
B682: 46 | C682: Chlorfenapyr (10%) Emamectin Benzoate (2.00) | D682: 1 | E682: Dimension 12SC | F682: AP-6002 | G682: Haychem (Bangladesh) Limited | H682: Jute | I682: Yelow mite | J682: 500 ml/ha | K682: Jute | Yelow mite | 500 ml/ha | L682: 1 | M682: IRAC 13
B683: 47 | C683: Chlorfenapyr (10%) + Fipronil (10%) | D683: 1 | E683: Puni 20WDG | F683: AP-5789 | G683: Roof Crop Care Ltd. | H683: Rice, Jute | I683: BPH, Weevil | J683: 10.00 kg/ha; 225 g/ha | K683: Rice | BPH | 10.00 kg/ha Jute | Weevil | 225 g/ha | L683: 2 | M683: IRAC 13
B684: 48 | C684: Chlorpyrifos | D684: 1 | E684: Dursban 20EC | F684: AP-93 | G684: Auto Crop Care Limited | H684: Rice, Tea, Potato, Cotton, Sugarcane | I684: BPH, Hispa, SB, LR, GH & Rice bug, Termite, Cutworm, Boll worm, Aphid, Jassid | J684: 1.00 L/ha; 7.50 L/ha; 700 ml/ha; 11.25 L/ha | K684: Rice | BPH, Hispa, SB, LR, GH & Rice bug | 1.00 L/ha Tea | Termite | 1.00 L/ha Potato | Cutworm | 7.50 L/ha Cotton | Boll worm, Aphid, Jassid | 700 ml/ha Sugarcane | Termite | 11.25 L/ha | L684: 5 | M684: IRAC 1B
B685: 48 | C685: Chlorpyrifos | D685: 2 | E685: Chlorban 20EC | F685: AP-346 | G685: United Phosphorus (Bangladesh) Ltd | H685: Rice, Tea | I685: Yellow Stemborer & BPH, Termite | J685: 1.00 L/ha; 10.00 L/ha | K685: Rice | Yellow Stemborer & BPH | 1.00 L/ha Tea | Termite | 10.00 L/ha | L685: 2 | M685: IRAC 1B
B686: 48 | C686: Chlorpyrifos | D686: 3 | E686: Chlorpyriphos 20EC | F686: AP-382 | G686: Alpha Agro Limited | H686: Rice, Tea, Cotton, Potato, Sugarcane | I686: Hispa, Termite, Boll worm, Aphid, Jassid, Cutworm | J686: 1.00 L/ha; 10.00 L/ha; 7.50 L/ha; 11.25 L/ha | K686: Rice | Hispa | 1.00 L/ha Tea | Termite | 10.00 L/ha Cotton | Boll worm, Aphid, Jassid | 1.00 L/ha Potato | Cutworm | 7.50 L/ha Sugarcane | Termite | 11.25 L/ha | L686: 5 | M686: IRAC 1B
B687: 48 | C687: Chlorpyrifos | D687: 4 | E687: Shimba 20EC | F687: AP-435 | G687: Nokon Limited | H687: Rice, Tea, Potato, Cotton | I687: Hispa & BPH, Termite, Cutworm, Bollworm, Aphid, Jassid | J687: 1.00 L/ha; 10.00 L/ha; 7.50 L/ha; 700/800 ml/ha | K687: Rice | Hispa & BPH | 1.00 L/ha Tea | Termite | 10.00 L/ha Potato | Cutworm | 7.50 L/ha Cotton | Bollworm, Aphid, Jassid | 700/800 ml/ha | L687: 4 | M687: IRAC 1B
B688: 48 | C688: Chlorpyrifos | D688: 5 | E688: Cyren 50WP | F688: AP-436 | G688: Shetu Corporation Limited | H688: Tea, Sugarcane | I688: Termite | J688: 3.50 kg/ha; 4.50 kg/ha | K688: Tea | Termite | 3.50 kg/ha Sugarcane | Termite | 4.50 kg/ha | L688: 2 | M688: IRAC 1B
B689: 48 | C689: Chlorpyrifos | D689: 6 | E689: Luxan Chlorpyrifos 20EC | F689: AP-344 | G689: Shetu Corporation Limited | H689: Potato, Rice | I689: Cutworm, Hispa, BPH | J689: 7.50 L/ha; 1.00 L/ha | K689: Potato | Cutworm | 7.50 L/ha Rice | Hispa, BPH | 1.00 L/ha | L689: 2 | M689: IRAC 1B
B690: 48 | C690: Chlorpyrifos | D690: 7 | E690: Chlorocid 20EC | F690: AP-466 | G690: Corbel International Limited | H690: Tea, Sugarcane, Rice | I690: Termite, Stemborer, BPH, GLH, LR | J690: 10.00 L/ha; 11.25 L/ha; 1.00 L/ha | K690: Tea | Termite | 10.00 L/ha Sugarcane | Termite | 11.25 L/ha Rice | Stemborer, BPH, GLH, LR | 1.00 L/ha | L690: 3 | M690: IRAC 1B
B691: 48 | C691: Chlorpyrifos | D691: 8 | E691: Cyren 20EC | F691: AP-477 | G691: Shetu Agro Industries Limited | H691: Potato, Sugarcane | I691: Catwarm, Termite | J691: 7.50 L/ha; 11.25 L/ha | K691: Potato | Catwarm | 7.50 L/ha Sugarcane | Termite | 11.25 L/ha | L691: 2 | M691: IRAC 1B
...

Sheet Herbicide
B2: Registered Herbicides in Bangladesh — up to 81st PTAC Meeting
B4: SL No (Common Name) | C4: Common Name | D4: SL No (Products) | E4: Brand Name | F4: Registration No | G4: Registration Holder | H4: Recommended Crops | I4: Recommended Pests | J4: Dosage Rate | K4: Recommendations (Crop | Pest | Dosage) | L4: No. of Recommendations | M4: MoA Code
B5: 1 | C5: 2,4-D Amine | D5: 1 | E5: U 46 D Fluid | F5: AP-243 | G5: BASF Bangladesh Limited | H5: Tea | I5: Mikania creeper, Bagracote | J5: 3.00 L/ha | K5: Tea | Mikania creeper, Bagracote | 3.00 L/ha | L5: 1 | M5: HRAC O
B6: 1 | C6: 2,4-D Amine | D6: 2 | E6: Kem Amin 58SL | F6: AP-482 | G6: Hossain Enterprises C.C. Ltd | H6: Tea | I6: Weed (Dicot) | J6: 2.80 L/ha | K6: Tea | Weed (Dicot) | 2.80 L/ha | L6: 1 | M6: HRAC O
B7: 1 | C7: 2,4-D Amine | D7: 3 | E7: Fielder 48SL | F7: AP-494 | G7: ACI Formulations Limited | H7: Tea, Wheat | I7: Weed (Dicot), C. album, O.europace, R.maritimus, V.hirsuta | J7: 2.80 L/ha | K7: Tea | Weed (Dicot) | 2.80 L/ha Wheat | C. album, O.europace, R.maritimus, V.hirsuta | 2.80 L/ha | L7: 2 | M7: HRAC O
B8: 1 | C8: 2,4-D Amine | D8: 4 | E8: Weedkill 480SL | F8: AP-702 | G8: SAM Agro Chemical | H8: Tea | I8: Weed (Dicot) | J8: 2.80 L/ha | K8: Tea | Weed (Dicot) | 2.80 L/ha | L8: 1 | M8: HRAC O
B9: 1 | C9: 2,4-D Amine | D9: 5 | E9: Salix | F9: AP-929 | G9: Hiron Agro Limited | H9: Rice | I9: Monochoria vaginalis, Ludwigia, octovalvis, Sphenoclea zeylanica | J9: 450 g/acare | K9: Rice | Monochoria vaginalis, Ludwigia, octovalvis, Sphenoclea zeylanica | 450 g/acare | L9: 1 | M9: HRAC O
B10: 1 | C10: 2,4-D Amine | D10: 6 | E10: Weed Clean 480SL | F10: AP-1196 | G10: Eminence Chemical Industries Ltd | H10: Tea | I10: Broad leaves | J10: 2.24 L/ha | K10: Tea | Broad leaves | 2.24 L/ha | L10: 1 | M10: HRAC O
B11: 1 | C11: 2,4-D Amine | D11: 7 | E11: 2,4-D Weeder | F11: AP-1197 | G11: McDonald Bangladesh (Pvt) Limited | H11: Tea | I11: Broad leaves | J11: 2.24 L/ha | K11: Tea | Broad leaves | 2.24 L/ha | L11: 1 | M11: HRAC O
B12: 1 | C12: 2,4-D Amine | D12: 8 | E12: Filder Plus 48SL | F12: AP-2272 | G12: ACI Formulations Limited | H12: Tea | I12: Dicot | J12: 2.80 L/ha | K12: Tea | Dicot | 2.80 L/ha | L12: 1 | M12: HRAC O
B13: 1 | C13: 2,4-D Amine | D13: 9 | E13: Bonmara 480SL | F13: AP-2273 | G13: East West Chemicals Ltd. | H13: Tea | I13: Dicot | J13: 2.80 L/ha | K13: Tea | Dicot | 2.80 L/ha | L13: 1 | M13: HRAC O
B14: 1 | C14: 2,4-D Amine | D14: 10 | E14: Just 48SL | F14: AP-2274 | G14: Sun Seed Pesticides | H14: Tea | I14: Dicot | J14: 2.80 L/ha | K14: Tea | Dicot | 2.80 L/ha | L14: 1 | M14: HRAC O
B15: 1 | C15: 2,4-D Amine | D15: 11 | E15: Chiruni 72SL | F15: AP-2547 | G15: Aama Green Care | H15: Tea | I15: Dicot, Monocot | J15: 2.80 L/ha | K15: Tea | Dicot, Monocot | 2.80 L/ha | L15: 1 | M15: HRAC O
B16: 1 | C16: 2,4-D Amine | D16: 12 | E16: Totomine 72SL | F16: AP-2548 | G16: Home Pest Control | H16: Tea | I16: Dicot, Monocot | J16: 2.80 L/ha | K16: Tea | Dicot, Monocot | 2.80 L/ha | L16: 1 | M16: HRAC O
... B107: 5 | C107: Bensulfuron methyl (4%) + Acetochlor (14%) | D107: 63 | E107: TP-Link 18WP | F107: AP-5179 | G107: ADR Crop Care | H107: Tea | I107: B.hispida, I.cylindrica | J107: 3.00 kg/ha | K107: Tea | B.hispida, I.cylindrica | 3.00 kg/ha | L107: 1 | M107: HRAC B
C108: (26% + 4%) | D108: 64 | E108: Serfclean 18WP | F108: AP-5181 | G108: Serf Agro Industries | H108: Tea | I108: B.hispida, I.cylindrica | J108: 3.00 kg/ha | K108: Tea | B.hispida, I.cylindrica | 3.00 kg/ha | L108: 1
C109: (26% + 4%) | D109: 65 | E109: Superfine 18WP | F109: AP-5182 | G109: Super Crop Care Ltd. | H109: Tea | I109: B.hispida, I.cylindrica | J109: 3.00 kg/ha | K109: Tea | B.hispida, I.cylindrica | 3.00 kg/ha | L109: 1
C110: (26% + 4%) | D110: 66 | E110: Dix 18WP | F110: AP-5183 | G110: Agro Link BD | H110: Tea | I110: B.hispida, I.cylindrica | J110: 3.00 kg/ha | K110: Tea | B.hispida, I.cylindrica | 3.00 kg/ha | L110: 1
C111: (26% + 4%) | D111: 67 | E111: Sky Blue 18WP | F111: AP-5184 | G111: The Sky Agro Products | H111: Tea | I111: B.hispida, I.cylindrica | J111: 3.00 kg/ha | K111: Tea | B.hispida, I.cylindrica | 3.00 kg/ha | L111: 1
C112: (26% + 4%) | D112: 68 | E112: Bendar 18WP | F112: AP-5185 | G112: Super Agro Services Co. Ltd. | H112: Onion | I112: E. crus-galli, C. rotundus, D. san | J112: 2.5 Kg/ha | K112: Onion | E. crus-galli, C. rotundus, D. san | 2.5 Kg/ha | L112: 1
C113: (26% + 4%) | D113: 69 | E113: Georjerice Gold 18WP | F113: AP-5186 | G113: Kohinoor Agro Chemicals | H113: Rice | I113: E. crus-galli, M.vaginalis | J113: 750 g/ha | K113: Rice | E. crus-galli, M.vaginalis | 750 g/ha | L113: 1
C114: (26% + 4%) | D114: 70 | E114: Boomer 18WP | F114: AP-5187 | G114: Agro Business Support Ltd. | H114: Rice | I114: E. crus-galli, M.vaginalis, S.maritimus, C. difformis | J114: 750 gm/ha | K114: Rice | E. crus-galli, M.vaginalis, S.maritimus, C. difformis | 750 gm/ha | L114: 1
C115: (26% + 4%) | D115: 71 | E115: Lalteer 18WP | F115: AP-5189 | G115: Chens Crop Science Bangladesh Ltd. | H115: Rice | I115: E. crus-galli, M.vaginalis, S.maritimus, C. difformis | J115: 750 gm/ha | K115: Rice | E. crus-galli, M.vaginalis, S.maritimus, C. difformis | 750 gm/ha | L115: 1
C116: (26% + 4%) | D116: 72 | E116: Naingla 18WP | F116: AP-5190 | G116: Evergreen Crop Care Limited | H116: Rice | I116: E. crus-galli, M.vaginalis, S.maritimus, C. difformis | J116: 750 gm/ha | K116: Rice | E. crus-galli, M.vaginalis, S.maritimus, C. difformis | 750 gm/ha | L116: 1
C117: (26% + 4%) | D117: 73 | E117: Palam 18WP | F117: AP-5191 | G117: Pafs Agro International Co. | H117: Rice | I117: E. crus-galli, M.vaginalis, S.maritimus, C. difformis | J117: 750 gm/ha | K117: Rice | E. crus-galli, M.vaginalis, S.maritimus, C. difformis | 750 gm/ha | L117: 1
C118: (26% + 4%) | D118: 74 | E118: Luxed 18WP | F118: AP-5192 | G118: Luxury Agro Limited | H118: Rice | I118: E. crus-galli, M.vaginalis, S.maritimus, C. difformis | J118: 750 gm/ha | K118: Rice | E. crus-galli, M.vaginalis, S.maritimus, C. difformis | 750 gm/ha | L118: 1
C119: (26% + 4%) | D119: 75 | E119: Dibar 18WP | F119: AP-5194 | G119: SAM Agro Chemical | H119: Rice | I119: E. crus-galli, M.vaginalis, S.maritimus, C. difformis | J119: 750 gm/ha | K119: Rice | E. crus-galli, M.vaginalis, S.maritimus, C. difformis | 750 gm/ha | L119: 1
... C163: (26% + 4%) | D163: 119 | E163: Agacha Clear 18WP | F163: AP-6098 | G163: Chashi Agro Care | H163: Rice | I163: E. crus-galli, M.vaginalis, S.maritimus, C. difformis | J163: 500 g/ha | K163: Rice | E. crus-galli, M.vaginalis, S.maritimus, C. difformis | 500 g/ha | L163: 1
B164: 6 | C164: Chloropropham (50%) | D164: 1 | E164: Oorja 50HN | F164: AP-5200 | G164: RiceCo International Bangladesh Ltd. | H164: Potato | I164: Anti Sprouting, agemt | J164: 40 ml/Ton | K164: Potato | Anti Sprouting, agemt | 40 ml/Ton | L164: 1 | M164: HRAC K2
B165: 7 | C165: Bensulfuron methyl (0.6%) + Pretilachlor (6%%) (6% + 34%) | D165: 1 | E165: Londax Powder 6.6GR | F165: AP-2111 | G165: Petrochem Agro Industries Ltd. | H165: Rice | I165: S. maritimus, E. crus-galli, M.vaginalis, L. octovalvis, D. trifolium, M. minuta, C. difformis, S. zeylanica | J165: 9.88 kg/ha | K165: Rice | S. maritimus, E. crus-galli, M.vaginalis, L. octovalvis, D. trifolium, M. minuta, C. difformis, S. zeylanica | 9.88 kg/ha | L165: 1 | M165: HRAC B
B166: 8 | C166: Bensulfuron methyl (3%) + Mefenacet (50%) | D166: 1 | E166: Super Clean 53WP | F166: AP-1175 | G166: National AgriCare Import & Export Ltd | H166: Rice | I166: Weeds | J166: 450 gm/ha | K166: Rice | Weeds | 450 gm/ha | L166: 1 | M166: HRAC B
B167: 8 | C167: Bensulfuron methyl (3%) + Mefenacet (50%) | D167: 2 | E167: Clean Master 53 WP | F167: AP-3182 | G167: Haychem (Bangladesh) Limited | H167: Rice | I167: Q. europea, M.vaginalis, C.difformis | J167: 1.10 kg/ha | K167: Rice | Q. europea, M.vaginalis, C.difformis | 1.10 kg/ha | L167: 1 | M167: HRAC B
B168: 8 | C168: Bensulfuron methyl (3%) + Mefenacet (50%) | D168: 3 | E168: Ghash Killer 53WP | F168: AP-4416 | G168: Sweet Agrovet Limited | H168: Rice | I168: E. crus-galli, M.vaginalis, C.difformis, S. maritimus | J168: 620 gm/ha | K168: Rice | E. crus-galli, M.vaginalis, C.difformis, S. maritimus | 620 gm/ha | L168: 1 | M168: HRAC B
B169: 8 | C169: Bensulfuron methyl (3%) + Mefenacet (50%) | D169: 4 | E169: Relief 53WP | F169: AP-4417 | G169: Eon Agro Industries Limited | H169: Rice | I169: E. crus-galli, M.vaginalis, M. quadrifolia, S. maritimus | J169: 800 gm/ha | K169: Rice | E. crus-galli, M.vaginalis, M. quadrifolia, S. maritimus | 800 gm/ha | L169: 1 | M169: HRAC B
B170: 8 | C170: Bensulfuron methyl (3%) + Mefenacet (50%) | D170: 5 | E170: Get-Clean 69WP | F170: AP-4418 | G170: Getco Agri Technologies Ltd. | H170: Rice | I170: M.vaginalis, M. quadrifolia, S. maritimus | J170: 700 gm/ha | K170: Rice | M.vaginalis, M. quadrifolia, S. maritimus | 700 gm/ha | L170: 1 | M170: HRAC B
B171: 9 | C171: Bensulfuron methyl (4%) + Quinclorac (28%) (6% + 34%) (6% + 34%) (4% + 32%) | D171: 1 | E171: Vacate 32WP | F171: AP-2580 | G171: Eon Agro Industries Limited | H171: Rice | I171: C. difformis, E. crus galli, F.miliacea, L.hexandra, L.chinensis, S.maritimus, C.irria | J171: 600 gm/ha | K171: Rice | C. difformis, E. crus galli, F.miliacea, L.hexandra, L.chinensis, S.maritimus, C.irria | 600 gm/ha | L171: 1 | M171: HRAC B
B172: 9 | C172: Bensulfuron methyl (4%) + Quinclorac (28%) (6% + 34%) (6% + 34%) (4% + 32%) | D172: 2 | E172: Move 40WP | F172: AP-3872 | G172: Nokon Limited | H172: Rice | I172: C. difformis, E. crus galli, M.vaginalis, N.nouchali | J172: 600 gm/ha | K172: Rice | C. difformis, E. crus galli, M.vaginalis, N.nouchali | 600 gm/ha | L172: 1 | M172: HRAC B
B173: 9 | C173: Bensulfuron methyl (4%) + Quinclorac (28%) (6% + 34%) (6% + 34%) (4% + 32%) | D173: 3 | E173: Namir 32WP | F173: AP-4425 | G173: Intefa | H173: Rice | I173: E. crus galli, S. maritimus, M.vaginalis, M.quadrifolis | J173: 600 gm/ha | K173: Rice | E. crus galli, S. maritimus, M.vaginalis, M.quadrifolis | 600 gm/ha | L173: 1 | M173: HRAC B
B174: 9 | C174: Bensulfuron methyl (4%) + Quinclorac (28%) (6% + 34%) (6% + 34%) (4% + 32%) | D174: 4 | E174: Loper 40WP | F174: AP-4824 | G174: Sun Seed Pesticides | H174: Potato | I174: C.dactylon, C.rotundus, C. album, A. spinosus | J174: 100 gm/ha | K174: Potato | C.dactylon, C.rotundus, C. album, A. spinosus | 100 gm/ha | L174: 1 | M174: HRAC B
B175: 9 | C175: Bensulfuron methyl (4%) + Quinclorac (28%) (6% + 34%) (6% + 34%) (4% + 32%) | D175: 1 | E175: Forise 36WP | F175: AP-4825 | G175: Forward International (BD) Ltd. | H175: Tea, Rice | I175: B. hispida, I.cylindrica, C. difformis, E. crus galli, M.vaginalis, C.dectylon | J175: 1.50 Kg/ha; 600 gm/ha | K175: Tea | B. hispida, I.cylindrica | 1.50 Kg/ha Rice | C. difformis, E. crus galli, M.vaginalis, C.dectylon | 600 gm/ha | L175: 2 | M175: HRAC B
C176: (4% + 28%) (6% + 34%) (6% + 34%) (6% + 34%) | D176: 2 | E176: Bensulin 32WP | F176: AP-5154 | G176: NCL | H176: Tea | I176: B. hispida, I.cylindrica | J176: 1.50 Kg/ha | K176: Tea | B. hispida, I.cylindrica | 1.50 Kg/ha | L176: 1
C177: (4% + 28%) (6% + 34%) (6% + 34%) (6% + 34%) | D177: 3 | E177: Quiben 32WP | F177: AP-5155 | G177: SAM Agro Chemical | H177: Rice | I177: E. crus galli, M.vaginalis, C.difformis | J177: 600 gm/ha | K177: Rice | E. crus galli, M.vaginalis, C.difformis | 600 gm/ha | L177: 1
C178: (4% + 28%) (6% + 34%) (6% + 34%) (6% + 34%) | D178: 4 | E178: Abad 32WP | F178: AP-5156 | G178: Gurpukur Corporation | H178: Tea | I178: B. hispida, I.cylindrica | J178: 1.50 Kg/ha | K178: Tea | B. hispida, I.cylindrica | 1.50 Kg/ha | L178: 1
C179: (4% + 28%) (6% + 34%) (6% + 34%) (6% + 34%) | D179: 5 | E179: Desiquat 36WP | F179: AP-5483 | G179: National AgriCare Import & Export Ltd | H179: Rice | I179: C. difformis, E. crus galli, M.vaginalis, C.dectylon | J179: 600 g/ha | K179: Rice | C. difformis, E. crus galli, M.vaginalis, C.dectylon | 600 g/ha | L179: 1
C180: (4% + 28%) (6% + 34%) (6% + 34%) (6% + 34%) | D180: 6 | E180: Ble Raj 32WP | F180: AP-5654 | G180: Blessing Agrovet Industries Ltd. | H180: Rice | I180: C. difformis, E. crus galli, M.vaginalis, C.dectylon | J180: 600 g/ha | K180: Rice | C. difformis, E. crus galli, M.vaginalis, C.dectylon | 600 g/ha | L180: 1
C181: (4% + 28%) (6% + 34%) (6% + 34%) (6% + 34%) | D181: 7 | E181: Tata Clear 40WP | F181: AP-6099 | G181: Tata Crop Care Company | H181: Rice | I181: E. crus-galli, M.vaginalis, S.maritimus, C. difformis | J181: 600 g/ha | K181: Rice | E. crus-galli, M.vaginalis, S.maritimus, C. difformis | 600 g/ha | L181: 1
C182: (4% + 28%) (6% + 34%) (6% + 34%) (6% + 34%) | D182: 8 | E182: Mapclorak 40WP | F182: AP-6100 | G182: MAP Agro Industries Limited | H182: Rice | I182: E. crus-galli, M.vaginalis, S.maritimus, C. difformis | J182: 600 g/ha | K182: Rice | E. crus-galli, M.vaginalis, S.maritimus, C. difformis | 600 g/ha | L182: 1
C183: (4% + 28%) (6% + 34%) (6% + 34%) (6% + 34%) | D183: 9 | E183: Ronorac 40WP | F183: AP-6101 | G183: Agrivision Bangladesh | H183: Rice | I183: E. crus-galli, M.vaginalis, S.maritimus, C. difformis | J183: 600 g/ha | K183: Rice | E. crus-galli, M.vaginalis, S.maritimus, C. difformis | 600 g/ha | L183: 1
B184: 10 | C184: Bensulfuron methyl (18%) + Bispyribac Sodium (12%) | D184: 1 | E184: Sirius Plus 300WP | F184: AP-3263 | G184: Alpha Agro Limited | H184: Rice | I184: C. difformis, M.vaginalis, C.dactylon, E. crus-galli | J184: 120 g/ha | K184: Rice | C. difformis, M.vaginalis, C.dactylon, E. crus-galli | 120 g/ha | L184: 1 | M184: HRAC B
B185: 10 | C185: Bensulfuron methyl (18%) + Bispyribac Sodium (12%) | D185: 2 | E185: Rexikiller 30WP | F185: AP-3665 | G185: Win Agro Limited | H185: Rice | I185: Imperata cylindrica, Borreeia articularis | J185: 2.50 kg/ha | K185: Rice | Imperata cylindrica, Borreeia articularis | 2.50 kg/ha | L185: 1 | M185: HRAC B
B186: 10 | C186: Bensulfuron methyl (18%) + Bispyribac Sodium (12%) | D186: 3 | E186: Manin 30WP | F186: AP-3666 | G186: Intefa | H186: Onion | I186: C. album, E. crus-galli, D. sangunalis, C. rotondus, C. difformis, M.vaginalis | J186: 75 gm/ha | K186: Onion | C. album, E. crus-galli, D. sangunalis, C. rotondus, C. difformis, M.vaginalis | 75 gm/ha | L186: 1 | M186: HRAC B
B187: 10 | C187: Bensulfuron methyl (18%) + Bispyribac Sodium (12%) | D187: 4 | E187: Lorox 30WP | F187: AP-4366 | G187: Valent Tech Limited | H187: Rice | I187: M.vaginalis, S. maritinus | J187: 144 gm/ha | K187: Rice | M.vaginalis, S. maritinus | 144 gm/ha | L187: 1 | M187: HRAC B
B188: 10 | C188: Bensulfuron methyl (18%) + Bispyribac Sodium (12%) | D188: 5 | E188: Benbake 30WP | F188: AP-4367 | G188: SAM Agro Chemical | H188: Rice | I188: E. crus-galli, S. maritums, C. difformis | J188: 2.50 kg/ha | K188: Rice | E. crus-galli, S. maritums, C. difformis | 2.50 kg/ha | L188: 1 | M188: HRAC B
B189: 10 | C189: Bensulfuron methyl (18%) + Bispyribac Sodium (12%) | D189: 6 | E189: Fatiha 30WP | F189: AP-4368 | G189: Eco Green International | H189: Tea | I189: B. hispida, I.cylindrica | J189: 2.50 kg/ha | K189: Tea | B. hispida, I.cylindrica | 2.50 kg/ha | L189: 1 | M189: HRAC B
B190: 10 | C190: Bensulfuron methyl (18%) + Bispyribac Sodium (12%) | D190: 7 | E190: Crossout 30WP | F190: AP-4369 | G190: Babylon Agriscience Ltd. | H190: Tea | I190: B. hispida, I.cylindrica | J190: 2.50 kg/ha | K190: Tea | B. hispida, I.cylindrica | 2.50 kg/ha | L190: 1 | M190: HRAC B
B191: 10 | C191: Bensulfuron methyl (18%) + Bispyribac Sodium (12%) | D191: 8 | E191: Kery 30WP | F191: AP-4370 | G191: Agritech | H191: Tea | I191: B. hispida, I.cylindrica | J191: 2.50 kg/ha | K191: Tea | B. hispida, I.cylindrica | 2.50 kg/ha | L191: 1 | M191: HRAC B
B192: 10 | C192: Bensulfuron methyl (18%) + Bispyribac Sodium (12%) | D192: 9 | E192: Chaka 30WP | F192: AP-4371 | G192: Aama Green Care | H192: Tea | I192: B. hispida, I.cylindrica | J192: 2.50 kg/ha | K192: Tea | B. hispida, I.cylindrica | 2.50 kg/ha | L192: 1 | M192: HRAC B
B193: 10 | C193: Bensulfuron methyl (18%) + Bispyribac Sodium (12%) | D193: 10 | E193: Bendium Plus 30WP | F193: AP-4838 | G193: The Limit Agroproducts Limited | H193: Tea | I193: B. hispida, I.cylindrica | J193: 2.50 kg/ha | K193: Tea | B. hispida, I.cylindrica | 2.50 kg/ha | L193: 1 | M193: HRAC B
B194: 10 | C194: Bensulfuron methyl (18%) + Bispyribac Sodium (12%) | D194: 11 | E194: Dhaman 30WP | F194: AP-4839 | G194: Eminence Chemical Industries Ltd. | H194: Rice | I194: E. cruss-galli | J194: 150 gm/ha | K194: Rice | E. cruss-galli | 150 gm/ha | L194: 1 | M194: HRAC B
B195: 10 | C195: Bensulfuron methyl (18%) + Bispyribac Sodium (12%) | D195: 12 | E195: Forend 30WP | F195: AP-4840 | G195: Forward International (BD) Ltd. | H195: Tea | I195: B. hispida, I.cylindrica | J195: 2.50 kg/ha | K195: Tea | B. hispida, I.cylindrica | 2.50 kg/ha | L195: 1 | M195: HRAC B
... B236: 12 | C236: Butachlor | D236: 22 | E236: Ecobuta 5G | F236: AP-2581 | G236: Amco Agricultural Industries | H236: Rice | I236: L.chinensis, L.hexandra, E. crus-galli | J236: 25.00 kg/ha; 20.00 kg/ha | K236: Rice | L.chinensis, L.hexandra | 25.00 kg/ha - | E. crus-galli | 20.00 kg/ha | L236: 2 | M236: HRAC K3
B237: 12 | C237: Butachlor | D237: 23 | E237: Chinachlor 5G | F237: AP-3155 | G237: Agro Winner Limited | H237: Tea | I237: L.cylindrica, c.rotundus, B. hispida, M.pudica | K237: Tea | L.cylindrica, c.rotundus | - - | B. hispida, M.pudica | - | L237: 2 | M237: HRAC K3
B238: 12 | C238: Butachlor | D238: 24 | E238: Butaguard 60EW | F238: AP-5219 | G238: GME Agro Limited | H238: Rice | I238: C.difformis,, M.vaginalis, S. zeylanica | J238: 1.5 L/ha | K238: Rice | C.difformis,, M.vaginalis, S. zeylanica | 1.5 L/ha | L238: 1 | M238: HRAC K3
B239: 13 | C239: Butachlor (35 %) + Propanil (35%) | D239: 1 | E239: Gang 700EC | F239: AP-2446 | G239: ACI Formulations Limited | H239: Rice | I239: E. crus-galli, L. chinensis, M.vaginalis, C. difformis | J239: 1.00 L/ha | K239: Rice | E. crus-galli, L. chinensis, M.vaginalis, C. difformis | 1.00 L/ha | L239: 1 | M239: HRAC K3
B240: 13 | C240: Butachlor (35 %) + Propanil (35%) | D240: 2 | E240: Butacrop 70EC | F240: AP-4423 | G240: Shetu Pesticides Limited | H240: Rice | I240: S. martimus, M. quadrifoli, M.vaginali | J240: 1.50 L/ha | K240: Rice | S. martimus, M. quadrifoli, M.vaginali | 1.50 L/ha | L240: 1 | M240: HRAC K3
B241: 14 | C241: Carfentrazone Ethyl (50%) + Isoproturon (0.75%) | D241: 1 | E241: Affinity 50.75WP | F241: AP-1059 | G241: Auto Crop Care Limited | H241: Wheat | I241: Weed complex | J241: 1.50 kg/ha | K241: Wheat | Weed complex | 1.50 kg/ha | L241: 1 | M241: HRAC E
B242: 14 | C242: Carfentrazone Ethyl (50%) + Isoproturon (0.75%) | D242: 2 | E242: Sunfinity 50.75WP: | F242: AP-6123 | G242: McDonald Bangladesh (Pvt) Limited | H242: Rice | I242: S. martimus, M. quadrifoli | J242: 1.0 L/ha | K242: Rice | S. martimus, M. quadrifoli | 1.0 L/ha | L242: 1 | M242: HRAC E
B243: 15 | C243: Carfentrazone Ethyl | D243: 1 | E243: Aim 40DF | F243: AP-410 | G243: Petrochem (Bangladesh) Limited | H243: Rice, Potato | I243: Scirpus maritimus, Monochoria, vaginalis, Marsilea cremata, Fimbristylis milliacea, E.futuans, E.crusgali, Crotundus, Sphenoclea zeylanica, C.album, Broad Leaf and Sedge | J243: 62.50 gm/ha; 62.5 gm/ha | K243: Rice | Scirpus maritimus, Monochoria, vaginalis, Marsilea cremata, Fimbristylis milliacea, E.futuans, E.crusgali, Crotundus, Sphenoclea zeylanica, C.album | 62.50 gm/ha Potato | Broad Leaf and Sedge | 62.5 gm/ha | L243: 2 | M243: HRAC E
B244: 15 | C244: Carfentrazone Ethyl | D244: 2 | E244: Hammer 24EC | F244: AP-1058 | G244: Auto Crop Care Limited | H244: Wheat, Rice, Potato | I244: Broadleaf & Sedge Weeds, Scirpus maritimus, Monochoria, vaginalis, Marsilea cremata, Cyperus iria,Cyperus difformis, C.album, A. virids, A. philoxeroides, G.affine | J244: 104 ml/ha; 100 ml/ha | K244: Wheat | Broadleaf & Sedge Weeds | 104 ml/ha Rice | Scirpus maritimus, Monochoria, vaginalis, Marsilea cremata, Cyperus iria,Cyperus difformis | 100 ml/ha Potato | C.album, A. virids, A. philoxeroides, G.affine | 104 ml/ha | L244: 3 | M244: HRAC E
B245: 16 | C245: Cyhalofop-butyl | D245: 1 | E245: Rain 10EC | F245: AP-3207 | G245: ACI Formulations Limited | H245: Rice | I245: E. crus-galli, C.iria, F. miliacea, M.vaginalis, C. difformis | J245: 100 ml/ha | K245: Rice | E. crus-galli, C.iria, F. miliacea, M.vaginalis, C. difformis | 100 ml/ha | L245: 1 | M245: HRAC A
B246: 16 | C246: Cyhalofop-butyl | D246: 2 | E246: Mitson 10EC | F246: AP-5218 | G246: Sun Seed Pesticides | H246: Rice | I246: E. crus-galli, Mvaginalis, S. maritimus | J246: 120 ml/ha | K246: Rice | E. crus-galli, Mvaginalis, S. maritimus | 120 ml/ha | L246: 1 | M246: HRAC A
B247: 16 | C247: Cyhalofop-butyl | D247: 3 | E247: Foray 10EC | F247: AP-5658 | G247: Forward International (BD) Ltd. | H247: Rice | I247: E. crus-galli, Mvaginalis, S. maritimus, C.difformis | J247: 100 gm/ha | K247: Rice | E. crus-galli, Mvaginalis, S. maritimus, C.difformis | 100 gm/ha | L247: 1 | M247: HRAC A
B248: 17 | C248: Ethoxysulfuron | D248: 1 | E248: Sunrice 15WG | F248: AP-579 | G248: Bayer CropScience Limited | H248: Rice, Jute | I248: Broad Leaf and Sedge, C.rotundus | J248: 100 gm/ha; 200 gm/ha | K248: Rice | Broad Leaf and Sedge | 100 gm/ha Jute | C.rotundus | 200 gm/ha | L248: 2 | M248: HRAC B
B249: 17 | C249: Ethoxysulfuron | D249: 2 | E249: Moon Rise 15WG | F249: AP-3664 | G249: Sweet Agrovet Limited | H249: Tea | I249: Imperata, cylindrica, Borreeia articularis | J249: 2.50 kg/ha | K249: Tea | Imperata, cylindrica, Borreeia articularis | 2.50 kg/ha | L249: 1 | M249: HRAC B
... B420: 32 | C420: Atrazine (25%) + Mesotrione (2.5%) | D420: 1 | E420: Calaris Xtra 27.5SC | F420: AP-5449 | G420: Syngenta Bangladesh Limited | H420: Maize | I420: A.spinosus, D. snagunali, C. colonum, E. indica, C. dactilon, C. rotundus, C. iria | J420: 3.0 L/ha | K420: Maize | A.spinosus, D. snagunali, C. colonum, E. indica, C. dactilon, C. rotundus, C. iria | 3.0 L/ha | L420: 1 | M420: HRAC C1
C421: (50% + 5%) | D421: 2 | E421: Vepar 27.5SC | F421: AP-5450 | G421: Crop Protection & Care Center | H421: Maize | I421: A.spinosus, D. snagunali, C. colonum, E. indica, C. dactilon, C. rotundus, C. iria | J421: 800 ml/ha | K421: Maize | A.spinosus, D. snagunali, C. colonum, E. indica, C. dactilon, C. rotundus, C. iria | 800 ml/ha | L421: 1
C422: (50% + 5%) | D422: 3 | E422: Aneha 27.5SC | F422: AP-5451 | G422: Valent Tech Limited | H422: Maize | I422: A.spinosus, D. snagunali, C. colonum, E. indica, C. dactilon, C. rotundus, C. iria | J422: 800 ml/ha | K422: Maize | A.spinosus, D. snagunali, C. colonum, E. indica, C. dactilon, C. rotundus, C. iria | 800 ml/ha | L422: 1
C423: (50% + 5%) | D423: 4 | E423: Extrafen 55SC | F423: AP-5656 | G423: Kohinoor Agro Chemicals | H423: Brinjal | I423: G. affine | J423: 2.0 L/ha | K423: Brinjal | G. affine | 2.0 L/ha | L423: 1
C424: (50% + 5%) | D424: 5 | E424: Atraforce Plus 55SC | F424: AP-5657 | G424: Sixon Chem BD Ltd. | H424: Maize | I424: E. crus-galli,, E. colomun, C.dectylon | J424: 2.0 L/ha | K424: Maize | E. crus-galli,, E. colomun, C.dectylon | 2.0 L/ha | L424: 1
C425: (50% + 5%) | D425: 6 | E425: Copter 55SC | F425: AP-5863 | G425: Mimpex Agrochemicals Limited | H425: Maize | I425: O.europia, D. stricia | J425: 2.00 L/ha | K425: Maize | O.europia, D. stricia | 2.00 L/ha | L425: 1
C426: (25% + 2.5%) | D426: 7 | E426: Triozine 55SC | F426: AP-5864 | G426: Haychem (Bangladesh) Limited | H426: Maize | I426: D. snagunali, E. colomun, | J426: 2.00 L/ha | K426: Maize | D. snagunali, E. colomun, | 2.00 L/ha | L426: 1
C427: (25% + 2.5%) | D427: 8 | E427: Moontex 55SC | F427: AP-5865 | G427: Mondol Traders | H427: Maize | I427: O.europia, Digitari astricia | J427: 2.00 L/ha | K427: Maize | O.europia, Digitari astricia | 2.00 L/ha | L427: 1
C428: (25% + 2.5%) | D428: 9 | E428: Prism 27.5SC | F428: AP-5866 | G428: ACI Agrolink Limited | H428: Maize | I428: Amaranthus, E.crusgalli | J428: 2.00 L/ha | K428: Maize | Amaranthus, E.crusgalli | 2.00 L/ha | L428: 1
C429: (25% + 2.5%) | D429: 10 | E429: Bajna 55SC | F429: AP-5867 | G429: General Agro Chemicals Ltd. | H429: Maize | I429: E. crus-galli,, C.dectylon | J429: 2.0 L/ha | K429: Maize | E. crus-galli,, C.dectylon | 2.0 L/ha | L429: 1
C430: (50% + 5%) (50% + 5%) (50% + 5%) | D430: 11 | E430: Mesotin 50WP | F430: AP-6140 | G430: Square Pharmaceuticals Limited | H430: Maize | I430: E. crus-galli,, D. snagunali | J430: 1.80 Kg/ha | K430: Maize | E. crus-galli,, D. snagunali | 1.80 Kg/ha | L430: 1
C431: (50% + 5%) (50% + 5%) (50% + 5%) | D431: 12 | E431: Jaba 55SC | F431: AP-6141 | G431: Intefa | H431: Maize | I431: E. crusgalli,C.rotundus, C.irri, E. colomun, C.dectylon, E. cindca | J431: 2.0 L/ha | K431: Maize | E. crusgalli,C.rotundus, C.irri, E. colomun, C.dectylon, E. cindca | 2.0 L/ha | L431: 1
C432: (50% + 5%) (50% + 5%) (50% + 5%) | D432: 13 | E432: Aone 55SC | F432: AP-6142 | G432: Agro Business Support Ltd. | H432: Maize | I432: O.europia, Digitaria spp | J432: 200 ml/ha | K432: Maize | O.europia, Digitaria spp | 200 ml/ha | L432: 1
C433: (50% + 5%) (50% + 5%) (50% + 5%) | D433: 14 | E433: Trione 55SC | F433: AP-6143 | G433: Aranya Crop Care Limited | H433: Onion | I433: C rotundus, C. album, R.rahanistrum, R.maritimus | J433: 1.0 L/ha | K433: Onion | C rotundus, C. album, R.rahanistrum, R.maritimus | 1.0 L/ha | L433: 1
B434: 33 | C434: Nicosulfuron | D434: 1 | E434: Uribest 4SC | F434: AP-2575 | G434: National AgriCare Import & Export Ltd | H434: Maize | I434: E. crus-galli, A.viridis | J434: 1.50 L/ha | K434: Maize | E. crus-galli, A.viridis | 1.50 L/ha | L434: 1 | M434: HRAC B
B435: 33 | C435: Nicosulfuron | D435: 2 | E435: Nicosul 4SC | F435: AP-3687 | G435: Sweet Agrovet Limited | H435: Cotton | I435: E. crus-galli, M.vaginalis, C. difformis | J435: 500 ml/ha | K435: Cotton | E. crus-galli, M.vaginalis, C. difformis | 500 ml/ha | L435: 1 | M435: HRAC B
B436: 33 | C436: Nicosulfuron | D436: 3 | E436: Hulk 4SC | F436: AP-6150 | G436: Vyytal AG Limited | H436: Maize | I436: E. crus-galli,, D. snagunali | J436: 1.0 L/ha | K436: Maize | E. crus-galli,, D. snagunali | 1.0 L/ha | L436: 1 | M436: HRAC B
B437: 34 | C437: Orthosulfamuron | D437: 1 | E437: Kelion 50WP | F437: AP-1176 | G437: ACI Formulations Limited | H437: Rice | I437: Weeds | J437: 150 gm/ha | K437: Rice | Weeds | 150 gm/ha | L437: 1 | M437: HRAC B
B438: 35 | C438: Oxadiazon (25%) | D438: 1 | E438: Corostar 25EC | F438: AP-576 | G438: Corbel International Limited | H438: Rice | I438: Broad Lead and Sedge | J438: 2.00 L/ha | K438: Rice | Broad Lead and Sedge | 2.00 L/ha | L438: 1 | M438: HRAC E
B439: 35 | C439: Oxadiazon (25%) | D439: 2 | E439: Oxastar 25EC | F439: AP-578 | G439: Shetu Pesticides Limited | H439: Rice | I439: Broad Lead and Sedge | J439: 2.00 L/ha | K439: Rice | Broad Lead and Sedge | 2.00 L/ha | L439: 1 | M439: HRAC E
B440: 35 | C440: Oxadiazon (25%) | D440: 3 | E440: Longstar 25EC | F440: AP-584 | G440: Sea Trade Fertilizer Limited | H440: Rice | I440: Weeds | J440: 2.00 L/ha | K440: Rice | Weeds | 2.00 L/ha Rice | - | 2.00 L/ha | L440: 2 | M440: HRAC E
B441: 35 | C441: Oxadiazon (25%) | D441: 4 | E441: Amcostar 25EC | F441: AP-695 | G441: Atherton Imbros Company Ltd. | I441: Weeds | J441: 2.00 L/ha | K441: - | Weeds | 2.00 L/ha | L441: 1 | M441: HRAC E
B442: 35 | C442: Oxadiazon (25%) | D442: 5 | E442: Activar 25EC | F442: AP-698 | G442: McDonald Bangladesh (Pvt) Limited | H442: Rice, Potato | I442: Weeds | J442: 2.00 L/ha; 1.00 L/ha | K442: Rice | Weeds | 2.00 L/ha Potato | Weeds | 1.00 L/ha | L442: 2 | M442: HRAC E
B443: 35 | C443: Oxadiazon (25%) | D443: 6 | E443: Weeder 25EC | F443: AP-854 | G443: National AgriCare Import & Export Ltd | H443: Rice | I443: S. maritimus, M.vaginalis | J443: 1.00 L/ha | K443: Rice | S. maritimus, M.vaginalis | 1.00 L/ha | L443: 1 | M443: HRAC E
B444: 35 | C444: Oxadiazon (25%) | D444: 7 | E444: Sentry 25EC | F444: AP-1585 | G444: Haychem (Bangladesh) Limited | H444: Onion, Rice | I444: Chenopodium, Oxalis europea, E. crusgali, C. diformis | J444: 1.00 L/ha; 1.20 L/ha | K444: Onion | Chenopodium | 1.00 L/ha Rice | Oxalis europea, E. crusgali, C. diformis | 1.20 L/ha | L444: 2 | M444: HRAC E
B445: 35 | C445: Oxadiazon (25%) | D445: 8 | E445: Super Care 250EC | F445: AP-2103 | G445: ACI Formulations Limited | H445: Onion, Rice, Potato | I445: Chenopodium, S. maritimus, M.vaginalis, C. diformis, S. maritimus, N. nouchali, D. trifolium, C.album, R.rahanistrum, H.indicum, O.pholoxeroides | J445: 1.00 L/ha; 1.0 L/ha | K445: Onion | Chenopodium | 1.00 L/ha Rice | S. maritimus, M.vaginalis, C. diformis, S. maritimus, N. nouchali, D. trifolium | 1.00 L/ha Potato | C.album, R.rahanistrum, H.indicum, O.pholoxeroides | 1.0 L/ha | L445: 3 | M445: HRAC E
...

Sheet Store Grain Insecticide
B2: Registered Store Grain Insecticide Products — up to 81st PTAC Meeting
B4: SL No (Common Name) | C4: Common Name | D4: SL No (Products) | E4: Brand Name | F4: Registration No | G4: Registration Holder | H4: Recommended Crops | I4: Recommended Pests | J4: Dosage Rate | K4: Recommendations (Crop | Pest | Dosage) | L4: No. of Recommendations | M4: MoA Code
B5: 1 | C5: Aluminium Phosphide | D5: 1 | E5: Agriphos 57% | F5: AP-174 | G5: Nokon Limited | H5: Stored grain pest in Rice | I5: Red grain bettle | J5: 4 tables/1000 kg | K5: Stored grain pest in Rice | Red grain bettle | 4 tables/1000 kg | L5: 1 | M5: IRAC 24A
B6: 1 | C6: Aluminium Phosphide | D6: 2 | E6: Alumphos 56% | F6: AP-253 | G6: McDonald Bangladesh (Pvt) Limited | H6: Stored grain pest in Rice | I6: Red grain bettle | J6: 4 tables/1000 kg | K6: Stored grain pest in Rice | Red grain bettle | 4 tables/1000 kg | L6: 1 | M6: IRAC 24A
B7: 1 | C7: Aluminium Phosphide | D7: 3 | E7: Quck-Fume | F7: AP-254 | G7: United Phosphorus (Bangladesh) Ltd | H7: Stored grain pest in Rice | I7: Red grain bettle | J7: 4 tables/1000 kg | K7: Stored grain pest in Rice | Red grain bettle | 4 tables/1000 kg | L7: 1 | M7: IRAC 24A
B8: 1 | C8: Aluminium Phosphide | D8: 4 | E8: Fumitox 56% | F8: AP-530 | G8: National AgriCare Import & Export Ltd | H8: Stored grain pest in Rice | I8: Red grain bettle | J8: 4 tables/1000 kg | K8: Stored grain pest in Rice | Red grain bettle | 4 tables/1000 kg | L8: 1 | M8: IRAC 24A
B9: 1 | C9: Aluminium Phosphide | D9: 5 | E9: Al-cor 56% | F9: AP-661 | G9: Corbel International Limited | H9: Stored grain pest in Rice | I9: Red grain bettle | J9: 4 tables/1000 kg | K9: Stored grain pest in Rice | Red grain bettle | 4 tables/1000 kg | L9: 1 | M9: IRAC 24A
B10: 1 | C10: Aluminium Phosphide | D10: 6 | E10: Gilphos 56% | F10: AP-662 | G10: Gourab Industries Limited | H10: Stored grain pest in Rice | I10: Red grain bettle | J10: 4 tables/1000 kg | K10: Stored grain pest in Rice | Red grain bettle | 4 tables/1000 kg | L10: 1 | M10: IRAC 24A
B11: 1 | C11: Aluminium Phosphide | D11: 7 | E11: Sanphos 56% | F11: AP-663 | G11: Integrated Crop Care Bangladesh | H11: Stored grain pest in Rice | I11: Red grain bettle | J11: 4 tables/1000 kg | K11: Stored grain pest in Rice | Red grain bettle | 4 tables/1000 kg | L11: 1 | M11: IRAC 24A
B12: 1 | C12: Aluminium Phosphide | D12: 8 | E12: Fumiphos 56% | F12: AP-738 | G12: Sun Seed Pesticides | H12: Stored grain pest in Rice | I12: Red grain bettle | J12: 4 tables/1000 kg | K12: Stored grain pest in Rice | Red grain bettle | 4 tables/1000 kg | L12: 1 | M12: IRAC 24A
B13: 1 | C13: Aluminium Phosphide | D13: 9 | E13: Tinder 56% | F13: AP-904 | G13: Maitri Agro Industries | H13: Stored grain pest in Rice | I13: Red grain bettle | J13: 4 tables/1000 kg | K13: Stored grain pest in Rice | Red grain bettle | 4 tables/1000 kg | L13: 1 | M13: IRAC 24A
B14: 1 | C14: Aluminium Phosphide | D14: 10 | E14: Green Fune 56% | F14: AP-905 | G14: Green Bangla Agrovet Ltd. | H14: Stored grain pest in Rice | I14: Red grain bettle | J14: 4 tables/1000 kg | K14: Stored grain pest in Rice | Red grain bettle | 4 tables/1000 kg | L14: 1 | M14: IRAC 24A
B15: 1 | C15: Aluminium Phosphide | D15: 11 | E15: Alphos 56% | F15: AP-908 | G15: Prime Agro Limited | H15: Stored grain pest in Rice | I15: Red grain bettle | J15: 4 tables/1000 kg | K15: Stored grain pest in Rice | Red grain bettle | 4 tables/1000 kg | L15: 1 | M15: IRAC 24A
B16: 1 | C16: Aluminium Phosphide | D16: 12 | E16: Quick balm 56% | F16: AP-910 | G16: Anika Enterprise | H16: Stored grain pest in Rice | I16: Red grain bettle | J16: 4 tables/1000 kg | K16: Stored grain pest in Rice | Red grain bettle | 4 tables/1000 kg | L16: 1 | M16: IRAC 24A
... B92: 4 | C92: Pirimiphos methyl | D92: 6 | E92: Fasmethyl 50EC | F92: AP-4589 | G92: Fasal Agro Industries Ltd. | H92: Rice | I92: Tribolium, Rhizopertha, Sitophilus | J92: 20 ml/L of water | K92: Rice | Tribolium, Rhizopertha, Sitophilus | 20 ml/L of water | L92: 1 | M92: IRAC 1B
B93: Total (visible rows) | E93: =SUBTOTAL(103,E5:E92) -> 88 | L93: =SUBTOTAL(109,L5:L92) -> 91
B95: Source: Department of Agricultural Extension (DAE), Bangladesh — List of Registered Pesticides approved up to the 81st Pesticide Technical Advisory Committee (PTAC) Meeting. Extracted 2026-09-15 from https://dae.gov.bd/pages/files/6922da2a933eb65569e02d1e

Sheet Rodenticide
B2: Registered Rodenticides in Bangladesh — up to 81st PTAC Meeting
B4: SL No (Common Name) | C4: Common Name | D4: SL No (Products) | E4: Brand Name | F4: Registration No | G4: Registration Holder | H4: Recommended Crops | I4: Recommended Pests | J4: Dosage Rate | K4: Recommendations (Crop | Pest | Dosage) | L4: No. of Recommendations | M4: MoA Code
B5: 1 | C5: Bromadiolone | D5: 1 | E5: Lanirat | F5: AP-182 | G5: Syngenta Bangladesh Limited | H5: Crops field | I5: Rats | J5: 2-3 times should be eaten | K5: Crops field | Rats | 2-3 times should be eaten | L5: 1
B6: 1 | C6: Bromadiolone | D6: 2 | E6: Bromapoint | F6: AP-271 | G6: Shetu Pesticides Limited | H6: " | I6: Rats | J6: 2-3 times should be eaten | K6: " | Rats | 2-3 times should be eaten | L6: 1
B7: 1 | C7: Bromadiolone | D7: 3 | E7: Ratox | F7: AP-430 | G7: Auto Crop Care Limited | H7: " | I7: Rats | J7: 2-3 times should be eaten | K7: " | Rats | 2-3 times should be eaten | L7: 1
B8: 1 | C8: Bromadiolone | D8: 4 | E8: Roma | F8: AP-1559 | G8: Eon Agro Industries Limited | H8: " | I8: Rats | J8: 2-3 times should be eaten | K8: " | Rats | 2-3 times should be eaten | L8: 1
B9: 1 | C9: Bromadiolone | D9: 5 | E9: Ratonil | F9: AP-1892 | G9: Green Bangla Agrovet Ltd. | H9: " | I9: Rats | J9: 2-3 times should be eaten | K9: " | Rats | 2-3 times should be eaten | L9: 1
B10: 1 | C10: Bromadiolone | D10: 6 | E10: Ratoma 0.005% RB | F10: AP-5605 | G10: Square Pharmaceuticals Limited | H10: " | I10: Rats | J10: 2-3 times should be eaten | K10: " | Rats | 2-3 times should be eaten | L10: 1
B11: 1 | C11: Bromadiolone | D11: 7 | E11: Rat Finish | F11: AP-6030 | G11: ACI Formulations Limited | H11: " | I11: Rats | J11: 2-3 times should be eaten | K11: " | Rats | 2-3 times should be eaten | L11: 1
B12: 1 | C12: Bromadiolone | D12: 8 | E12: Roban | F12: AP-6031 | G12: Cannon Pest Management (BD) Pvt Ltd. | H12: " | I12: Rats | J12: 2-3 times should be eaten | K12: " | Rats | 2-3 times should be eaten | L12: 1
B13: 1 | C13: Bromadiolone | D13: 9 | E13: Rat Killer | F13: AP-6032 | G13: Sotota Agro Science | H13: " | I13: Rats | J13: 2-3 times should be eaten | K13: " | Rats | 2-3 times should be eaten | L13: 1
B14: 2 | C14: Zinc Phosphide | D14: 1 | E14: Zinc Phosphide | F14: AP-17 | G14: United Phosphorus (Bangladesh) Ltd | H14: " | I14: Rats | J14: 2% bait | K14: " | Rats | 2% bait | L14: 1 | M14: IRAC 24A
B15: 2 | C15: Zinc Phosphide | D15: 2 | E15: Gilphide 80% | F15: AP-739 | G15: Gourab Industries Limited | H15: " | I15: Rats | J15: 2% bait | K15: " | Rats | 2% bait | L15: 1 | M15: IRAC 24A
B16: 2 | C16: Zinc Phosphide | D16: 3 | E16: Commando 80% | F16: AP-915 | G16: Haychem (Bangladesh) Limited | H16: " | I16: Rats | J16: 2% bait | K16: " | Rats | 2% bait | L16: 1 | M16: IRAC 24A
B17: 2 | C17: Zinc Phosphide | D17: 4 | E17: Ratil | F17: AP-916 | G17: Integrated Crop Care Bangladesh | H17: " | I17: Rats | J17: 2% bait | K17: " | Rats | 2% bait | L17: 1 | M17: IRAC 24A
B18: 2 | C18: Zinc Phosphide | D18: 5 | E18: Crystal Zinc 2% | F18: AP-1891 | G18: Green Care Bangladesh | H18: " | I18: Rats | J18: 2% bait | K18: " | Rats | 2% bait | L18: 1 | M18: IRAC 24A
B19: 2 | C19: Zinc Phosphide | D19: 6 | E19: Phonix Brand 2% | F19: AP-5604 | G19: Khaja Chemical Industries | H19: " | I19: Rats | J19: 2% bait | K19: " | Rats | 2% bait | L19: 1 | M19: IRAC 24A
B20: Total (visible rows) | E20: =SUBTOTAL(103,E5:E19) -> 15 | L20: =SUBTOTAL(109,L5:L19) -> 15
B22: Source: Department of Agricultural Extension (DAE), Bangladesh — List of Registered Pesticides approved up to the 81st Pesticide Technical Advisory Committee (PTAC) Meeting. Extracted 2026-09-15 from https://dae.gov.bd/pages/files/6922da2a933eb65569e02d1e

Sheet Bio Pesticide
B2: Registered Bio Pesticicides in Bangladesh — up to 81st PTAC Meeting
B4: SL No (Common Name) | C4: Common Name | D4: SL No (Products) | E4: Brand Name | F4: Registration No | G4: Registration Holder | H4: Recommended Crops | I4: Recommended Pests | J4: Dosage Rate | K4: Recommendations (Crop | Pest | Dosage) | L4: No. of Recommendations | M4: MoA Code
B5: 1 | C5: Abamectin | D5: 1 | E5: Matrixine Plus 5% ME | F5: AP (Bio)-21 | G5: Russell IPM Bangladesh Ltd. | H5: Tea | I5: Red spider mite | J5: 250 ml/ha | K5: Tea | Red spider mite | 250 ml/ha | L5: 1 | M5: IRAC 6
B6: 2 | C6: Cuelure (97%) | D6: 1 | E6: Q-Phero | F6: AP (Bio)-02 | G6: Ispahani Agro Limited | H6: Bitter gourd | I6: Fruit fly | J6: 70 Lures/ha | K6: Bitter gourd | Fruit fly | 70 Lures/ha | L6: 1
B7: 2 | C7: Cuelure (97%) | D7: 2 | E7: Bactro-D | F7: AP (Bio)-03 | G7: Ispahani Agro Limited | H7: Mango, Guava | I7: Fruit fly | J7: 80 Lures/ha | K7: Mango, Guava | Fruit fly | 80 Lures/ha | L7: 1
B8: 2 | C8: Cuelure (97%) | D8: 3 | E8: AT Cuelure '69 | F8: AP (Bio)-28 | G8: Agritech 69 Limited | H8: Bitter gourd | I8: Fruit fly | J8: 70 Lures/ha | K8: Bitter gourd | Fruit fly | 70 Lures/ha | L8: 1
B9: 2 | C9: Cuelure (97%) | D9: 4 | E9: Tabiz Pheromone Trap | F9: AP (Bio)-29 | G9: ACP Bangladesh | H9: Bitter gourd | I9: Fruit fly | J9: 100 Lures/ha | K9: Bitter gourd | Fruit fly | 100 Lures/ha | L9: 1
B10: 3 | C10: Pheromone lure (4[p-acetoxiphenyl]-2-butanon | D10: 1 | E10: BSFB-Phero | F10: AP (Bio)-05 | G10: Ispahani Agro Limited | H10: Brinjal | I10: Shoot & Fruit borer | J10: 100 lures/ha | K10: Brinjal | Shoot & Fruit borer | 100 lures/ha | L10: 1
B11: 3 | C11: Pheromone lure (4[p-acetoxiphenyl]-2-butanon | D11: 2 | E11: Spodo-lure | F11: AP (Bio)-06 | G11: Ispahani Agro Limited | H11: Cabbage | I11: Common cutworm | J11: 40 lures/ha | K11: Cabbage | Common cutworm | 40 lures/ha | L11: 1
B12: 3 | C12: Pheromone lure (4[p-acetoxiphenyl]-2-butanon | D12: 3 | E12: Fuji Qlure | F12: AP (Bio)-11 | G12: GME Agro Limited | H12: Bitter gourd | I12: Fruit fly | J12: 70 lures/ha | K12: Bitter gourd | Fruit fly | 70 lures/ha | L12: 1
B13: 3 | C13: Pheromone lure (4[p-acetoxiphenyl]-2-butanon | D13: 4 | E13: Bio-lure | F13: AP (Bio)-42 | G13: Integrated Crop Solution Bangladesh | H13: Brinjal | I13: Shoot & Fruit borer | J13: 100 lures/ha | K13: Brinjal | Shoot & Fruit borer | 100 lures/ha | L13: 1
B14: 3 | C14: Pheromone lure (4[p-acetoxiphenyl]-2-butanon | D14: 5 | E14: Cue Magneto | F14: AP (Bio)-43 | G14: TBS Agro Limited | H14: Bitter gourd | I14: Fruit fly | J14: 90 lures/ha | K14: Bitter gourd | Fruit fly | 90 lures/ha | L14: 1
B15: 4 | C15: Azadiractin | D15: 1 | E15: Ecomec 1.8EC | F15: AP (Bio)-10 | G15: Ispahani Agro Limited | H15: Brinjal, Tea | I15: Aphid, Red Spider mite | J15: 1 ml/Lof water; 0.5 L/ha | K15: Brinjal | Aphid | 1 ml/Lof water Tea | Red Spider mite | 0.5 L/ha | L15: 2 | M15: IRAC UN
B16: 4 | C16: Azadiractin | D16: 2 | E16: Bio-cure Plus 1EC | F16: AP (Bio)-33 | G16: Integrated Crop Solution Bangladesh | H16: Tea | I16: Red Spider mite | J16: 1.00 L/ha | K16: Tea | Red Spider mite | 1.00 L/ha | L16: 1 | M16: IRAC UN
B17: 5 | C17: 1,2-Diemthoxy-4-(2-propenyl) Benzene | D17: 1 | E17: Fuji Fruit Lure | F17: AP (Bio)-14 | G17: GME Agro Limited | H17: Guava | I17: Fruit fly | J17: 80 lures/ha | K17: Guava | Fruit fly | 80 lures/ha | L17: 1
B18: 5 | C18: 1,2-Diemthoxy-4-(2-propenyl) Benzene | D18: 2 | E18: Fruit Magneto | F18: AP (Bio)-40 | G18: TBS Agro Limited | H18: Mango & Guava | I18: Fruit fly | J18: 80 ml/ha | K18: Mango & Guava | Fruit fly | 80 ml/ha | L18: 1
B19: 6 | C19: Alkaloids mater Lantadenes & Vasine | D19: 1 | E19: Archer 75WP | F19: AP (Bio) -17 | G19: Haychem (Bangladesh) Limited | H19: Tea, Tomato | I19: Red rust, Damping off | J19: 2.00 kg/ha; 3 g/L of water | K19: Tea | Red rust | 2.00 kg/ha Tomato | Damping off | 3 g/L of water | L19: 2
B20: 7 | C20: Azadirectin A + Azadirectin B | D20: 1 | E20: Achta 1%EC | F20: AP (Bio) -18 | G20: Haychem (Bangladesh) Limited | H20: Jute, Tomato | I20: Hairy caterpillar, Aphid | J20: 1.50 L/ha; 1 ml/L of water | K20: Jute | Hairy caterpillar | 1.50 L/ha Tomato | Aphid | 1 ml/L of water | L20: 2 | M20: IRAC UN
B21: 8 | C21: Alpha Cypermethrin | D21: 1 | E21: Ceranock | F21: AP (Bio) -19 | G21: Russell IPM Bangladesh Ltd. | H21: Mango | I21: Fruit fly | J21: 100 trap/ha | K21: Mango | Fruit fly | 100 trap/ha | L21: 1 | M21: IRAC 3A
B22: 9 | C22: Methyl Euginol + Abamectin | D22: 1 | E22: Zonatrac | F22: AP (Bio) -20 | G22: Russell IPM Bangladesh Ltd. | H22: Mango | I22: Fruit fly | J22: 100 g/ha | K22: Mango | Fruit fly | 100 g/ha | L22: 1
B23: 10 | C23: Spodoptera Litura, nucleo polyhedro virus | D23: 1 | E23: Spodo-NPV | F23: AP (Bio) -22 | G23: Ispahani Agro Limited | H23: Cabbage | I23: Common cutworm | J23: 0.2 g/l of water | K23: Cabbage | Common cutworm | 0.2 g/l of water | L23: 1
B24: 11 | C24: Spodoptera frugiperda multiple nucleo polyhedro virus | D24: 1 | E24: Fawligen (SFNPV) | F24: AP (Bio) -44 | G24: Ispahani Agro Limited | H24: Maize | I24: Fall Armyworm, (Spodoptera frugiperda) | J24: 1 ml/L of water | K24: Maize | Fall Armyworm, (Spodoptera frugiperda) | 1 ml/L of water | L24: 1
B25: 12 | C25: Microbial Fungicide, Cell Microbe | D25: 1 | E25: Decoprima | F25: AP (Bio) - 23 | G25: Mohsin Enterprise | H25: Brinjal | I25: Fusarium Wilt | J25: 100 g/ha | K25: Brinjal | Fusarium Wilt | 100 g/ha | L25: 1
B26: 13 | C26: Trichoderma | D26: 1 | E26: Tricost 1%WP | F26: AP (Bio)-24 | G26: Haychem (Bangladesh) Limited | H26: Tea | I26: Charcoal Stump Rot, Collar Rot | J26: 5.0 Kg/ha | K26: Tea | Charcoal Stump Rot | 5.0 Kg/ha Tea | Collar Rot | 5.0 Kg/ha | L26: 2
B27: 14 | C27: Pseudomons Fluorescens 0.5% | D27: 1 | E27: Monexe 0.5WP | F27: AP (Bio)-25 | G27: Haychem (Bangladesh) Ltd. | H27: Tomato, Tea | I27: Bacterial Wilt, Black rot | J27: 5 g/L of water; 5 kg/ha | K27: Tomato | Bacterial Wilt | 5 g/L of water Tea | Black rot | 5 kg/ha | L27: 2
B28: 15 | C28: [(E)-11-hexadecenyl acetate and (E)-11-hexadecen-1-01] sex pheromone lure | D28: 1 | E28: BSFB Lure '69 | F28: AP (Bio)-27 | G28: Agritech 69 Limited | H28: Brinjal | I28: Shoot & Fruit borer | J28: 100 lures/ha | K28: Brinjal | Shoot & Fruit borer | 100 lures/ha | L28: 1
B29: 15 | C29: [(E)-11-hexadecenyl acetate and (E)-11-hexadecen-1-01] sex pheromone lure | D29: 2 | E29: Haylure Brinjal | F29: AP (Bio)-41 | G29: Haychem (Bangladesh) Limited | H29: Brinjal | I29: Shoot & Fruit borer | J29: 100 lures/ha | K29: Brinjal | Shoot & Fruit borer | 100 lures/ha | L29: 1
B30: 16 | C30: Methyl Eugenol | D30: 1 | E30: AT Fruit's Lure '69 | F30: AP (Bio)-28 | G30: Agritech 69 Limited | H30: Mango | I30: Fruit fly | J30: 100 lures/ha | K30: Mango | Fruit fly | 100 lures/ha | L30: 1
B31: 16 | C31: Methyl Eugenol | D31: 2 | E31: Ratan Pheromone | F31: AP (Bio)-36 | G31: ACP Bangladesh | H31: Mango & Guava | I31: Fruit fly | J31: 80 lures/ha | K31: Mango & Guava | Fruit fly | 80 lures/ha | L31: 1
B32: 16 | C32: Methyl Eugenol | D32: 3 | E32: Apache | F32: AP (Bio)-37 | G32: ACI Limited | H32: Mango & Guava | I32: Fruit fly | J32: 80 lures/ha | K32: Mango & Guava | Fruit fly | 80 lures/ha | L32: 1
B33: 16 | C33: Methyl Eugenol | D33: 4 | E33: Orolure | F33: AP (Bio)-38 | G33: Oroni International Limited | H33: Mango & Guava | I33: Fruit fly | J33: 80 lures/ha | K33: Mango & Guava | Fruit fly | 80 lures/ha | L33: 1
... B39: 20 | C39: (Z)-9-Tetradecenyl acetate) (Z)-7-Dodecenyl acetate | D39: 1 | E39: Hay Lure Army Worm | F39: AP (Bio)-32 | G39: Haychem (Bangladesh) Ltd. | H39: Maize | I39: Fall Armyworm | J39: 40 lures/ha | K39: Maize | Fall Armyworm | 40 lures/ha | L39: 1
B40: Total (visible rows) | E40: =SUBTOTAL(103,E5:E39) -> 35 | L40: =SUBTOTAL(109,L5:L39) -> 42
B42: Source: Department of Agricultural Extension (DAE), Bangladesh — List of Registered Pesticides approved up to the 81st Pesticide Technical Advisory Committee (PTAC) Meeting. Extracted 2026-09-15 from https://dae.gov.bd/pages/files/6922da2a933eb65569e02d1e

Sheet Public Health
B2: Registered Public Health Pesticides (PHP) in Bangladesh — up to 81st PTAC Meeting
B4: SL No (Common Name) | C4: Common Name | D4: SL No (Products) | E4: Brand Name | F4: Registration No | G4: Registration Holder | H4: Recommended Pests | I4: Dosage Rate | J4: Recommendations (Pest | Dosage) | K4: No. of Recommendations
B5: 1 | C5: S-bio-allethrin (0.10%)+Permethrin (0.50%) Tetramethrin (0.20%) | D5: 1 | E5: ACI Mosquito Inseciticdes | F5: PHP-186 | G5: ACI Formulations Limited | H5: Adult Mosquito and Cockroach | I5: 2.0 L/ha | J5: Adult Mosquito and Cockroach | 2.0 L/ha | K5: 1
B6: 2 | C6: D-tetramethrin + Permethrin | D6: 1 | E6: Globe Aerosol | F6: PHP-120 | G6: Globe Insecticides Limited | H6: Adult Mosquito and Cockroach | I6: 10 Second stroke; spray/100 cft room/12 ml/100 cft | J6: Adult Mosquito and Cockroach | 10 Second stroke - | spray/100 cft room/12 ml/100 cft | K6: 2
B7: 3 | C7: S Bioallethrin+Permethrin | D7: 1 | E7: Phonix Powder | F7: PHP-257 | G7: Khaza Chemical Industries | H7: Cockroach | I7: 10 gm/m2 | J7: Cockroach | 10 gm/m2 | K7: 1
B8: 4 | C8: Pynamine Fort | D8: 1 | E8: Alpha Mosquito Coil | F8: PHP-176 | G8: Alpha Agro Limited | H8: Adult Mosquito | I8: 6 gm/32 m3 | J8: Adult Mosquito | 6 gm/32 m3 | K8: 1
B9: 5 | C9: Fenitrothion | D9: 1 | E9: Fenon 40WP | F9: PHP-1056 | G9: A & E International | H9: Mosquito Larva & Adult | I9: 5 g/Square meter/2.0 Litre water | J9: Mosquito Larva & Adult | 5 g/Square meter/2.0 Litre water | K9: 1
B10: 6 | C10: Deltamethrin | D10: 1 | E10: Delete 2.5 EC | F10: PHP-162 | G10: ACI Formulations Limited | H10: Mosquito Larvae | I10: 103.74 ml per hectare | J10: Mosquito Larvae | 103.74 ml per hectare | K10: 1
B11: 6 | C11: Deltamethrin | D11: 2 | E11: Finis Insect Chalk | F11: PHP-213 | G11: Standard Finis Oil Company | H11: Cockroach | I11: 1.1gm2 | J11: Cockroach | 1.1gm2 | K11: 1
B12: 6 | C12: Deltamethrin | D12: 3 | E12: Alta 2.5 EC | F12: PHP-214 | G12: Eon Agro Industries Limited | H12: Mosquito Larva/Adult | I12: 100 ml/ha & 2 ml/33m2 | J12: Mosquito Larva/Adult | 100 ml/ha & 2 ml/33m2 | K12: 1
B13: 6 | C13: Deltamethrin | D13: 4 | E13: K-Othrine 1%SC | F13: PHP-215 | G13: Bayer CropScience Limited | H13: Mosquito Adult | I13: 40 ml+0.5 Litre of water/15m2 | J13: Mosquito Adult | 40 ml+0.5 Litre of water/15m2 | K13: 1
B14: 6 | C14: Deltamethrin | D14: 5 | E14: K-Othrine 2.5WP | F14: PHP-222 | G14: Bayer CropScience Limited | H14: Mosquito Adult | I14: 200 gm/250m2 | J14: Mosquito Adult | 200 gm/250m2 | K14: 1
B15: 6 | C15: Deltamethrin | D15: 6 | E15: K-Othrine 5% WP | F15: PHP-223 | G15: Bayer CropScience Limited | H15: Mosquito Adult | I15: 100 gm/250m2 | J15: Mosquito Adult | 100 gm/250m2 | K15: 1
B16: 6 | C16: Deltamethrin | D16: 7 | E16: Lakshaya 2.5Flow | F16: PHP-238 | G16: Larsen Chemical Industries (Pvt) Ltd | H16: Mosquito Adult | I16: 300 ml/500m2 | J16: Mosquito Adult | 300 ml/500m2 | K16: 1
... B36: 6 | C36: Deltamethrin | D36: 27 | E36: Hot Clean Insect Powder 5WP | F36: PHP-1053 | G36: Chistia Marketing & Distribution | H36: Mosquito | I36: 100 g/250 m2 | J36: Mosquito | 100 g/250 m2 | K36: 1
C37: 1.25% | D37: 28 | E37: Cityclean 1.25 ULV | F37: PHP-1095 | G37: Dhaka South City Corporation | H37: Adult Mosquito | I37: 6 ml/100m2 | J37: Adult Mosquito | 6 ml/100m2 | K37: 1
C38: 2% | D38: 29 | E38: Cityclean-G 2% EW | F38: PHP-1087 | G38: Gazipur City Corporation | H38: Mosquito Larva | I38: 5 Litre/ha | J38: Mosquito Larva | 5 Litre/ha | K38: 1
C39: 2% | D39: 30 | E39: City Delta-G 1.25 ULV | F39: PHP-1088 | G39: Gazipur City Corporation | H39: Adult Mosquito | I39: 50 ml/1000 m3 | J39: Adult Mosquito | 50 ml/1000 m3 | K39: 1
C40: 2% | D40: 31 | E40: Deltafog 2.5EC | F40: PHP-1096 | G40: M R Enterprise | H40: Adult Mosquito | I40: 0.40 ml/m2 | J40: Adult Mosquito | 0.40 ml/m2 | K40: 1
C41: 2% | D41: 32 | E41: Biobos 2.5EC | F41: PHP-1101 | G41: Dhaka Hangzhou Biotechnology Ltd. | H41: Adult Mosquito | I41: 100 ml/ha | J41: Adult Mosquito | 100 ml/ha | K41: 1
C42: 2% | D42: 33 | E42: Bio Killer 2.5EC | F42: PHP-1103 | G42: Biosave Agrovet | H42: Adult Mosquito | I42: 0.40 ml/m2 | J42: Adult Mosquito | 0.40 ml/m2 | K42: 1
C43: 2% | D43: 34 | E43: Chemmothrin 2.5EC | F43: PHP-1114 | G43: Chemist Crop Care Ltd. | H43: Adult Mosquito | I43: 0.40 ml/m2 | J43: Adult Mosquito | 0.40 ml/m2 | K43: 1
C44: 2% | D44: 35 | E44: Hiter 2.5EC | F44: PHP-1115 | G44: Tens International | H44: Adult Mosquito | I44: 0.40 ml/m2 | J44: Adult Mosquito | 0.40 ml/m2 | K44: 1
C45: 2% | D45: 36 | E45: Super Killer 1.25 ULV | F45: PHP-1121 | G45: Siraj Agro International Ltd. | H45: Mosquito | I45: 6 ml/100m2 | J45: Mosquito | 6 ml/100m2 | K45: 1
B46: 7 | C46: Permethrin (5%) | D46: 1 | E46: Finis Insect Powder | F46: PHP-59 | G46: Standard Finis Oil Company | H46: Cockroach | I46: 10 gm/m2 | J46: Cockroach | 10 gm/m2 | K46: 1
B47: 7 | C47: Permethrin (5%) | D47: 2 | E47: Supreme Insect Powder | F47: PHP-245 | G47: Shahid Chemical Co. | H47: Cockroach | I47: 10 gm/m2 | J47: Cockroach | 10 gm/m2 | K47: 1
B48: 7 | C48: Permethrin (5%) | D48: 3 | E48: Eagle Insect Powder | F48: PHP-250 | G48: Quazi Enterprises Limited | H48: Ant/Bed bug/Cockroach | I48: 10 gm/m2 | J48: Ant/Bed bug/Cockroach | 10 gm/m2 | K48: 1
B49: 7 | C49: Permethrin (5%) | D49: 4 | E49: Nokon Insect Powder | F49: PHP-330 | G49: Nokon Limited | H49: Cockroach | I49: 10 gm/50m2 | J49: Cockroach | 10 gm/50m2 | K49: 1
B50: 7 | C50: Permethrin (5%) | D50: 5 | E50: Challenge Insect Powder | F50: PHP-335 | G50: Santana Chemical Company | H50: Cockroach | I50: 15 gm/m2 | J50: Cockroach | 15 gm/m2 | K50: 1
B51: 7 | C51: Permethrin (5%) | D51: 6 | E51: Standard Insect Powder | F51: PHP-345 | G51: Santana Chemical Company | H51: Cockroach | I51: 10 gm/m2 | J51: Cockroach | 10 gm/m2 | K51: 1
B52: 7 | C52: Permethrin (5%) | D52: 7 | E52: Finis Liquid Spray | F52: PHP-376 | G52: Standard Finis Oil Company | H52: Mosquito | I52: 10 ml/100m3 | J52: Mosquito | 10 ml/100m3 | K52: 1
B53: 7 | C53: Permethrin (5%) | D53: 8 | E53: Finis Booster Insect Powder | F53: PHP-377 | G53: Standard Finis Oil Company | H53: Cockroach | I53: 2 gm/m2 | J53: Cockroach | 2 gm/m2 | K53: 1
B54: 7 | C54: Permethrin (5%) | D54: 9 | E54: Super Star Insect Power | F54: PHP-474 | G54: Selina Chemical Industries | H54: Cockroach | I54: 10 gm/m2 X 100 CM | J54: Cockroach | 10 gm/m2 X 100 CM | K54: 1
B55: 7 | C55: Permethrin (5%) | D55: 10 | E55: Rocky Brand Insect Power | F55: PHP-488 | G55: Rocky Chemical Company | H55: Cockroach | I55: 10 gm/82 Ft | J55: Cockroach | 10 gm/82 Ft | K55: 1
B56: 7 | C56: Permethrin (5%) | D56: 11 | E56: K-2 Brand Insect Power | F56: PHP-498 | G56: J H Chemical Co. | H56: Cockroach | I56: 10 gm/m2 X 100 CM | J56: Cockroach | 10 gm/m2 X 100 CM | K56: 1
B57: 7 | C57: Permethrin (5%) | D57: 12 | E57: Boss Brand Insect Power | F57: PHP-499 | G57: Shomon Chemical Co. | H57: Cockroach | I57: 10 gm/m2 X 100 CM | J57: Cockroach | 10 gm/m2 X 100 CM | K57: 1
... B76: 7 | C76: Permethrin (5%) | D76: 31 | E76: Tighter Finish Brand Insecticide Powder | F76: PHP-946 | G76: M H Chemical Co. | H76: Cockorach | I76: 1m2-10 gm/m2 | J76: Cockorach | 1m2-10 gm/m2 | K76: 1
C77: -0.03 0.30% 0.30% 0.10% 0.30% 0.30% | D77: 32 | E77: Astro Liquid Spray | F77: PHP-951 | G77: Ashad Enterprise | H77: Adult Mosquito | I77: 30 ml/L of water, 100m2 | J77: Adult Mosquito | 30 ml/L of water, 100m2 | K77: 1
C78: -0.03 0.30% 0.30% 0.10% 0.30% 0.30% | D78: 33 | E78: Khushi High Power Mosquito Coil | F78: PHP-970 | G78: Islam Agro Industries | H78: Mosquito | I78: 63X63X73 cm3 | J78: Mosquito | 63X63X73 cm3 | K78: 1
C79: -0.03 0.30% 0.30% 0.10% 0.30% 0.30% | D79: 34 | E79: Al-Time High Power Mosquito Coil | F79: PHP-987 | G79: Byuyan Corporation | H79: Mosquito | I79: 63X63X73 cm3 | J79: Mosquito | 63X63X73 cm3 | K79: 1
C80: -0.03 0.30% 0.30% 0.10% 0.30% 0.30% | D80: 35 | E80: Daniel Spray Liquid Insecticide | F80: PHP-1023 | G80: Daniel Agro Chemicals | H80: Mosquito Larva | I80: 6 ml/100m3 | J80: Mosquito Larva | 6 ml/100m3 | K80: 1
C81: -0.03 0.30% 0.30% 0.10% 0.30% 0.30% | D81: 36 | E81: Saff Liquid Spray | F81: PHP-1024 | G81: Siam Crop Care | H81: Mosquito Larva | I81: 6 ml/100m3 | J81: Mosquito Larva | 6 ml/100m3 | K81: 1
C82: -0.03 0.30% 0.30% 0.10% 0.30% 0.30% | D82: 37 | E82: Ecotraps | F82: PHP-1048 | G82: Square Pharmaceuticals Ltd. | H82: Mosquito | I82: 1 Trap/404m2 | J82: Mosquito | 1 Trap/404m2 | K82: 1
C83: -0.03 0.30% 0.30% 0.10% 0.30% 0.30% | D83: 38 | E83: Star Liquid Insecticides | F83: PHP-1054 | G83: Alam Trading | H83: Mosquito | I83: 6 ml/100m3 | J83: Mosquito | 6 ml/100m3 | K83: 1
C84: -0.03 0.30% 0.30% 0.10% 0.30% 0.30% | D84: 39 | E84: Rico Liquid Insecticides | F84: PHP-1086 | G84: Rico Agrovet | H84: Adult Mosquito | I84: 6 ml/100m2 | J84: Adult Mosquito | 6 ml/100m2 | K84: 1
C85: -0.03 0.30% 0.30% 0.10% 0.30% 0.30% | D85: 40 | E85: Moskill Spray | F85: PHP-1068 | G85: Standard Finis Oil Company | H85: Adult Mosquito | I85: 12 Stroke/1200 cft Room - 20 minute | J85: Adult Mosquito | 12 Stroke/1200 cft Room - 20 minute | K85: 1
C86: -0.03 0.30% 0.30% 0.10% 0.30% 0.30% | D86: 41 | E86: Cosmo Insect Powder | F86: PHP-1080 | G86: Cosmo Consumer Products Ltd. | H86: Adult Mosquito | I86: 10 gm/m2 | J86: Adult Mosquito | 10 gm/m2 | K86: 1
C87: -0.03 0.30% 0.30% 0.10% 0.30% 0.30% | D87: 42 | E87: Fast Kill Liquid Spray | F87: PHP-1099 | G87: May Gold Agro Science | H87: Adult Mosquito | I87: 6 ml/100m2 | J87: Adult Mosquito | 6 ml/100m2 | K87: 1
C88: -0.03 0.30% 0.30% 0.10% 0.30% 0.30% | D88: 43 | E88: Biolin Liquid Insecticide | F88: PHP-1100 | G88: Dhaka Hangzhou Biotechnology Ltd. | H88: Adult Mosquito | I88: 6 ml/100m2 | J88: Adult Mosquito | 6 ml/100m2 | K88: 1
... C94: -0.03 0.30% 0.30% 0.10% 0.30% 0.30% | D94: 49 | E94: Labiba Liquid Insecticides | F94: PHP-1120 | G94: Ariyan Trading | H94: Adult Mosquito | I94: 6 ml/100m2 | J94: Adult Mosquito | 6 ml/100m2 | K94: 1
B95: 8 | C95: Permethrin + Tetramethrin | D95: 1 | E95: Duracide 25% | F95: PHP-236 | G95: The Limit Agroproducts Limited | H95: Adult Mosquito | I95: 10 ml/100 m2 | J95: Adult Mosquito | 10 ml/100 m2 | K95: 1
B96: 8 | C96: Permethrin + Tetramethrin | D96: 2 | E96: Goldeer Aerosol | F96: PHP-228 | G96: Bismillah Trading | H96: Adult Mosquito | I96: 33 CFT | J96: Adult Mosquito | 33 CFT | K96: 1
B97: 8 | C97: Permethrin + Tetramethrin | D97: 3 | E97: Grand Lion Aerosol | F97: PHP-724 | G97: Mannan Electronic | H97: Mosquito | I97: 5 sce spray/50m3 | J97: Mosquito | 5 sce spray/50m3 | K97: 1
B98: 9 | C98: Azamethiphos | D98: 1 | E98: No-Kroach | F98: PHP-254 | G98: Green Bangla Agrovet Ltd. | H98: Cockroach | I98: 10 gm/m2 | J98: Cockroach | 10 gm/m2 | K98: 1
B99: 9 | C99: Azamethiphos | D99: 2 | E99: Akros 1 WDG | F99: PHP-779 | G99: Sun Seed Pesticide | H99: Cockroach | I99: 10 gm/m2 | J99: Cockroach | 10 gm/m2 | K99: 1
B100: 10 | C100: Chlorpyriphos | D100: 1 | E100: Limban 20 EC | F100: PHP-102 | G100: The Limit Agroproducts Limited | H100: Adult Mosquito & Larva | I100: 0.125 litre/ai/ha | J100: Adult Mosquito & Larva | 0.125 litre/ai/ha | K100: 1
B101: 10 | C101: Chlorpyriphos | D101: 2 | E101: M Fos 20EC | F101: PHP-939 | G101: M R Enterprise | H101: Mosquito | I101: 62.50 ml/ha | J101: Mosquito | 62.50 ml/ha | K101: 1
B102: 11 | C102: Pirimiphos methyl | D102: 1 | E102: Cleaner 50 EC | F102: PHP-175 | G102: ACI Formulations Limited | H102: Adult Mosquito & Larva | I102: 2 gm/m2 and 200 ml/ha | J102: Adult Mosquito & Larva | 2 gm/m2 and 200 ml/ha | K102: 1
B103: 11 | C103: Pirimiphos methyl | D103: 2 | E103: Ciyphos-S 50EC | F103: PHP-1039 | G103: Dhaka South City Corporation | H103: Adult Mosquito & Larva | I103: 2 gm/m2 and 200 ml/ha | J103: Adult Mosquito & Larva | 2 gm/m2 and 200 ml/ha | K103: 1
B104: 11 | C104: Pirimiphos methyl | D104: 3 | E104: Cityphos-N 50EC | F104: PHP-1041 | G104: Dhaka North City Corporation | H104: Adult Mosquito & Larva | I104: 2 gm/m2 and 200 ml/ha | J104: Adult Mosquito & Larva | 2 gm/m2 and 200 ml/ha | K104: 1
B105: 11 | C105: Pirimiphos methyl | D105: 4 | E105: City Fos-G 50% | F105: PHP-1091 | G105: Gazipur City Corporation | H105: Adult Mosquito | I105: 2 ml/m2 | J105: Adult Mosquito | 2 ml/m2 | K105: 1
B106: 12 | C106: Temiphos | D106: 1 | E106: Limbate 50 EC | F106: PHP-163 | G106: The Limit Agroproducts Limited | H106: Mosquito Larva | I106: 100 ml/ha | J106: Mosquito Larva | 100 ml/ha | K106: 1
... B382: 32 | C382: Permethrin, Tetramethrin, Es bioallethrin | D382: 3 | E382: Green Liquid Insecticide | F382: PHP-354 | G382: Green Care Bangladesh | H382: Adult Mosquito | I382: 6 ml/1000 cum2 | J382: Adult Mosquito | 6 ml/1000 cum2 | K382: 1
B383: 32 | C383: Permethrin, Tetramethrin, Es bioallethrin | D383: 4 | E383: Golder Aerosol | G383: S N Trade International | H383: Cockoroach, Adult Mosquito | I383: 20 Second spray/100m3 | J383: Cockoroach | 20 Second spray/100m3 Adult Mosquito | 20 Second spray/100m3 | K383: 2
B384: 32 | C384: Permethrin, Tetramethrin, Es bioallethrin | D384: 5 | E384: Fix Liquid Spray | F384: PHP-1098 | G384: Padma Agro Sprayers Co. Ltd. | H384: Adult Mosquito | I384: 6 ml/100m3 | J384: Adult Mosquito | 6 ml/100m3 | K384: 1
B385: 33 | C385: d-allethrin (0.30%) | D385: 1 | E385: Fighter King Mosquito Coil | F385: PHP-149 | G385: Supti Chemical Company | H385: Adult Mosquito | I385: 1.20 ml/m2 | J385: Adult Mosquito | 1.20 ml/m2 | K385: 1
B386: 33 | C386: d-allethrin (0.30%) | D386: 2 | E386: Mayakul Brand Mosquito Coil | F386: PHP-155 | G386: Belal Welcome Company | H386: Adult Mosquito | I386: 1.20 ml/m2 | J386: Adult Mosquito | 1.20 ml/m2 | K386: 1
B387: 33 | C387: d-allethrin (0.30%) | D387: 3 | E387: Eagle Super Mosquito Coil | F387: PHP-202 | G387: Quazi Enterprises Limited | H387: Adult Mosquito | I387: 1/2gm/63x63x73 cm2 | J387: Adult Mosquito | 1/2gm/63x63x73 cm2 | K387: 1
B388: 33 | C388: d-allethrin (0.30%) | D388: 4 | E388: Supreme Mosquito Coil | F388: PHP-203 | G388: M K International | H388: Adult Mosquito | I388: 1/2gm/63x63x73 cm2 | J388: Adult Mosquito | 1/2gm/63x63x73 cm2 | K388: 1
B389: 33 | C389: d-allethrin (0.30%) | D389: 5 | E389: A M Mosquito Coil | F389: PHP-216 | G389: S A Formulation Ltd. | H389: Adult Mosquito | I389: 1/2gm/63x63x73 cm2 | J389: Adult Mosquito | 1/2gm/63x63x73 cm2 | K389: 1
B390: 33 | C390: d-allethrin (0.30%) | D390: 6 | E390: K-2 Mosquito Coil | F390: PHP-220 | G390: J. H. Chemical Co. | H390: Adult Mosquito | I390: 1/2gm/63x63x73 cm2 | J390: Adult Mosquito | 1/2gm/63x63x73 cm2 | K390: 1
B391: 33 | C391: d-allethrin (0.30%) | D391: 7 | E391: 555 Brand Mosquito Coil | F391: PHP-227 | G391: S. S. Chemical Works | H391: Adult Mosquito | I391: 1/2gm/63x63x73 cm2 | J391: Adult Mosquito | 1/2gm/63x63x73 cm2 | K391: 1
B392: 33 | C392: d-allethrin (0.30%) | D392: 8 | E392: Nice Brand Mosquito Coil | F392: PHP-259 | G392: Salim Enterprise | H392: Adult Mosquito | I392: 63x63x73 cm2 | J392: Adult Mosquito | 63x63x73 cm2 | K392: 1
B393: 33 | C393: d-allethrin (0.30%) | D393: 9 | E393: Super Fighter King Coil | F393: PHP-260 | G393: Supti Chemical Company | H393: Adult Mosquito | I393: 63x63x73 cm2 | J393: Adult Mosquito | 63x63x73 cm2 | K393: 1
B394: 33 | C394: d-allethrin (0.30%) | D394: 10 | E394: R.M. Mosquito Coil | F394: PHP-262 | G394: R.M. Chemical Industry | H394: Adult Mosquito | I394: 63x63x73 cm2 | J394: Adult Mosquito | 63x63x73 cm2 | K394: 1
B395: 33 | C395: d-allethrin (0.30%) | D395: 11 | E395: ARS Brand High Power Frannent | F395: PHP-263 | G395: Globe Insecticides Limited | H395: Adult Mosquito | I395: 63x63x73 cm2 | J395: Adult Mosquito | 63x63x73 cm2 | K395: 1
... B555: 49 | C555: Permethrin+S-bioallethrin+prallethrin | D555: 2 | E555: Energy Mosquito Insecticide | F555: PHP-766 | G555: Agrivision International Ltd. | H555: Mosquito | I555: 12ft2 (500 ml/ha); 15X15X12/10 second/20 min | J555: Mosquito | 12ft2 (500 ml/ha) Mosquito | 15X15X12/10 second/20 min | K555: 2
B556: 50 | C556: (d-tetramethrin +d-d-T Cyphenothrin) | D556: 1 | E556: Mosfly Cik Aerosol | F556: PHP-419 | G556: RAK Mosfly (Bangladesh) Pvt. Ltd | K556: 0
B557: 51 | C557: Meperfluthrin | D557: 1 | E557: Astro Herbal Brand Mosquito Coil | F557: PHP-552 | G557: Ashad Enterprise | H557: Mosquito | I557: 63x63x73 cm2 | J557: Mosquito | 63x63x73 cm2 | K557: 1
B558: 51 | C558: Meperfluthrin | D558: 2 | E558: M. Rose Plant Fiber Mosquito Coil | F558: PHP-616 | G558: Green Leaves International | H558: Mosquito | I558: 63x63x73 cm2 | J558: Mosquito | 63x63x73 cm2 | K558: 1
B559: 51 | C559: Meperfluthrin | D559: 3 | E559: Gecko osquito Coil | F559: PHP-625 | G559: M. R. Khan Associates Company | H559: Mosquito | I559: 63x63x73 cm2 | J559: Mosquito | 63x63x73 cm2 | K559: 1
B560: 51 | C560: Meperfluthrin | D560: 4 | E560: Eagle Max Hit Jumboo Mosquito Coil | F560: PHP-717 | G560: Quazi Enterprises Limited | H560: Mosquito | I560: 63x63x73 cm2 | J560: Mosquito | 63x63x73 cm2 | K560: 1
B561: 51 | C561: Meperfluthrin | D561: 5 | E561: DF Artillery Plant Fibre Mosquito Coil | F561: PHP-792 | G561: Dewan Trading | H561: Mosquito | I561: 63x63x73 cm2 | J561: Mosquito | 63x63x73 cm2 | K561: 1
B562: 51 | C562: Meperfluthrin | D562: 6 | E562: DF Artilllery 1 Mosquito Coil | F562: PHP-794 | G562: Dewan Trading | H562: Mosquito | I562: 63x63x73 cm2 | J562: Mosquito | 63x63x73 cm2 | K562: 1
B563: 51 | C563: Meperfluthrin | D563: 7 | E563: Extra Power King Mosquito Coil | F563: PHP-808 | G563: P T Consumer Products Industries | H563: Mosquito | I563: 63x63x73 cm2 | J563: Mosquito | 63x63x73 cm2 | K563: 1
B564: 51 | C564: Meperfluthrin | D564: 8 | E564: Banglar Raja Mosquito Coil | F564: PHP-811 | G564: Arif Enterprise | H564: Mosquito | I564: 63x63x73 cm2 | J564: Mosquito | 63x63x73 cm2 | K564: 1
B565: 51 | C565: Meperfluthrin | D565: 9 | E565: Golden Lion Mosquito Coil | F565: PHP-815 | G565: Goldenkey Agribusiness Co. Ltd. | H565: Mosquito | I565: 63x63x73 cm2 | J565: Mosquito | 63x63x73 cm2 | K565: 1
B566: 51 | C566: Meperfluthrin | D566: 10 | E566: Danger Gold Mosquito Coil | F566: PHP-828 | G566: Unison Trading Co. | H566: Mosquito | I566: 63x63x73 cm2 | J566: Mosquito | 63x63x73 cm2 | K566: 1
B567: 51 | C567: Meperfluthrin | D567: 11 | E567: Sprarrow Mosquito Coil | F567: PHP-849 | G567: Maruf Enterprise | H567: Mosquito | I567: 63x63x73 cm2 | J567: Mosquito | 63x63x73 cm2 | K567: 1
B568: 51 | C568: Meperfluthrin | D568: 12 | E568: Egale Super Booster Mosquito Coil | F568: PHP-871 | G568: Quazi Enterprises Limited | H568: Mosquito | I568: 63x63x73 cm2 | J568: Mosquito | 63x63x73 cm2 | K568: 1
... B622: 52 | C622: Dimefluthrin 0.25% | D622: 46 | E622: Saba Mosquito Coil | F622: PHP-906 | G622: Saba Trade & Associates | H622: Mosquito | I622: 63x63x73 cm2 | J622: Mosquito | 63x63x73 cm2 | K622: 1
C623: (0.02%) -0.03 (0.05%) | D623: 47 | E623: Black Panther Super Mosquito Coil | F623: PHP-908 | G623: Hussain Trading Company Ltd. | H623: Mosquito | I623: 63x63x73 cm2 | J623: Mosquito | 63x63x73 cm2 | K623: 1
C624: (0.02%) -0.03 (0.05%) | D624: 48 | E624: Lizard Mega Mosquito Coil | F624: PHP-909 | G624: Sheuly Chemical Works | H624: Mosquito | I624: 63x63x73 cm2 | J624: Mosquito | 63x63x73 cm2 | K624: 1
C625: (0.02%) -0.03 (0.05%) | D625: 49 | E625: B P Super Power Mosquito Coil | F625: PHP-920 | G625: B P Internationa | H625: Mosquito | I625: 63x63x73 cm2 | J625: Mosquito | 63x63x73 cm2 | K625: 1
C626: (0.02%) -0.03 (0.05%) | D626: 50 | E626: Hisense Mosquito Coil | F626: PHP-928 | G626: S Nahar Consumer Products | H626: Mosquito | I626: 63x63x73 cm2 | J626: Mosquito | 63x63x73 cm2 | K626: 1
C627: (0.02%) -0.03 (0.05%) | D627: 51 | E627: Techno Mosquito Coil | F627: PHP-932 | G627: Techno Enterprise | H627: Mosquito | I627: 63x63x73 cm2 | J627: Mosquito | 63x63x73 cm2 | K627: 1
C628: (0.02%) -0.03 (0.05%) | D628: 52 | E628: Godzila Mosquito Coil | F628: PHP-933 | G628: Agromine Pvt. Ltd. | H628: Mosquito | I628: 63x63x73 cm2 | J628: Mosquito | 63x63x73 cm2 | K628: 1
C629: (0.02%) -0.03 (0.05%) | D629: 53 | E629: Joom Power Mosquito Coil | F629: PHP-935 | G629: Sun Basic Chemicals Ltd. | H629: Mosquito | I629: 63x63x73 cm2 | J629: Mosquito | 63x63x73 cm2 | K629: 1
C630: (0.02%) -0.03 (0.05%) | D630: 54 | E630: VIP Mosquito Coil | F630: PHP-936 | G630: Habib Chemical Works | H630: Mosquito | I630: 63x63x73 cm2 | J630: Mosquito | 63x63x73 cm2 | K630: 1
C631: (0.02%) -0.03 (0.05%) | D631: 55 | E631: Good Kinght Octa Guard Mosquito Coil | F631: PHP-938 | G631: Godrej Household Products (BD) Pvt. Ltd. | H631: Mosquito | I631: 63x63x73 cm2 | J631: Mosquito | 63x63x73 cm2 | K631: 1
...

Sheet Review
B2: Review — Extraction Integrity Checks
B4: Check | C4: Expected (from parse) | D4: Actual (live formulas) | E4: Status
B5: Total registered products | C5: 5452 | D5: =Summary!D17 -> 5452 | E5: =IF(C5=D5,"PASS","FAIL") -> PASS
B6: Miticide — products | C6: 205 | D6: =Summary!D9 -> 205 | E6: =IF(C6=D6,"PASS","FAIL") -> PASS
B7: Fungicide — products | C7: 1052 | D7: =Summary!D10 -> 1052 | E7: =IF(C7=D7,"PASS","FAIL") -> PASS
B8: Insecticide — products | C8: 2500 | D8: =Summary!D11 -> 2500 | E8: =IF(C8=D8,"PASS","FAIL") -> PASS
B9: Herbicide — products | C9: 892 | D9: =Summary!D12 -> 892 | E9: =IF(C9=D9,"PASS","FAIL") -> PASS
B10: Store Grain Insecticide — products | C10: 88 | D10: =Summary!D13 -> 88 | E10: =IF(C10=D10,"PASS","FAIL") -> PASS
B11: Rodenticide — products | C11: 15 | D11: =Summary!D14 -> 15 | E11: =IF(C11=D11,"PASS","FAIL") -> PASS
B12: Bio Pesticide — products | C12: 35 | D12: =Summary!D15 -> 35 | E12: =IF(C12=D12,"PASS","FAIL") -> PASS
B13: Public Health — products | C13: 665 | D13: =Summary!D16 -> 665 | E13: =IF(C13=D13,"PASS","FAIL") -> PASS
B14: Total recommendations | C14: 7250 | D14: =Summary!E17 -> 7250 | E14: =IF(C14=D14,"PASS","FAIL") -> PASS
B15: Unique common names | C15: 441 | D15: =Summary!C17 -> 441 | E15: =IF(C15=D15,"PASS","FAIL") -> PASS
B17: Expected values are counted from the parsed records; actual values are live COUNTA/SUM formulas over the data sheets. All rows must show PASS.
